Workbook

Sheet 01_Organigrama_y_Roles
B4: PLANIFICACIÓN Y CONTROL DE OBRAS · ES3
B6: SEDE SOCIAL EL BOSQUE
B11: Programa, costos y control de ejecución
B14: PLAZO PLANIFICADO | D14: 150 días corridos
B15: INICIO PROGRAMADO | D15: 02 de noviembre de 2026
B16: ALCANCE | D16: Construcción de sede social
B18: DOCENTE | D18: Francisca Pizarro Oliveros
B20: INTEGRANTES · GRUPO 4
B21: Mario Pinto
B22: Gerardo Pavez
B23: Tomas Correa
B24: Eliasin Roman
A31: PASO 1 · ORGANIGRAMA DE PROYECTO · ES3 IND. 1
B132: MATRIZ DE ROLES Y RESPONSABILIDADES · ES3 IND. 1
B135: ES3 - IND. 1 | MATRIZ DE ROLES Y RESPONSABILIDADES
B137: Construcción Sede Social El Bosque | Andacollo | Matriz concordante con el organigrama
B138: Los KPI indicados son indicadores de seguimiento de gestión; deben ajustarse al contrato, programa y procedimientos aprobados.
B140: Cargo | C140: Dependencia directa | D140: Funciones principales | E140: Entregables / KPI bajo su responsabilidad
B141: Mandante / Propietario | C141: Ilustre Municipalidad de Andacollo | D141: Define el objetivo y necesidades del proyecto; dispone del contrato; valida decisiones que afecten alcance, plazo o costo; participa en definiciones formales. | E141: Contrato y decisiones formales; aprobaciones del mandante; cumplimiento del objetivo; trazabilidad de cambios autorizados.
B142: Inspección Técnica de Obra (ITO) | C142: Mandante / Municipalidad (Control externo) | D142: Inspecciona ejecución, avance y calidad; revisa materiales y partidas; formula observaciones; resuelve consultas por encargo del municipio; otorga V°B° antes de continuar partidas. | E142: Actas y registros de inspección; % partidas con V°B°; observaciones abiertas/cerradas; tiempos de respuesta; recepción de partidas.
B143: Dirección de Obra / Contratista | C143: Mandante e ITO (Relación contractual) | D143: Lidera la ejecución integral; asegura cumplimiento de EE.TT., planos y normativa; dispone recursos; coordina proyectistas, ITO y equipos; responde por discrepancias y resultados. | E143: Plan de ejecución; cumplimiento de hitos; desviación de costo/plazo; respuestas a discrepancias; recepción provisoria y cierre contractual.
B144: Administrador de Obra | C144: Dirección de Obra / Contratista | D144: Administra contrato, programa, costos, adquisiciones y coordinación general; mantiene relación operativa con ITO; consolida reportes y decisiones de obra. | E144: Informe semanal; avance físico-financiero; control de cambios; curva S; compromisos con ITO; RFI críticos; forecast de costo/plazo.
B145: Jefe de Terreno | C145: Administrador de Obra | D145: Planifica producción diaria y semanal; coordina frentes, cuadrillas, equipos, materiales y restricciones; verifica secuencia y liberación de actividades. | E145: Lookahead 3-6 semanas; partes diarios; % cumplimiento plan semanal; productividad; restricciones levantadas; avance por frente.
B146: Jefe Oficina Técnica / Coordinador BIM | C146: Administrador de Obra | D146: Coordina arquitectura, estructura y especialidades; administra planos y revisiones; gestiona RFI, submittals, interferencias, información BIM y antecedentes conforme a obra. | E146: Matriz RFI; planos vigentes; reportes de interferencias; submittals aprobados; control de revisiones; modelo/planos as-built; % documentos en plazo.
B147: Encargado de Calidad PAC | C147: Administrador de Obra (Funcional con ITO) | D147: Implementa PAC/ITP; controla inspecciones y ensayos; verifica certificados, trazabilidad y criterios de aceptación; gestiona no conformidades y liberación de partidas. | E147: PAC e ITP; checklists; protocolos; certificados; registros de trazabilidad; % primera pasada; NCR abiertas/cerradas; V°B° de calidad.
B148: Encargado SSOMA | C148: Administrador de Obra | D148: Gestiona seguridad, salud ocupacional y medio ambiente; aplica Ley 16.744, D.S. 594 y controles preventivos; coordina inducciones, permisos, EPP, señalización y emergencias. | E148: Matriz de riesgos; inducciones; AST/charlas; inspecciones; permisos de trabajo; tasa de incidentes; cumplimiento de capacitaciones; acciones correctivas cerradas.
B149: Bodeguero | C149: Jefe de Terreno / Administrador de Obra | D149: Recibe y verifica materiales; controla almacenamiento, inventario, orden, protección y entrega; mantiene trazabilidad y comunica quiebres o daños. | E149: Kardex / inventario; recepción conforme; exactitud de stock; entregas oportunas; materiales protegidos; pérdidas y daños controlados.
B150: Capataz Obra Gruesa | C150: Jefe de Terreno | D150: Conduce cuadrillas y ejecuta fundaciones, radier, estructura y demás partidas de obra gruesa conforme a planos, secuencia, calidad y seguridad. | E150: Avance por frente; checklists; productividad; horas-hombre; controles previos; retrabajos; observaciones PAC/SSOMA cerradas.
B151: Capataz Terminaciones | C151: Jefe de Terreno | D151: Conduce revestimientos, pavimentos, pinturas, cielos, artefactos, remates y limpieza; coordina liberación de recintos con calidad y especialidades. | E151: Avance de terminaciones; punch list; % recepción primera vez; retrabajos; recintos liberados; observaciones de ITO cerradas.
B152: Personal de terreno y subcontratos | C152: Jefe de Terreno / Capataz correspondiente | D152: Ejecutan las actividades asignadas conforme a instrucciones, planos vigentes, procedimientos de trabajo, controles de calidad y medidas SSOMA. | E152: Producción diaria; asistencia y rendimiento; cumplimiento de procedimientos; incidentes; no conformidades; avances y registros de ejecución.
B154: Base documental: 7-EE.TT_SEDE_EL_BOSQUE.pdf - Especificaciones Técnicas “Construcción Sede Social El Bosque, Comuna Andacollo”, agosto 2025. Apartados considerados: 0.1 Generalidades; 0.2 Productos y materiales; 0.3 Obligaciones del contratista; 0.4 Ubicación; 0.5 Propietario; 0.6 Marco normativo; A.1 Instalación de faenas; B.1 Obra gruesa; B.2 Terminaciones.

Sheet 02_Rendimientos
A1: PASO 2 · RENDIMIENTOS POR CUADRILLA Y TIEMPOS · ES3 IND. 2
A2: Construcción Sede Social El Bosque | Andacollo | Plazo contractual mínimo: 150 días corridos
A3: La duración planificada utiliza frentes de trabajo paralelos. La ponderación orienta el programa, pero la secuencia CPM determina las fechas de inicio y término.
A5: Ítem | B5: Macro-etapa | C5: Partida | D5: Cantidad referencial | E5: Unidad | F5: Cuadrilla tipo | G5: Rendimiento diario | H5: N° cuadrillas | I5: Duración base | J5: Ponderación objetivo | K5: Duración planificada (días)
A6: 1 | B6: Instalación de faenas | C6: Instalación de faenas y cierre perimetral | D6: 1 | E6: lote | F6: 1 Maestro + 2 Ayudantes | G6: 1 | H6: 1 | I6: =D6/(G6*H6) -> 1 | J6: 0.08 | K6: 6
A7: 2 | B7: Instalación de faenas | C7: Replanteo y nivelación del área de trabajo | D7: 180 | E7: m2 | F7: 1 Topógrafo + 1 Ayudante | G7: 180 | H7: 1 | I7: =D7/(G7*H7) -> 1 | J7: 0.08 | K7: 5
A8: 3 | B8: Instalación de faenas | C8: Servicios provisorios y habilitación de instalaciones | D8: 1 | E8: lote | F8: 1 Maestro + 1 Ayudante | G8: 0.5 | H8: 1 | I8: =D8/(G8*H8) -> 2 | J8: 0.08 | K8: 10
A9: 4 | B9: Obra Gruesa | C9: Excavación y retiro de material | D9: 45 | E9: m3 | F9: 1 Operador + 2 Ayudantes | G9: 15 | H9: 1 | I9: =D9/(G9*H9) -> 3 | J9: 0.38 | K9: 11
A10: 5 | B10: Obra Gruesa | C10: Relleno, humectación y compactación | D10: 35 | E10: m3 | F10: 1 Maestro + 2 Ayudantes | G10: 12 | H10: 1 | I10: =D10/(G10*H10) -> 2.9166667 | J10: 0.38 | K10: 9
A11: 6 | B11: Obra Gruesa | C11: Emplantillado de hormigón | D11: 12 | E11: m3 | F11: 1 Maestro + 2 Ayudantes | G11: 4 | H11: 1 | I11: =D11/(G11*H11) -> 3 | J11: 0.38 | K11: 5
A12: 7 | B12: Obra Gruesa | C12: Fundaciones de hormigón armado | D12: 28 | E12: m3 | F12: 1 Maestro + 3 Ayudantes | G12: 7 | H12: 1 | I12: =D12/(G12*H12) -> 4 | J12: 0.38 | K12: 13
A13: 8 | B13: Obra Gruesa | C13: Radier y losas de hormigón | D13: 95 | E13: m2 | F13: 1 Maestro + 3 Ayudantes | G13: 28 | H13: 1 | I13: =D13/(G13*H13) -> 3.3928571 | J13: 0.38 | K13: 12
A14: 9 | B14: Obra Gruesa | C14: Estructura metálica y viga reticulada | D14: 2800 | E14: kg | F14: 1 Soldador + 2 Ayudantes | G14: 350 | H14: 1 | I14: =D14/(G14*H14) -> 8 | J14: 0.38 | K14: 20
A15: 10 | B15: Obra Gruesa | C15: Cubierta y hojalatería | D15: 190 | E15: m2 | F15: 1 Maestro + 2 Ayudantes | G15: 45 | H15: 1 | I15: =D15/(G15*H15) -> 4.2222222 | J15: 0.38 | K15: 12
A16: 11 | B16: Obra Gruesa | C16: Muros y tabiques Metalcon | D16: 360 | E16: m2 | F16: 1 Maestro + 2 Ayudantes | G16: 45 | H16: 2 | I16: =D16/(G16*H16) -> 4 | J16: 0.38 | K16: 18
A17: 12 | B17: Instalaciones | C17: Instalación eléctrica interior | D17: 1 | E17: lote | F17: 1 Técnico Eléctrico + 1 Ayudante | G17: 0.25 | H17: 1 | I17: =D17/(G17*H17) -> 4 | J17: 0.22 | K17: 14
... A27: 22 | B27: Terminaciones | C27: Limpieza, remates y entrega | D27: 1 | E27: lote | F27: 1 Maestro + 2 Ayudantes | G27: 0.5 | H27: 1 | I27: =D27/(G27*H27) -> 2 | J27: 0.32 | K27: 7
A30: CONTROL DE PLAZO
A31: Macro-etapa | B31: Ponderación objetivo | C31: Días de referencia | D31: Criterio de programación | F31: Criterio adoptado: el programa determinístico queda en 150 días corridos, cumpliendo el mínimo contractual de 150 días. Las tareas C, H, K, M, N, O, P, S y U se organizan como ramas paralelas o convergentes para representar una obra ejecutable con varios frentes. Las cantidades y rendimientos son de planificación y deben validarse contra planos, presupuesto, EE.TT. y recursos reales.
A32: Instalación de faenas | B32: =J6 -> 0.08 | C32: =B32*'02_Rendimientos'!$B$80 -> 12 | D32: Habilitación inicial y logística
A33: Obra Gruesa | B33: =J9 -> 0.38 | C33: =B33*'02_Rendimientos'!$B$80 -> 57 | D33: Estructura, hormigones, muros y cubierta
A34: Instalaciones | B34: =J17 -> 0.22 | C34: =B34*'02_Rendimientos'!$B$80 -> 33 | D34: Redes eléctricas, sanitarias, pruebas y conexiones
A35: Terminaciones | B35: =J22 -> 0.32 | C35: =B35*'02_Rendimientos'!$B$80 -> 48 | D35: Revestimientos, pavimentos, pintura y cierre
A36: Las ponderaciones son las adoptadas en esta planificación, no una transcripción acreditada de los porcentajes de clase. Los días de referencia suman 150; las etapas se superponen en CPM, por eso no se suman sus duraciones de ejecución.
A39: Duración base: jornadas productivas según cantidad y cuadrilla. Duración planificada: días corridos con esperas y coordinación. La cubicación contractual de las 140 partidas figura en el Paso 6.
A42: Act. | B42: Paquete del programa | C42: Jornadas base | D42: Días corridos | E42: Días a 5/7 | F42: Diferencia no productiva | G42: Interpretación
A43: A | B43: =C6 -> Instalación de faenas y cierre perimetral | C43: =I6 -> 1 | D43: =K6 -> 6 | E43: =D43*5/7 -> 4.2857143 | F43: =E43-C43 -> 3.2857143 | G43: Esperas y coordinación previstas. Validar en terreno.
A44: B | B44: =C7 -> Replanteo y nivelación del área de trabajo | C44: =I7 -> 1 | D44: =K7 -> 5 | E44: =D44*5/7 -> 3.5714286 | F44: =E44-C44 -> 2.5714286 | G44: Esperas y coordinación previstas. Validar en terreno.
A45: C | B45: =C8 -> Servicios provisorios y habilitación de instalaciones | C45: =I8 -> 2 | D45: =K8 -> 10 | E45: =D45*5/7 -> 7.1428571 | F45: =E45-C45 -> 5.1428571 | G45: Esperas y coordinación previstas. Validar en terreno.
A46: D | B46: =C9 -> Excavación y retiro de material | C46: =I9 -> 3 | D46: =K9 -> 11 | E46: =D46*5/7 -> 7.8571429 | F46: =E46-C46 -> 4.8571429 | G46: Esperas y coordinación previstas. Validar en terreno.
A47: E | B47: =C10 -> Relleno, humectación y compactación | C47: =I10 -> 2.9166667 | D47: =K10 -> 9 | E47: =D47*5/7 -> 6.4285714 | F47: =E47-C47 -> 3.5119048 | G47: Esperas y coordinación previstas. Validar en terreno.
A48: F | B48: =C11 -> Emplantillado de hormigón | C48: =I11 -> 3 | D48: =K11 -> 5 | E48: =D48*5/7 -> 3.5714286 | F48: =E48-C48 -> 0.57142857 | G48: Esperas y coordinación previstas. Validar en terreno.
A49: G | B49: =C12 -> Fundaciones de hormigón armado | C49: =I12 -> 4 | D49: =K12 -> 13 | E49: =D49*5/7 -> 9.2857143 | F49: =E49-C49 -> 5.2857143 | G49: Esperas y coordinación previstas. Validar en terreno.
A50: H | B50: =C13 -> Radier y losas de hormigón | C50: =I13 -> 3.3928571 | D50: =K13 -> 12 | E50: =D50*5/7 -> 8.5714286 | F50: =E50-C50 -> 5.1785714 | G50: Esperas y coordinación previstas. Validar en terreno.
A51: I | B51: =C14 -> Estructura metálica y viga reticulada | C51: =I14 -> 8 | D51: =K14 -> 20 | E51: =D51*5/7 -> 14.285714 | F51: =E51-C51 -> 6.2857143 | G51: Esperas y coordinación previstas. Validar en terreno.
A52: J | B52: =C15 -> Cubierta y hojalatería | C52: =I15 -> 4.2222222 | D52: =K15 -> 12 | E52: =D52*5/7 -> 8.5714286 | F52: =E52-C52 -> 4.3492063 | G52: Esperas y coordinación previstas. Validar en terreno.
A53: K | B53: =C16 -> Muros y tabiques Metalcon | C53: =I16 -> 4 | D53: =K16 -> 18 | E53: =D53*5/7 -> 12.857143 | F53: =E53-C53 -> 8.8571429 | G53: Esperas y coordinación previstas. Validar en terreno.
A54: L | B54: =C17 -> Instalación eléctrica interior | C54: =I17 -> 4 | D54: =K17 -> 14 | E54: =D54*5/7 -> 10 | F54: =E54-C54 -> 6 | G54: Esperas y coordinación previstas. Validar en terreno.
... A64: V | B64: =C27 -> Limpieza, remates y entrega | C64: =I27 -> 2 | D64: =K27 -> 7 | E64: =D64*5/7 -> 5 | F64: =E64-C64 -> 3 | G64: Esperas y coordinación previstas. Validar en terreno.
A72: PARÁMETROS Y SUPUESTOS DE CÁLCULO · ANEXO DEL PASO 2
A75: ANEXO · PARÁMETROS, FUENTES Y SUPUESTOS DEL ES3
A78: Variable | B78: Valor | C78: Unidad | D78: Criterio / fuente | E78: Estado | F78: Observación
A79: Inicio del programa | B79: 46328 | C79: fecha | D79: Usuario: 02-11-2026 | E79: Definido | F79: El inicio contractual corresponde al acta de entrega de terreno.
A80: Plazo mínimo | B80: 150 | C80: días corridos | D80: BAE, numeral 1.7, PDF pág. 6 | E80: Documentado | F80: No equivale a un plazo máximo.
A81: Presupuesto municipal | B81: 114446607 | C81: CLP con IVA | D81: BAE, numeral 1.6, PDF pág. 6 | E81: Documentado | F81: Techo económico de la oferta.
A82: IVA | B82: 0.19 | C82: % | D82: Guía paso 6 y BAE PDF pág. 17 | E82: Documentado | F82: Los costos de control se comparan sin IVA.
A83: Gastos generales | B83: 0.15 | C83: % CD | D83: Itemizado municipal: GG 15% | E83: Referencia | F83: Se conserva la tasa del formulario.
A84: Utilidad ofertada | B84: 0.1 | C84: % CD | D84: Utilidad propuesta para la oferta: 10% | E84: Estimado | F84: Se reduce respecto al 15% del formulario municipal.
A85: Utilidad del formulario | B85: 0.15 | C85: % CD | D85: Itemizado municipal: utilidad 15% | E85: Referencia | F85: Sirve para comparar el precio con igual costo directo.
A86: Retención de garantía | B86: 0.05 | C86: % neto EEPP | D86: Criterio financiero de planificación: 5% | E86: Criterio de planificación | F86: Tasa aplicada para proyectar estados de pago; ajustar a la garantía del contrato suscrito.
A87: Anticipo | B87: 0 | C87: % neto | D87: Sin anticipo en el escenario base | E87: Supuesto | F87: Devolución proporcional si se activa.
A88: Cobro después de conformidad | B88: 30 | C88: días hábiles | D88: BAE, numeral 55, PDF pág. 65 | E88: Documentado | F88: Calendario hábil simplificado lunes a viernes más feriados listados.
A89: Recepción conforme tras presentación | B89: 5 | C89: días hábiles | D89: Supuesto de revisión ITO | E89: Estimado | F89: No es un plazo contractual acreditado.
A90: Reserva mínima último EEPP | B90: 0.1 | C90: % contrato | D90: BAE, numeral 54, PDF pág. 64 | E90: Documentado | F90: Se limita facturación parcial acumulada al 90%.
... A100: Retraso devolución retención | B100: 180 | C100: días corridos | D100: Supuesto financiero | E100: Criterio de planificación | F100: Plazo adoptado para proyectar la devolución de la garantía.
A102: Fuentes: Guía paso a paso (págs. 1-4); 5-PPTO..xlsx (140 partidas, cantidades y GG/utilidad); BAE numerales 1.6, 1.7, 54 y 55. Precios de oferta referenciales, no cotizaciones vinculantes.
A104: Referencia comercial | B104: Precio observado | C104: Unidad | D104: Tratamiento | E104: Consulta | F104: Enlace
A105: Perfil C 60x20x0,85 de 2,4 m | B105: 3290 | C105: CLP/un con IVA | D105: Referencia de material, no sistema instalado | E105: 22-09-2026 | F105: https://www.sodimac.cl/sodimac-cl/lista/CATG10931/Perfiles-Metalcon
A106: Yeso cartón RH 12,5 mm 1,20x2,40 | B106: 14964 | C106: CLP/plancha | D106: Precio mayorista publicado; referencia | E106: 22-09-2026 | F106: https://www.sodimac.cl/sodimac-cl/b/volcanita-rh-12-5
A107: OSB 11,1 mm 1,22x2,44 | C107: CLP/plancha | D107: Especificación; precio depende de tienda | E107: 22-09-2026 | F107: https://www.sodimac.cl/sodimac-cl/articulo/110291060/Tablero-OSB-11.1-mm-122x244-cm?exp=so_com
A109: Los P.U. instalados incorporan provisión, flete local, mano de obra, equipos y merma estimada. Se convierten a neto antes de sumar GG, utilidad e IVA; no duplicar suministro y colocación cuando el itemizado los separa.
A111: Feriado calendario de cobro | B111: Fecha | C111: Tipo | D111: Uso | E111: Estado | F111: Fuente / alcance
A112: Feriado considerado | B112: 46364 | C112: Calendario modelo | D112: Cálculo de cobro | E112: Revisar | F112: Agregar feriados extraordinarios si corresponde
A113: Feriado considerado | B113: 46381 | C113: Calendario modelo | D113: Cálculo de cobro | E113: Revisar | F113: Agregar feriados extraordinarios si corresponde
A114: Feriado considerado | B114: 46388 | C114: Calendario modelo | D114: Cálculo de cobro | E114: Revisar | F114: Agregar feriados extraordinarios si corresponde
A115: Feriado considerado | B115: 46472 | C115: Calendario modelo | D115: Cálculo de cobro | E115: Revisar | F115: Agregar feriados extraordinarios si corresponde
A116: Feriado considerado | B116: 46473 | C116: Calendario modelo | D116: Cálculo de cobro | E116: Revisar | F116: Agregar feriados extraordinarios si corresponde
A117: Feriado considerado | B117: 46508 | C117: Calendario modelo | D117: Cálculo de cobro | E117: Revisar | F117: Agregar feriados extraordinarios si corresponde
A118: Feriado considerado | B118: 46528 | C118: Calendario modelo | D118: Cálculo de cobro | E118: Revisar | F118: Agregar feriados extraordinarios si corresponde
A119: Feriado considerado | B119: 46559 | C119: Calendario modelo | D119: Cálculo de cobro | E119: Revisar | F119: Agregar feriados extraordinarios si corresponde
A120: Feriado considerado | B120: 46566 | C120: Calendario modelo | D120: Cálculo de cobro | E120: Revisar | F120: Agregar feriados extraordinarios si corresponde
A121: Feriado considerado | B121: 46584 | C121: Calendario modelo | D121: Cálculo de cobro | E121: Revisar | F121: Agregar feriados extraordinarios si corresponde
A122: Feriado considerado | B122: 46614 | C122: Calendario modelo | D122: Cálculo de cobro | E122: Revisar | F122: Agregar feriados extraordinarios si corresponde
A123: Feriado considerado | B123: 46648 | C123: Calendario modelo | D123: Cálculo de cobro | E123: Revisar | F123: Agregar feriados extraordinarios si corresponde
A124: Feriado considerado | B124: 46649 | C124: Calendario modelo | D124: Cálculo de cobro | E124: Revisar | F124: Agregar feriados extraordinarios si corresponde
A127: COBERTURA DE LA GUÍA HASTA EL PASO 12
A128: Paso | B128: Indicador ES3 | C128: Hoja | D128: Contenido incorporado | E128: Estado | F128: Dato pendiente de validación
A129: 1 | B129: 1 | C129: 01 / 02 | D129: Organigrama y roles | E129: Conservado
A130: 2 | B130: 2 | C130: 03 | D130: Cuadrillas, cálculo y relación de duraciones | E130: Desarrollado | F130: Ponderaciones de programa y cubicaciones de producción
A131: 3 | B131: 3 | C131: 04 | D131: Tabla completa y red específica obra gruesa | E131: Desarrollado | F131: Liberaciones y recursos de terreno
A132: 4 | B132: 4 | C132: 06 | D132: PERT completo y sector terminaciones | E132: Desarrollado | F132: Tres tiempos estimados, no muestra estadística
A133: 5 | B133: 5 | C133: 05 | D133: Gantt completo con barras condicionales | E133: Desarrollado | F133: Acta real de entrega de terreno
A134: 6 | B134: 6 | C134: 07 | D134: 140 partidas, GG, utilidad, IVA y oferta inferior | E134: Desarrollado | F134: Cotizaciones y cubicación corroborada
A135: 7 | B135: 7-8 | C135: 08 | D135: Curvas S físicas y financieras con tablas | E135: Desarrollado | F135: Avance real no suministrado
A136: 8 | B136: 9 | C136: 09 | D136: Flujo mensual, cobros, pagos y capital | E136: Desarrollado | F136: Fechas de conformidad/decreto y retención
A137: 9 | B137: 10 | C137: 10 | D137: Compromisos diarios primeras dos semanas | E137: Desarrollado | F137: Liberar restricciones antes de ejecutar
A138: 10 | B138: 11 | C138: 11 | D138: EEPP obra gruesa: cantidad, valorización y liquidación | E138: Proyectado | F138: Mediciones certificadas
A139: 11 | B139: 12 | C139: 12 | D139: Nueve eventos externos, valoración y responsables | E139: Desarrollado | F139: Evaluación inicial con equipo de obra
A140: 12 | B140: 13 | C140: 13 | D140: PP, CR, VG, VC, IRC y alertas | E140: Simulación | F140: Registrar avances aprobados y costos incurridos al cierre

Sheet 03_CPM_Obra_Gruesa
A2: CPM DE OBRA GRUESA - ES3 IND. 3
A3: CPM sectorial: 8 paquetes de programación asociados a 26 partidas presupuestarias de obra gruesa. La correspondencia por partida se presenta desde la fila 103.
A5: Red sectorial autónoma: día 0 local, 70.00 días. Entradas externas D depende de B se conservan en la red total, no en esta subred. No sumar su duración al plazo total.
A7: Lectura: arriba IT (inicio temprano) / FT (término temprano); abajo ITa (inicio tardío) / FTa (término tardío). Rojo: ruta crítica. Azul: actividades con holgura.
A40: TABLA SECTORIAL - RUTA CRÍTICA D → E → F → G → I → J
A41: Nodo | B41: EDT | C41: Partida / paquete | D41: Predecesoras locales | E41: Duración (d) | F41: IT | G41: FT | H41: ITa | I41: FTa | J41: HT | K41: HL | L41: Crítica
A42: ='03_CPM_Obra_Gruesa'!A148 -> D | B42: ='03_CPM_Obra_Gruesa'!B148 -> 2.1 | C42: ='03_CPM_Obra_Gruesa'!D148 -> Excavación y retiro de material | D42: — | E42: ='03_CPM_Obra_Gruesa'!E148 -> 11 | F42: =0 -> 0 | G42: =F42+E42 -> 11 | H42: =I42-E42 -> 0 | I42: =MIN(H43) -> 11 | J42: =H42-F42 -> 0 | K42: =MIN(F43)-G42 -> 0 | L42: =IF(ABS(J42)<0.0001,"SÍ","NO") -> SÍ
A43: ='03_CPM_Obra_Gruesa'!A149 -> E | B43: ='03_CPM_Obra_Gruesa'!B149 -> 2.2 | C43: ='03_CPM_Obra_Gruesa'!D149 -> Relleno, humectación y compactación | D43: D | E43: ='03_CPM_Obra_Gruesa'!E149 -> 9 | F43: =MAX(G42) -> 11 | G43: =F43+E43 -> 20 | H43: =I43-E43 -> 11 | I43: =MIN(H44) -> 20 | J43: =H43-F43 -> 0 | K43: =MIN(F44)-G43 -> 0 | L43: =IF(ABS(J43)<0.0001,"SÍ","NO") -> SÍ
A44: ='03_CPM_Obra_Gruesa'!A150 -> F | B44: ='03_CPM_Obra_Gruesa'!B150 -> 2.3 | C44: ='03_CPM_Obra_Gruesa'!D150 -> Emplantillado de hormigón | D44: E | E44: ='03_CPM_Obra_Gruesa'!E150 -> 5 | F44: =MAX(G43) -> 20 | G44: =F44+E44 -> 25 | H44: =I44-E44 -> 20 | I44: =MIN(H45) -> 25 | J44: =H44-F44 -> 0 | K44: =MIN(F45)-G44 -> 0 | L44: =IF(ABS(J44)<0.0001,"SÍ","NO") -> SÍ
A45: ='03_CPM_Obra_Gruesa'!A151 -> G | B45: ='03_CPM_Obra_Gruesa'!B151 -> 2.4 | C45: ='03_CPM_Obra_Gruesa'!D151 -> Fundaciones de hormigón armado | D45: F | E45: ='03_CPM_Obra_Gruesa'!E151 -> 13 | F45: =MAX(G44) -> 25 | G45: =F45+E45 -> 38 | H45: =I45-E45 -> 25 | I45: =MIN(H46,H47,H49) -> 38 | J45: =H45-F45 -> 0 | K45: =MIN(F46,F47,F49)-G45 -> 0 | L45: =IF(ABS(J45)<0.0001,"SÍ","NO") -> SÍ
A46: ='03_CPM_Obra_Gruesa'!A152 -> H | B46: ='03_CPM_Obra_Gruesa'!B152 -> 2.5 | C46: ='03_CPM_Obra_Gruesa'!D152 -> Radier y losas de hormigón | D46: G | E46: ='03_CPM_Obra_Gruesa'!E152 -> 12 | F46: =MAX(G45) -> 38 | G46: =F46+E46 -> 50 | H46: =I46-E46 -> 58 | I46: =MAX(G42:G49) -> 70 | J46: =H46-F46 -> 20 | K46: =MAX(G42:G49)-G46 -> 20 | L46: =IF(ABS(J46)<0.0001,"SÍ","NO") -> NO
A47: ='03_CPM_Obra_Gruesa'!A153 -> I | B47: ='03_CPM_Obra_Gruesa'!B153 -> 2.6 | C47: ='03_CPM_Obra_Gruesa'!D153 -> Estructura metálica y viga reticulada | D47: G | E47: ='03_CPM_Obra_Gruesa'!E153 -> 20 | F47: =MAX(G45) -> 38 | G47: =F47+E47 -> 58 | H47: =I47-E47 -> 38 | I47: =MIN(H48) -> 58 | J47: =H47-F47 -> 0 | K47: =MIN(F48)-G47 -> 0 | L47: =IF(ABS(J47)<0.0001,"SÍ","NO") -> SÍ
A48: ='03_CPM_Obra_Gruesa'!A154 -> J | B48: ='03_CPM_Obra_Gruesa'!B154 -> 2.7 | C48: ='03_CPM_Obra_Gruesa'!D154 -> Cubierta y hojalatería | D48: I | E48: ='03_CPM_Obra_Gruesa'!E154 -> 12 | F48: =MAX(G47) -> 58 | G48: =F48+E48 -> 70 | H48: =I48-E48 -> 58 | I48: =MAX(G42:G49) -> 70 | J48: =H48-F48 -> 0 | K48: =MAX(G42:G49)-G48 -> 0 | L48: =IF(ABS(J48)<0.0001,"SÍ","NO") -> SÍ
A49: ='03_CPM_Obra_Gruesa'!A155 -> K | B49: ='03_CPM_Obra_Gruesa'!B155 -> 2.8 | C49: ='03_CPM_Obra_Gruesa'!D155 -> Muros y tabiques Metalcon | D49: G | E49: ='03_CPM_Obra_Gruesa'!E155 -> 18 | F49: =MAX(G45) -> 38 | G49: =F49+E49 -> 56 | H49: =I49-E49 -> 52 | I49: =MAX(G42:G49) -> 70 | J49: =H49-F49 -> 14 | K49: =MAX(G42:G49)-G49 -> 14 | L49: =IF(ABS(J49)<0.0001,"SÍ","NO") -> NO
A51: FT = IT + duración. IT = máximo FT de las predecesoras. FTa = mínimo ITa de las sucesoras. ITa = FTa − duración. HT = ITa − IT. PERT usa te = (to + 4 tm + tp) / 6 sin redondear los cálculos. Las capturas son estáticas: regenerarlas después de cambiar entradas.
A64: CPM DEL PROYECTO COMPLETO - COMPLEMENTO DE COORDINACIÓN
A65: Plazo 150.00 días. Ruta crítica: A → B → D → E → F → G → I → J → L → Q → R → T → V. Se mantienen todas las entradas externas y frentes del proyecto.
A101: DESGLOSE DE COBERTURA Y TRAZABILIDAD POR PARTIDA
A102: Cada subpartida se ejecuta dentro de su paquete. No tiene duración individual calculada en el Paso 2. Los tiempos siguientes son del paquete, no un rendimiento propio.
A103: Código presupuesto | B103: Nodo | C103: Partida presupuestaria | D103: Unidad | E103: Cantidad | F103: Duración paquete | G103: IT paquete | H103: FT paquete | I103: ITa paquete | J103: FTa paquete | K103: HT paquete | L103: Crítica paquete
A104: ='06_Presupuesto'!A183 -> B.1.1.1 | B104: ='06_Presupuesto'!B183 -> D | C104: ='06_Presupuesto'!C183 -> Excavaciones | D104: ='06_Presupuesto'!D183 -> M3 | E104: ='06_Presupuesto'!E183 -> 15 | F104: =E42 -> 11 | G104: =F42 -> 0 | H104: =G42 -> 11 | I104: =H42 -> 0 | J104: =I42 -> 11 | K104: =J42 -> 0 | L104: =L42 -> SÍ
A105: ='06_Presupuesto'!A184 -> B.1.1.2 | B105: ='06_Presupuesto'!B184 -> F | C105: ='06_Presupuesto'!C184 -> Emplantillado | D105: ='06_Presupuesto'!D184 -> M2 | E105: ='06_Presupuesto'!E184 -> 23 | F105: =E44 -> 5 | G105: =F44 -> 20 | H105: =G44 -> 25 | I105: =H44 -> 20 | J105: =I44 -> 25 | K105: =J44 -> 0 | L105: =L44 -> SÍ
A106: ='06_Presupuesto'!A185 -> B.1.1.3 | B106: ='06_Presupuesto'!B185 -> G | C106: ='06_Presupuesto'!C185 -> Cimientos | D106: ='06_Presupuesto'!D185 -> M3 | E106: ='06_Presupuesto'!E185 -> 14 | F106: =E45 -> 13 | G106: =F45 -> 25 | H106: =G45 -> 38 | I106: =H45 -> 25 | J106: =I45 -> 38 | K106: =J45 -> 0 | L106: =L45 -> SÍ
A107: ='06_Presupuesto'!A186 -> B.1.2.1 | B107: ='06_Presupuesto'!B186 -> E | C107: ='06_Presupuesto'!C186 -> Preparación de la subrasante | D107: ='06_Presupuesto'!D186 -> M2 | E107: ='06_Presupuesto'!E186 -> 143 | F107: =E43 -> 9 | G107: =F43 -> 11 | H107: =G43 -> 20 | I107: =H43 -> 11 | J107: =I43 -> 20 | K107: =J43 -> 0 | L107: =L43 -> SÍ
A108: ='06_Presupuesto'!A187 -> B.1.2.2 | B108: ='06_Presupuesto'!B187 -> E | C108: ='06_Presupuesto'!C187 -> Base Estabilizada e=8cm | D108: ='06_Presupuesto'!D187 -> M3 | E108: ='06_Presupuesto'!E187 -> 11.44 | F108: =E43 -> 9 | G108: =F43 -> 11 | H108: =G43 -> 20 | I108: =H43 -> 11 | J108: =I43 -> 20 | K108: =J43 -> 0 | L108: =L43 -> SÍ
A109: ='06_Presupuesto'!A188 -> B.1.2.3 | B109: ='06_Presupuesto'!B188 -> H | C109: ='06_Presupuesto'!C188 -> Impermeabilización film de Polietileno e=0,10mm | D109: ='06_Presupuesto'!D188 -> M2 | E109: ='06_Presupuesto'!E188 -> 143 | F109: =E46 -> 12 | G109: =F46 -> 38 | H109: =G46 -> 50 | I109: =H46 -> 58 | J109: =I46 -> 70 | K109: =J46 -> 20 | L109: =L46 -> NO
A110: ='06_Presupuesto'!A189 -> B.1.2.4 | B110: ='06_Presupuesto'!B189 -> H | C110: ='06_Presupuesto'!C189 -> Cama de Ripio e=8cm | D110: ='06_Presupuesto'!D189 -> M3 | E110: ='06_Presupuesto'!E189 -> 11.44 | F110: =E46 -> 12 | G110: =F46 -> 38 | H110: =G46 -> 50 | I110: =H46 -> 58 | J110: =I46 -> 70 | K110: =J46 -> 20 | L110: =L46 -> NO
A111: ='06_Presupuesto'!A190 -> B.1.2.5 | B111: ='06_Presupuesto'!B190 -> H | C111: ='06_Presupuesto'!C190 -> Malla Acma C-92 | D111: ='06_Presupuesto'!D190 -> M2 | E111: ='06_Presupuesto'!E190 -> 143 | F111: =E46 -> 12 | G111: =F46 -> 38 | H111: =G46 -> 50 | I111: =H46 -> 58 | J111: =I46 -> 70 | K111: =J46 -> 20 | L111: =L46 -> NO
A112: ='06_Presupuesto'!A191 -> B.1.2.6 | B112: ='06_Presupuesto'!B191 -> H | C112: ='06_Presupuesto'!C191 -> Radier e= 7cm | D112: ='06_Presupuesto'!D191 -> M2 | E112: ='06_Presupuesto'!E191 -> 143 | F112: =E46 -> 12 | G112: =F46 -> 38 | H112: =G46 -> 50 | I112: =H46 -> 58 | J112: =I46 -> 70 | K112: =J46 -> 20 | L112: =L46 -> NO
A113: ='06_Presupuesto'!A192 -> B.1.3.1 | B113: ='06_Presupuesto'!B192 -> E | C113: ='06_Presupuesto'!C192 -> Estabilizado Compactado e=20cm | D113: ='06_Presupuesto'!D192 -> M3 | E113: ='06_Presupuesto'!E192 -> 18.65 | F113: =E43 -> 9 | G113: =F43 -> 11 | H113: =G43 -> 20 | I113: =H43 -> 11 | J113: =I43 -> 20 | K113: =J43 -> 0 | L113: =L43 -> SÍ
A114: ='06_Presupuesto'!A193 -> B.1.3.2 | B114: ='06_Presupuesto'!B193 -> E | C114: ='06_Presupuesto'!C193 -> Ripio Compactado e=10cm | D114: ='06_Presupuesto'!D193 -> M3 | E114: ='06_Presupuesto'!E193 -> 9.324 | F114: =E43 -> 9 | G114: =F43 -> 11 | H114: =G43 -> 20 | I114: =H43 -> 11 | J114: =I43 -> 20 | K114: =J43 -> 0 | L114: =L43 -> SÍ
A115: ='06_Presupuesto'!A194 -> B.1.3.3 | B115: ='06_Presupuesto'!B194 -> H | C115: ='06_Presupuesto'!C194 -> Polietileno e=0,15mm | D115: ='06_Presupuesto'!D194 -> M2 | E115: ='06_Presupuesto'!E194 -> 93.24 | F115: =E46 -> 12 | G115: =F46 -> 38 | H115: =G46 -> 50 | I115: =H46 -> 58 | J115: =I46 -> 70 | K115: =J46 -> 20 | L115: =L46 -> NO
A116: ='06_Presupuesto'!A195 -> B.1.3.4 | B116: ='06_Presupuesto'!B195 -> H | C116: ='06_Presupuesto'!C195 -> Radier e=10cm | D116: ='06_Presupuesto'!D195 -> M2 | E116: ='06_Presupuesto'!E195 -> 93.24 | F116: =E46 -> 12 | G116: =F46 -> 38 | H116: =G46 -> 50 | I116: =H46 -> 58 | J116: =I46 -> 70 | K116: =J46 -> 20 | L116: =L46 -> NO
A117: ='06_Presupuesto'!A196 -> B.1.4.1 | B117: ='06_Presupuesto'!B196 -> K | C117: ='06_Presupuesto'!C196 -> Estructura de Metalcon en Muros | D117: ='06_Presupuesto'!D196 -> M2 | E117: ='06_Presupuesto'!E196 -> 236 | F117: =E49 -> 18 | G117: =F49 -> 38 | H117: =G49 -> 56 | I117: =H49 -> 52 | J117: =I49 -> 70 | K117: =J49 -> 14 | L117: =L49 -> NO
A118: ='06_Presupuesto'!A197 -> B.1.4.2 | B118: ='06_Presupuesto'!B197 -> K | C118: ='06_Presupuesto'!C197 -> Planchas de OSB e=11.1mm | D118: ='06_Presupuesto'!D197 -> M2 | E118: ='06_Presupuesto'!E197 -> 153 | F118: =E49 -> 18 | G118: =F49 -> 38 | H118: =G49 -> 56 | I118: =H49 -> 52 | J118: =I49 -> 70 | K118: =J49 -> 14 | L118: =L49 -> NO
A119: ='06_Presupuesto'!A198 -> B.1.4.3 | B119: ='06_Presupuesto'!B198 -> K | C119: ='06_Presupuesto'!C198 -> Forro Exterior | D119: ='06_Presupuesto'!D198 -> M2 | E119: ='06_Presupuesto'!E198 -> 153 | F119: =E49 -> 18 | G119: =F49 -> 38 | H119: =G49 -> 56 | I119: =H49 -> 52 | J119: =I49 -> 70 | K119: =J49 -> 14 | L119: =L49 -> NO
A120: ='06_Presupuesto'!A199 -> B.1.4.4 | B120: ='06_Presupuesto'!B199 -> K | C120: ='06_Presupuesto'!C199 -> Forro Interior Volcanita y Aleros Exteriores | D120: ='06_Presupuesto'!D199 -> M2 | E120: ='06_Presupuesto'!E199 -> 180 | F120: =E49 -> 18 | G120: =F49 -> 38 | H120: =G49 -> 56 | I120: =H49 -> 52 | J120: =I49 -> 70 | K120: =J49 -> 14 | L120: =L49 -> NO
A121: ='06_Presupuesto'!A200 -> B.1.4.5 | B121: ='06_Presupuesto'!B200 -> K | C121: ='06_Presupuesto'!C200 -> Forro Interior Fibrocemento | D121: ='06_Presupuesto'!D200 -> M2 | E121: ='06_Presupuesto'!E200 -> 65 | F121: =E49 -> 18 | G121: =F49 -> 38 | H121: =G49 -> 56 | I121: =H49 -> 52 | J121: =I49 -> 70 | K121: =J49 -> 14 | L121: =L49 -> NO
A122: ='06_Presupuesto'!A201 -> B.1.5.1 | B122: ='06_Presupuesto'!B201 -> I | C122: ='06_Presupuesto'!C201 -> Cerchas y Costaneras de Acero Galvanizado | D122: ='06_Presupuesto'!D201 -> M2 | E122: ='06_Presupuesto'!E201 -> 78.61 | F122: =E47 -> 20 | G122: =F47 -> 38 | H122: =G47 -> 58 | I122: =H47 -> 38 | J122: =I47 -> 58 | K122: =J47 -> 0 | L122: =L47 -> SÍ
A123: ='06_Presupuesto'!A202 -> B.1.6.1 | B123: ='06_Presupuesto'!B202 -> J | C123: ='06_Presupuesto'!C202 -> Aislación Papel Impermeabilizante | D123: ='06_Presupuesto'!D202 -> M2 | E123: ='06_Presupuesto'!E202 -> 78.61 | F123: =E48 -> 12 | G123: =F48 -> 58 | H123: =G48 -> 70 | I123: =H48 -> 58 | J123: =I48 -> 70 | K123: =J48 -> 0 | L123: =L48 -> SÍ
A124: ='06_Presupuesto'!A203 -> B.1.6.2 | B124: ='06_Presupuesto'!B203 -> J | C124: ='06_Presupuesto'!C203 -> Planchas OSB e=11.1mm | D124: ='06_Presupuesto'!D203 -> M2 | E124: ='06_Presupuesto'!E203 -> 78.61 | F124: =E48 -> 12 | G124: =F48 -> 58 | H124: =G48 -> 70 | I124: =H48 -> 58 | J124: =I48 -> 70 | K124: =J48 -> 0 | L124: =L48 -> SÍ
A125: ='06_Presupuesto'!A204 -> B.1.6.3 | B125: ='06_Presupuesto'!B204 -> J | C125: ='06_Presupuesto'!C204 -> Cubierta Onda Estándar | D125: ='06_Presupuesto'!D204 -> M2 | E125: ='06_Presupuesto'!E204 -> 78.61 | F125: =E48 -> 12 | G125: =F48 -> 58 | H125: =G48 -> 70 | I125: =H48 -> 58 | J125: =I48 -> 70 | K125: =J48 -> 0 | L125: =L48 -> SÍ
A126: ='06_Presupuesto'!A210 -> B.2.4/a) | B126: ='06_Presupuesto'!B210 -> J | C126: ='06_Presupuesto'!C210 -> Forros | D126: ='06_Presupuesto'!D210 -> ML | E126: ='06_Presupuesto'!E210 -> 25 | F126: =E48 -> 12 | G126: =F48 -> 58 | H126: =G48 -> 70 | I126: =H48 -> 58 | J126: =I48 -> 70 | K126: =J48 -> 0 | L126: =L48 -> SÍ
A127: ='06_Presupuesto'!A211 -> B.2.4/b) | B127: ='06_Presupuesto'!B211 -> J | C127: ='06_Presupuesto'!C211 -> Canales | D127: ='06_Presupuesto'!D211 -> ML | E127: ='06_Presupuesto'!E211 -> 45 | F127: =E48 -> 12 | G127: =F48 -> 58 | H127: =G48 -> 70 | I127: =H48 -> 58 | J127: =I48 -> 70 | K127: =J48 -> 0 | L127: =L48 -> SÍ
A128: ='06_Presupuesto'!A212 -> B.2.4/c) | B128: ='06_Presupuesto'!B212 -> J | C128: ='06_Presupuesto'!C212 -> Bajadas | D128: ='06_Presupuesto'!D212 -> ML | E128: ='06_Presupuesto'!E212 -> 24 | F128: =E48 -> 12 | G128: =F48 -> 58 | H128: =G48 -> 70 | I128: =H48 -> 58 | J128: =I48 -> 70 | K128: =J48 -> 0 | L128: =L48 -> SÍ
A129: ='06_Presupuesto'!A213 -> B.2.4/d) | B129: ='06_Presupuesto'!B213 -> J | C129: ='06_Presupuesto'!C213 -> Salida Ventilaciones | D129: ='06_Presupuesto'!D213 -> ML | E129: ='06_Presupuesto'!E213 -> 6 | F129: =E48 -> 12 | G129: =F48 -> 58 | H129: =G48 -> 70 | I129: =H48 -> 58 | J129: =I48 -> 70 | K129: =J48 -> 0 | L129: =L48 -> SÍ
A137: RED CPM DEL PROYECTO COMPLETO · ANÁLISIS COMPLEMENTARIO
A140: PASO 3 · MALLA CPM Y RUTA CRÍTICA · ES3 IND. 3
A141: Construcción Sede Social El Bosque | Andacollo | Red AON con frentes paralelos y convergencias
A142: Cálculo hacia adelante y atrás. IT: inicio temprano; FT: término temprano; ITa: inicio tardío; FTa: término tardío. Vista específica de la rúbrica y desglose: 04A_CPM_Mallas.
A144: Act. | B144: EDT | C144: Macro-etapa | D144: Partida | E144: Duración (d) | F144: Predecesoras | G144: IT | H144: FT | I144: ITa | J144: FTa | K144: Holgura Total | L144: Holgura Libre | M144: Crítica | N144: Sucesoras
A145: A | B145: 1.1 | C145: Instalación de faenas | D145: Instalación de faenas y cierre perimetral | E145: ='02_Rendimientos'!K6 -> 6 | F145: — | G145: =0 -> 0 | H145: =G145+E145 -> 6 | I145: =J145-E145 -> 0 | J145: =MIN(I146,I147) -> 6 | K145: =ROUND(I145-G145,3) -> 0 | L145: =ROUND(MIN(G146,G147)-H145,3) -> 0 | M145: =IF(ABS(K145)<0.001,"SÍ","NO") -> SÍ | N145: B, C
A146: B | B146: 1.2 | C146: Instalación de faenas | D146: Replanteo y nivelación del área de trabajo | E146: ='02_Rendimientos'!K7 -> 5 | F146: A | G146: =MAX(H145) -> 6 | H146: =G146+E146 -> 11 | I146: =J146-E146 -> 6 | J146: =MIN(I148) -> 11 | K146: =ROUND(I146-G146,3) -> 0 | L146: =ROUND(MIN(G148)-H146,3) -> 0 | M146: =IF(ABS(K146)<0.001,"SÍ","NO") -> SÍ | N146: D
A147: C | B147: 1.3 | C147: Instalación de faenas | D147: Servicios provisorios y habilitación de instalaciones | E147: ='02_Rendimientos'!K8 -> 10 | F147: A | G147: =MAX(H145) -> 6 | H147: =G147+E147 -> 16 | I147: =J147-E147 -> 140 | J147: =J167 -> 150 | K147: =ROUND(I147-G147,3) -> 134 | L147: =J167-H147 -> 134 | M147: =IF(ABS(K147)<0.001,"SÍ","NO") -> NO | N147: FIN
A148: D | B148: 2.1 | C148: Obra Gruesa | D148: Excavación y retiro de material | E148: ='02_Rendimientos'!K9 -> 11 | F148: B | G148: =MAX(H146) -> 11 | H148: =G148+E148 -> 22 | I148: =J148-E148 -> 11 | J148: =MIN(I149) -> 22 | K148: =ROUND(I148-G148,3) -> 0 | L148: =ROUND(MIN(G149)-H148,3) -> 0 | M148: =IF(ABS(K148)<0.001,"SÍ","NO") -> SÍ | N148: E
A149: E | B149: 2.2 | C149: Obra Gruesa | D149: Relleno, humectación y compactación | E149: ='02_Rendimientos'!K10 -> 9 | F149: D | G149: =MAX(H148) -> 22 | H149: =G149+E149 -> 31 | I149: =J149-E149 -> 22 | J149: =MIN(I150,I158) -> 31 | K149: =ROUND(I149-G149,3) -> 0 | L149: =ROUND(MIN(G150,G158)-H149,3) -> 0 | M149: =IF(ABS(K149)<0.001,"SÍ","NO") -> SÍ | N149: F, N
A150: F | B150: 2.3 | C150: Obra Gruesa | D150: Emplantillado de hormigón | E150: ='02_Rendimientos'!K11 -> 5 | F150: E | G150: =MAX(H149) -> 31 | H150: =G150+E150 -> 36 | I150: =J150-E150 -> 31 | J150: =MIN(I151) -> 36 | K150: =ROUND(I150-G150,3) -> 0 | L150: =ROUND(MIN(G151)-H150,3) -> 0 | M150: =IF(ABS(K150)<0.001,"SÍ","NO") -> SÍ | N150: G
A151: G | B151: 2.4 | C151: Obra Gruesa | D151: Fundaciones de hormigón armado | E151: ='02_Rendimientos'!K12 -> 13 | F151: F | G151: =MAX(H150) -> 36 | H151: =G151+E151 -> 49 | I151: =J151-E151 -> 36 | J151: =MIN(I152,I153,I155) -> 49 | K151: =ROUND(I151-G151,3) -> 0 | L151: =ROUND(MIN(G152,G153,G155)-H151,3) -> 0 | M151: =IF(ABS(K151)<0.001,"SÍ","NO") -> SÍ | N151: H, I, K
A152: H | B152: 2.5 | C152: Obra Gruesa | D152: Radier y losas de hormigón | E152: ='02_Rendimientos'!K13 -> 12 | F152: G | G152: =MAX(H151) -> 49 | H152: =G152+E152 -> 61 | I152: =J152-E152 -> 69 | J152: =MIN(I156) -> 81 | K152: =ROUND(I152-G152,3) -> 20 | L152: =ROUND(MIN(G156)-H152,3) -> 20 | M152: =IF(ABS(K152)<0.001,"SÍ","NO") -> NO | N152: L
A153: I | B153: 2.6 | C153: Obra Gruesa | D153: Estructura metálica y viga reticulada | E153: ='02_Rendimientos'!K14 -> 20 | F153: G | G153: =MAX(H151) -> 49 | H153: =G153+E153 -> 69 | I153: =J153-E153 -> 49 | J153: =MIN(I154,I156) -> 69 | K153: =ROUND(I153-G153,3) -> 0 | L153: =ROUND(MIN(G154,G156)-H153,3) -> 0 | M153: =IF(ABS(K153)<0.001,"SÍ","NO") -> SÍ | N153: J, L
A154: J | B154: 2.7 | C154: Obra Gruesa | D154: Cubierta y hojalatería | E154: ='02_Rendimientos'!K15 -> 12 | F154: I | G154: =MAX(H153) -> 69 | H154: =G154+E154 -> 81 | I154: =J154-E154 -> 69 | J154: =MIN(I156,I165) -> 81 | K154: =ROUND(I154-G154,3) -> 0 | L154: =ROUND(MIN(G156,G165)-H154,3) -> 0 | M154: =IF(ABS(K154)<0.001,"SÍ","NO") -> SÍ | N154: L, U
A155: K | B155: 2.8 | C155: Obra Gruesa | D155: Muros y tabiques Metalcon | E155: ='02_Rendimientos'!K16 -> 18 | F155: G | G155: =MAX(H151) -> 49 | H155: =G155+E155 -> 67 | I155: =J155-E155 -> 63 | J155: =MIN(I156,I157,I161,I165) -> 81 | K155: =ROUND(I155-G155,3) -> 14 | L155: =ROUND(MIN(G156,G157,G161,G165)-H155,3) -> 0 | M155: =IF(ABS(K155)<0.001,"SÍ","NO") -> NO | N155: L, M, Q, U
A156: L | B156: 3.1 | C156: Instalaciones | D156: Instalación eléctrica interior | E156: ='02_Rendimientos'!K17 -> 14 | F156: H - I - J - K | G156: =MAX(H152,H153,H154,H155) -> 81 | H156: =G156+E156 -> 95 | I156: =J156-E156 -> 81 | J156: =MIN(I160,I161) -> 95 | K156: =ROUND(I156-G156,3) -> 0 | L156: =ROUND(MIN(G160,G161)-H156,3) -> 0 | M156: =IF(ABS(K156)<0.001,"SÍ","NO") -> SÍ | N156: P, Q
A157: M | B157: 3.2 | C157: Instalaciones | D157: Red de agua potable | E157: ='02_Rendimientos'!K18 -> 12 | F157: K | G157: =MAX(H155) -> 67 | H157: =G157+E157 -> 79 | I157: =J157-E157 -> 115 | J157: =MIN(I159) -> 127 | K157: =ROUND(I157-G157,3) -> 48 | L157: =ROUND(MIN(G159)-H157,3) -> 0 | M157: =IF(ABS(K157)<0.001,"SÍ","NO") -> NO | N157: O
A158: N | B158: 3.3 | C158: Instalaciones | D158: Red de alcantarillado | E158: ='02_Rendimientos'!K19 -> 14 | F158: E | G158: =MAX(H149) -> 31 | H158: =G158+E158 -> 45 | I158: =J158-E158 -> 113 | J158: =MIN(I159) -> 127 | K158: =ROUND(I158-G158,3) -> 82 | L158: =ROUND(MIN(G159)-H158,3) -> 34 | M158: =IF(ABS(K158)<0.001,"SÍ","NO") -> NO | N158: O
A159: O | B159: 3.4 | C159: Instalaciones | D159: Instalación de artefactos sanitarios | E159: ='02_Rendimientos'!K20 -> 8 | F159: M - N | G159: =MAX(H157,H158) -> 79 | H159: =G159+E159 -> 87 | I159: =J159-E159 -> 127 | J159: =MIN(I160) -> 135 | K159: =ROUND(I159-G159,3) -> 48 | L159: =ROUND(MIN(G160)-H159,3) -> 8 | M159: =IF(ABS(K159)<0.001,"SÍ","NO") -> NO | N159: P
A160: P | B160: 3.5 | C160: Instalaciones | D160: Pruebas, conexiones y certificaciones | E160: ='02_Rendimientos'!K21 -> 8 | F160: L - O | G160: =MAX(H156,H159) -> 95 | H160: =G160+E160 -> 103 | I160: =J160-E160 -> 135 | J160: =MIN(I166) -> 143 | K160: =ROUND(I160-G160,3) -> 40 | L160: =ROUND(MIN(G166)-H160,3) -> 40 | M160: =IF(ABS(K160)<0.001,"SÍ","NO") -> NO | N160: V
A161: Q | B161: 4.1 | C161: Terminaciones | D161: Revestimientos interiores | E161: ='02_Rendimientos'!K22 -> 16 | F161: L - K | G161: =MAX(H156,H155) -> 95 | H161: =G161+E161 -> 111 | I161: =J161-E161 -> 95 | J161: =MIN(I162,I163) -> 111 | K161: =ROUND(I161-G161,3) -> 0 | L161: =ROUND(MIN(G162,G163)-H161,3) -> 0 | M161: =IF(ABS(K161)<0.001,"SÍ","NO") -> SÍ | N161: R, S
A162: R | B162: 4.2 | C162: Terminaciones | D162: Cielos y elementos complementarios | E162: ='02_Rendimientos'!K23 -> 12 | F162: Q | G162: =MAX(H161) -> 111 | H162: =G162+E162 -> 123 | I162: =J162-E162 -> 111 | J162: =MIN(I164) -> 123 | K162: =ROUND(I162-G162,3) -> 0 | L162: =ROUND(MIN(G164)-H162,3) -> 0 | M162: =IF(ABS(K162)<0.001,"SÍ","NO") -> SÍ | N162: T
A163: S | B163: 4.3 | C163: Terminaciones | D163: Pavimentos | E163: ='02_Rendimientos'!K24 -> 10 | F163: Q | G163: =MAX(H161) -> 111 | H163: =G163+E163 -> 121 | I163: =J163-E163 -> 113 | J163: =MIN(I164) -> 123 | K163: =ROUND(I163-G163,3) -> 2 | L163: =ROUND(MIN(G164)-H163,3) -> 2 | M163: =IF(ABS(K163)<0.001,"SÍ","NO") -> NO | N163: T
A164: T | B164: 4.4 | C164: Terminaciones | D164: Pinturas interiores y exteriores | E164: ='02_Rendimientos'!K25 -> 20 | F164: R - S | G164: =MAX(H162,H163) -> 123 | H164: =G164+E164 -> 143 | I164: =J164-E164 -> 123 | J164: =MIN(I166) -> 143 | K164: =ROUND(I164-G164,3) -> 0 | L164: =ROUND(MIN(G166)-H164,3) -> 0 | M164: =IF(ABS(K164)<0.001,"SÍ","NO") -> SÍ | N164: V
A165: U | B165: 4.5 | C165: Terminaciones | D165: Puertas, ventanas y quincallería | E165: ='02_Rendimientos'!K26 -> 16 | F165: J - K | G165: =MAX(H154,H155) -> 81 | H165: =G165+E165 -> 97 | I165: =J165-E165 -> 127 | J165: =MIN(I166) -> 143 | K165: =ROUND(I165-G165,3) -> 46 | L165: =ROUND(MIN(G166)-H165,3) -> 46 | M165: =IF(ABS(K165)<0.001,"SÍ","NO") -> NO | N165: V
A166: V | B166: 4.6 | C166: Terminaciones | D166: Limpieza, remates y entrega | E166: ='02_Rendimientos'!K27 -> 7 | F166: T - U - P | G166: =MAX(H164,H165,H160) -> 143 | H166: =G166+E166 -> 150 | I166: =J166-E166 -> 143 | J166: =J167 -> 150 | K166: =ROUND(I166-G166,3) -> 0 | L166: =0 -> 0 | M166: =IF(ABS(K166)<0.001,"SÍ","NO") -> SÍ | N166: FIN
A167: FIN | B167: — | C167: — | D167: Fin contractual del proyecto | E167: 0 | F167: V | G167: =MAX(H145:H166) -> 150 | H167: =G167 -> 150 | I167: =G167 -> 150 | J167: =G167 -> 150 | K167: 0 | L167: 0 | M167: SÍ | N167: —
A169: RESULTADOS CPM
A170: Duración calculada (días) | D170: =H167 -> 150 | F170: Ruta crítica: A - B - D - E - F - G - I - J - L - Q - R - T - V
A171: Actividades críticas | D171: =COUNTIF(M145:M166,"SÍ") -> 13
A173: Se conserva la red del avance y la imagen generada por la aplicación del usuario. C es una rama terminal del programa. La tabla usa IT, FT, ITa y FTa en español.
A177: Lectura: C, H, K, M, N, O, P, S y U forman frentes paralelos o ramas convergentes. El plazo final queda gobernado por la cadena crítica A-B-D-E-F-G-I-J-L-Q-R-T-V y alcanza exactamente 150 días corridos.
A180: Fuente: precedencias y duraciones de planificación definidas para cumplir el mínimo contractual indicado por la Municipalidad de Andacollo. Deben validarse con antecedentes contractuales, recursos, rendimientos y secuencia definitiva de obra.
A213: CPM ESPECÍFICO DE OBRA GRUESA | PASO 3
A214: Red sectorial con inicio relativo en día 0. Las predecesoras externas liberan el frente. La correspondencia de los paquetes con el itemizado está en el Paso 6.
A216: Act. | B216: Duración | C216: Predecesoras internas | D216: Partida | E216: IT | F216: FT | G216: ITa | H216: FTa | I216: HT | J216: Crítica
A217: D | B217: =E148 -> 11 | C217: Inicio del sector | D217: ='03_CPM_Obra_Gruesa'!D148 -> Excavación y retiro de material | E217: =0 -> 0 | F217: =E217+B217 -> 11 | G217: =H217-B217 -> 0 | H217: =MIN(G218) -> 11 | I217: =ROUND(G217-E217,6) -> 0 | J217: =IF(ABS(I217)<0.00001,"SÍ","NO") -> SÍ
A218: E | B218: =E149 -> 9 | C218: D | D218: ='03_CPM_Obra_Gruesa'!D149 -> Relleno, humectación y compactación | E218: =MAX(F217) -> 11 | F218: =E218+B218 -> 20 | G218: =H218-B218 -> 11 | H218: =MIN(G219) -> 20 | I218: =ROUND(G218-E218,6) -> 0 | J218: =IF(ABS(I218)<0.00001,"SÍ","NO") -> SÍ
A219: F | B219: =E150 -> 5 | C219: E | D219: ='03_CPM_Obra_Gruesa'!D150 -> Emplantillado de hormigón | E219: =MAX(F218) -> 20 | F219: =E219+B219 -> 25 | G219: =H219-B219 -> 20 | H219: =MIN(G220) -> 25 | I219: =ROUND(G219-E219,6) -> 0 | J219: =IF(ABS(I219)<0.00001,"SÍ","NO") -> SÍ
A220: G | B220: =E151 -> 13 | C220: F | D220: ='03_CPM_Obra_Gruesa'!D151 -> Fundaciones de hormigón armado | E220: =MAX(F219) -> 25 | F220: =E220+B220 -> 38 | G220: =H220-B220 -> 25 | H220: =MIN(G221,G222,G224) -> 38 | I220: =ROUND(G220-E220,6) -> 0 | J220: =IF(ABS(I220)<0.00001,"SÍ","NO") -> SÍ
A221: H | B221: =E152 -> 12 | C221: G | D221: ='03_CPM_Obra_Gruesa'!D152 -> Radier y losas de hormigón | E221: =MAX(F220) -> 38 | F221: =E221+B221 -> 50 | G221: =H221-B221 -> 58 | H221: =F225 -> 70 | I221: =ROUND(G221-E221,6) -> 20 | J221: =IF(ABS(I221)<0.00001,"SÍ","NO") -> NO
A222: I | B222: =E153 -> 20 | C222: G | D222: ='03_CPM_Obra_Gruesa'!D153 -> Estructura metálica y viga reticulada | E222: =MAX(F220) -> 38 | F222: =E222+B222 -> 58 | G222: =H222-B222 -> 38 | H222: =MIN(G223) -> 58 | I222: =ROUND(G222-E222,6) -> 0 | J222: =IF(ABS(I222)<0.00001,"SÍ","NO") -> SÍ
A223: J | B223: =E154 -> 12 | C223: I | D223: ='03_CPM_Obra_Gruesa'!D154 -> Cubierta y hojalatería | E223: =MAX(F222) -> 58 | F223: =E223+B223 -> 70 | G223: =H223-B223 -> 58 | H223: =F225 -> 70 | I223: =ROUND(G223-E223,6) -> 0 | J223: =IF(ABS(I223)<0.00001,"SÍ","NO") -> SÍ
A224: K | B224: =E155 -> 18 | C224: G | D224: ='03_CPM_Obra_Gruesa'!D155 -> Muros y tabiques Metalcon | E224: =MAX(F220) -> 38 | F224: =E224+B224 -> 56 | G224: =H224-B224 -> 52 | H224: =F225 -> 70 | I224: =ROUND(G224-E224,6) -> 14 | J224: =IF(ABS(I224)<0.00001,"SÍ","NO") -> NO
D225: Duración del sector | F225: =MAX(F217:F224) -> 70
A227: MALLA NODAL DE OBRA GRUESA (TIEMPOS EN DÍAS)
A229: =A217&" | d="&TEXT(B217,"0.00") -> D | d=011 | D229: =A218&" | d="&TEXT(B218,"0.00") -> E | d=009 | G229: =A219&" | d="&TEXT(B219,"0.00") -> F | d=005 | J229: =A220&" | d="&TEXT(B220,"0.00") -> G | d=013
A230: ="IT "&TEXT(E217,"0.00")&" | FT "&TEXT(F217,"0.00") -> IT 000 | FT 011 | C230: → | D230: ="IT "&TEXT(E218,"0.00")&" | FT "&TEXT(F218,"0.00") -> IT 011 | FT 020 | F230: → | G230: ="IT "&TEXT(E219,"0.00")&" | FT "&TEXT(F219,"0.00") -> IT 020 | FT 025 | I230: → | J230: ="IT "&TEXT(E220,"0.00")&" | FT "&TEXT(F220,"0.00") -> IT 025 | FT 038
A231: ="ITa "&TEXT(G217,"0.00")&" | FTa "&TEXT(H217,"0.00") -> ITa 000 | FTa 011 | D231: ="ITa "&TEXT(G218,"0.00")&" | FTa "&TEXT(H218,"0.00") -> ITa 011 | FTa 020 | G231: ="ITa "&TEXT(G219,"0.00")&" | FTa "&TEXT(H219,"0.00") -> ITa 020 | FTa 025 | J231: ="ITa "&TEXT(G220,"0.00")&" | FTa "&TEXT(H220,"0.00") -> ITa 025 | FTa 038
A232: ="Holgura "&TEXT(I217,"0.00") -> Holgura 000 | D232: ="Holgura "&TEXT(I218,"0.00") -> Holgura 000 | G232: ="Holgura "&TEXT(I219,"0.00") -> Holgura 000 | J232: ="Holgura "&TEXT(I220,"0.00") -> Holgura 000
J234: ↓ G se abre en H, I, K
D236: =A223&" | d="&TEXT(B223,"0.00") -> J | d=012 | G236: =A222&" | d="&TEXT(B222,"0.00") -> I | d=020 | M236: =A221&" | d="&TEXT(B221,"0.00") -> H | d=012
D237: ="IT "&TEXT(E223,"0.00")&" | FT "&TEXT(F223,"0.00") -> IT 058 | FT 070 | F237: ← | G237: ="IT "&TEXT(E222,"0.00")&" | FT "&TEXT(F222,"0.00") -> IT 038 | FT 058 | M237: ="IT "&TEXT(E221,"0.00")&" | FT "&TEXT(F221,"0.00") -> IT 038 | FT 050
...

Sheet 04_PERT_Terminaciones
A2: PERT DE TERMINACIONES - ES3 IND. 4
A3: PERT sectorial: 6 paquetes de programación asociados a 38 partidas presupuestarias de terminaciones. La correspondencia por partida se presenta desde la fila 103.
A5: Red sectorial autónoma: día 0 local, 57.50 días. Entradas externas Q depende de L, K; U depende de J, K; V depende de P se conservan en la red total, no en esta subred. No sumar su duración al plazo total.
A7: Lectura: arriba IT (inicio temprano) / FT (término temprano); abajo ITa (inicio tardío) / FTa (término tardío). Rojo: ruta crítica. Azul: actividades con holgura.
A51: TABLA SECTORIAL - RUTA CRÍTICA Q → R → T → V
A52: Nodo | B52: EDT | C52: Partida / paquete | D52: Predecesoras locales | E52: Duración (d) | F52: IT | G52: FT | H52: ITa | I52: FTa | J52: HT | K52: HL | L52: Crítica
A53: ='04_PERT_Terminaciones'!A171 -> Q | B53: ='04_PERT_Terminaciones'!B171 -> 4.1 | C53: ='04_PERT_Terminaciones'!D171 -> Revestimientos interiores | D53: — | E53: ='04_PERT_Terminaciones'!I171 -> 16.666667 | F53: =0 -> 0 | G53: =F53+E53 -> 16.666667 | H53: =I53-E53 -> 0 | I53: =MIN(H54,H55) -> 16.666667 | J53: =H53-F53 -> 0 | K53: =MIN(F54,F55)-G53 -> 0 | L53: =IF(ABS(J53)<0.0001,"SÍ","NO") -> SÍ
A54: ='04_PERT_Terminaciones'!A172 -> R | B54: ='04_PERT_Terminaciones'!B172 -> 4.2 | C54: ='04_PERT_Terminaciones'!D172 -> Cielos y elementos complementarios | D54: Q | E54: ='04_PERT_Terminaciones'!I172 -> 12.5 | F54: =MAX(G53) -> 16.666667 | G54: =F54+E54 -> 29.166667 | H54: =I54-E54 -> 16.666667 | I54: =MIN(H56) -> 29.166667 | J54: =H54-F54 -> 0 | K54: =MIN(F56)-G54 -> 0 | L54: =IF(ABS(J54)<0.0001,"SÍ","NO") -> SÍ
A55: ='04_PERT_Terminaciones'!A173 -> S | B55: ='04_PERT_Terminaciones'!B173 -> 4.3 | C55: ='04_PERT_Terminaciones'!D173 -> Pavimentos | D55: Q | E55: ='04_PERT_Terminaciones'!I173 -> 10.5 | F55: =MAX(G53) -> 16.666667 | G55: =F55+E55 -> 27.166667 | H55: =I55-E55 -> 18.666667 | I55: =MIN(H56) -> 29.166667 | J55: =H55-F55 -> 2 | K55: =MIN(F56)-G55 -> 2 | L55: =IF(ABS(J55)<0.0001,"SÍ","NO") -> NO
A56: ='04_PERT_Terminaciones'!A174 -> T | B56: ='04_PERT_Terminaciones'!B174 -> 4.4 | C56: ='04_PERT_Terminaciones'!D174 -> Pinturas interiores y exteriores | D56: R, S | E56: ='04_PERT_Terminaciones'!I174 -> 20.833333 | F56: =MAX(G54,G55) -> 29.166667 | G56: =F56+E56 -> 50 | H56: =I56-E56 -> 29.166667 | I56: =MIN(H58) -> 50 | J56: =H56-F56 -> 0 | K56: =MIN(F58)-G56 -> 0 | L56: =IF(ABS(J56)<0.0001,"SÍ","NO") -> SÍ
A57: ='04_PERT_Terminaciones'!A175 -> U | B57: ='04_PERT_Terminaciones'!B175 -> 4.5 | C57: ='04_PERT_Terminaciones'!D175 -> Puertas, ventanas y quincallería | D57: — | E57: ='04_PERT_Terminaciones'!I175 -> 16.666667 | F57: =0 -> 0 | G57: =F57+E57 -> 16.666667 | H57: =I57-E57 -> 33.333333 | I57: =MIN(H58) -> 50 | J57: =H57-F57 -> 33.333333 | K57: =MIN(F58)-G57 -> 33.333333 | L57: =IF(ABS(J57)<0.0001,"SÍ","NO") -> NO
A58: ='04_PERT_Terminaciones'!A176 -> V | B58: ='04_PERT_Terminaciones'!B176 -> 4.6 | C58: ='04_PERT_Terminaciones'!D176 -> Limpieza, remates y entrega | D58: T, U | E58: ='04_PERT_Terminaciones'!I176 -> 7.5 | F58: =MAX(G56,G57) -> 50 | G58: =F58+E58 -> 57.5 | H58: =I58-E58 -> 50 | I58: =MAX(G53:G58) -> 57.5 | J58: =H58-F58 -> 0 | K58: =MAX(G53:G58)-G58 -> 0 | L58: =IF(ABS(J58)<0.0001,"SÍ","NO") -> SÍ
A60: FT = IT + duración. IT = máximo FT de las predecesoras. FTa = mínimo ITa de las sucesoras. ITa = FTa − duración. HT = ITa − IT. PERT usa te = (to + 4 tm + tp) / 6 sin redondear los cálculos. Las capturas son estáticas: regenerarlas después de cambiar entradas.
A64: PERT DEL PROYECTO COMPLETO - COMPLEMENTO DE COORDINACIÓN
A65: Plazo 155.17 días. Ruta crítica: A → B → D → E → F → G → I → J → L → Q → R → T → V. Se mantienen todas las entradas externas y frentes del proyecto.
A101: DESGLOSE DE COBERTURA Y TRAZABILIDAD POR PARTIDA
A102: Cada subpartida se ejecuta dentro de su paquete. No tiene duración individual calculada en el Paso 2. Los tiempos siguientes son del paquete, no un rendimiento propio.
A103: Código presupuesto | B103: Nodo | C103: Partida presupuestaria | D103: Unidad | E103: Cantidad | F103: Duración paquete | G103: IT paquete | H103: FT paquete | I103: ITa paquete | J103: FTa paquete | K103: HT paquete | L103: Crítica paquete
A104: ='06_Presupuesto'!A205 -> B.2.1.1 | B104: ='06_Presupuesto'!B205 -> Q | C104: ='06_Presupuesto'!C205 -> Aislante Térmico Para Muros | D104: ='06_Presupuesto'!D205 -> M2 | E104: ='06_Presupuesto'!E205 -> 236 | F104: =E53 -> 16.666667 | G104: =F53 -> 0 | H104: =G53 -> 16.666667 | I104: =H53 -> 0 | J104: =I53 -> 16.666667 | K104: =J53 -> 0 | L104: =L53 -> SÍ
A105: ='06_Presupuesto'!A206 -> B.2.1.2 | B105: ='06_Presupuesto'!B206 -> R | C105: ='06_Presupuesto'!C206 -> Aislante Térmico Para Cielo | D105: ='06_Presupuesto'!D206 -> M2 | E105: ='06_Presupuesto'!E206 -> 78.61 | F105: =E54 -> 12.5 | G105: =F54 -> 16.666667 | H105: =G54 -> 29.166667 | I105: =H54 -> 16.666667 | J105: =I54 -> 29.166667 | K105: =J54 -> 0 | L105: =L54 -> SÍ
A106: ='06_Presupuesto'!A207 -> B.2.1.3 | B106: ='06_Presupuesto'!B207 -> S | C106: ='06_Presupuesto'!C207 -> Impermeabilización Bajo Pavimentos | D106: ='06_Presupuesto'!D207 -> M2 | E106: ='06_Presupuesto'!E207 -> 85 | F106: =E55 -> 10.5 | G106: =F55 -> 16.666667 | H106: =G55 -> 27.166667 | I106: =H55 -> 18.666667 | J106: =I55 -> 29.166667 | K106: =J55 -> 2 | L106: =L55 -> NO
A107: ='06_Presupuesto'!A208 -> B.2.2/a) | B107: ='06_Presupuesto'!B208 -> R | C107: ='06_Presupuesto'!C208 -> Yeso Cartón RH | D107: ='06_Presupuesto'!D208 -> M2 | E107: ='06_Presupuesto'!E208 -> 34 | F107: =E54 -> 12.5 | G107: =F54 -> 16.666667 | H107: =G54 -> 29.166667 | I107: =H54 -> 16.666667 | J107: =I54 -> 29.166667 | K107: =J54 -> 0 | L107: =L54 -> SÍ
A108: ='06_Presupuesto'!A209 -> B.2.3/a) | B108: ='06_Presupuesto'!B209 -> R | C108: ='06_Presupuesto'!C209 -> Yeso Cartón | D108: ='06_Presupuesto'!D209 -> M2 | E108: ='06_Presupuesto'!E209 -> 50 | F108: =E54 -> 12.5 | G108: =F54 -> 16.666667 | H108: =G54 -> 29.166667 | I108: =H54 -> 16.666667 | J108: =I54 -> 29.166667 | K108: =J54 -> 0 | L108: =L54 -> SÍ
A109: ='06_Presupuesto'!A214 -> B.2.5.1 | B109: ='06_Presupuesto'!B214 -> Q | C109: ='06_Presupuesto'!C214 -> Cerámicos Muros | D109: ='06_Presupuesto'!D214 -> M2 | E109: ='06_Presupuesto'!E214 -> 70 | F109: =E53 -> 16.666667 | G109: =F53 -> 0 | H109: =G53 -> 16.666667 | I109: =H53 -> 0 | J109: =I53 -> 16.666667 | K109: =J53 -> 0 | L109: =L53 -> SÍ
A110: ='06_Presupuesto'!A215 -> B.2.5.2 | B110: ='06_Presupuesto'!B215 -> S | C110: ='06_Presupuesto'!C215 -> Cerámicos Pisos | D110: ='06_Presupuesto'!D215 -> M2 | E110: ='06_Presupuesto'!E215 -> 84 | F110: =E55 -> 10.5 | G110: =F55 -> 16.666667 | H110: =G55 -> 27.166667 | I110: =H55 -> 18.666667 | J110: =I55 -> 29.166667 | K110: =J55 -> 2 | L110: =L55 -> NO
A111: ='06_Presupuesto'!A216 -> B.2.6.1 | B111: ='06_Presupuesto'!B216 -> T | C111: ='06_Presupuesto'!C216 -> Pintura Puertas Exteriores Esmalte Sintético | D111: ='06_Presupuesto'!D216 -> M2 | E111: ='06_Presupuesto'!E216 -> 35 | F111: =E56 -> 20.833333 | G111: =F56 -> 29.166667 | H111: =G56 -> 50 | I111: =H56 -> 29.166667 | J111: =I56 -> 50 | K111: =J56 -> 0 | L111: =L56 -> SÍ
A112: ='06_Presupuesto'!A217 -> B.2.6.2 | B112: ='06_Presupuesto'!B217 -> T | C112: ='06_Presupuesto'!C217 -> Pintura Interior | D112: ='06_Presupuesto'!D217 -> M2 | E112: ='06_Presupuesto'!E217 -> 250 | F112: =E56 -> 20.833333 | G112: =F56 -> 29.166667 | H112: =G56 -> 50 | I112: =H56 -> 29.166667 | J112: =I56 -> 50 | K112: =J56 -> 0 | L112: =L56 -> SÍ
A113: ='06_Presupuesto'!A218 -> B.2.7.1/a) | B113: ='06_Presupuesto'!B218 -> U | C113: ='06_Presupuesto'!C218 -> P1 / Madera Puertas | D113: ='06_Presupuesto'!D218 -> UNI | E113: ='06_Presupuesto'!E218 -> 1 | F113: =E57 -> 16.666667 | G113: =F57 -> 0 | H113: =G57 -> 16.666667 | I113: =H57 -> 33.333333 | J113: =I57 -> 50 | K113: =J57 -> 33.333333 | L113: =L57 -> NO
A114: ='06_Presupuesto'!A219 -> B.2.7.1/b) | B114: ='06_Presupuesto'!B219 -> U | C114: ='06_Presupuesto'!C219 -> P2 / Madera Puertas | D114: ='06_Presupuesto'!D219 -> UNI | E114: ='06_Presupuesto'!E219 -> 2 | F114: =E57 -> 16.666667 | G114: =F57 -> 0 | H114: =G57 -> 16.666667 | I114: =H57 -> 33.333333 | J114: =I57 -> 50 | K114: =J57 -> 33.333333 | L114: =L57 -> NO
A115: ='06_Presupuesto'!A220 -> B.2.7.1/c) | B115: ='06_Presupuesto'!B220 -> U | C115: ='06_Presupuesto'!C220 -> P3 / Madera Puertas | D115: ='06_Presupuesto'!D220 -> UNI | E115: ='06_Presupuesto'!E220 -> 3 | F115: =E57 -> 16.666667 | G115: =F57 -> 0 | H115: =G57 -> 16.666667 | I115: =H57 -> 33.333333 | J115: =I57 -> 50 | K115: =J57 -> 33.333333 | L115: =L57 -> NO
A116: ='06_Presupuesto'!A221 -> B.2.7.1/d) | B116: ='06_Presupuesto'!B221 -> U | C116: ='06_Presupuesto'!C221 -> P4 / Madera Puertas | D116: ='06_Presupuesto'!D221 -> UNI | E116: ='06_Presupuesto'!E221 -> 1 | F116: =E57 -> 16.666667 | G116: =F57 -> 0 | H116: =G57 -> 16.666667 | I116: =H57 -> 33.333333 | J116: =I57 -> 50 | K116: =J57 -> 33.333333 | L116: =L57 -> NO
A117: ='06_Presupuesto'!A222 -> B.2.7.2/a) | B117: ='06_Presupuesto'!B222 -> U | C117: ='06_Presupuesto'!C222 -> P1 / Marcos | D117: ='06_Presupuesto'!D222 -> ML | E117: ='06_Presupuesto'!E222 -> 6 | F117: =E57 -> 16.666667 | G117: =F57 -> 0 | H117: =G57 -> 16.666667 | I117: =H57 -> 33.333333 | J117: =I57 -> 50 | K117: =J57 -> 33.333333 | L117: =L57 -> NO
A118: ='06_Presupuesto'!A223 -> B.2.7.2/b) | B118: ='06_Presupuesto'!B223 -> U | C118: ='06_Presupuesto'!C223 -> P2 / Marcos | D118: ='06_Presupuesto'!D223 -> ML | E118: ='06_Presupuesto'!E223 -> 10 | F118: =E57 -> 16.666667 | G118: =F57 -> 0 | H118: =G57 -> 16.666667 | I118: =H57 -> 33.333333 | J118: =I57 -> 50 | K118: =J57 -> 33.333333 | L118: =L57 -> NO
A119: ='06_Presupuesto'!A224 -> B.2.7.2/c) | B119: ='06_Presupuesto'!B224 -> U | C119: ='06_Presupuesto'!C224 -> P3 / Marcos | D119: ='06_Presupuesto'!D224 -> ML | E119: ='06_Presupuesto'!E224 -> 15 | F119: =E57 -> 16.666667 | G119: =F57 -> 0 | H119: =G57 -> 16.666667 | I119: =H57 -> 33.333333 | J119: =I57 -> 50 | K119: =J57 -> 33.333333 | L119: =L57 -> NO
A120: ='06_Presupuesto'!A225 -> B.2.7.2/d) | B120: ='06_Presupuesto'!B225 -> U | C120: ='06_Presupuesto'!C225 -> P4 / Marcos | D120: ='06_Presupuesto'!D225 -> ML | E120: ='06_Presupuesto'!E225 -> 5 | F120: =E57 -> 16.666667 | G120: =F57 -> 0 | H120: =G57 -> 16.666667 | I120: =H57 -> 33.333333 | J120: =I57 -> 50 | K120: =J57 -> 33.333333 | L120: =L57 -> NO
A121: ='06_Presupuesto'!A226 -> B.2.8/a) | B121: ='06_Presupuesto'!B226 -> U | C121: ='06_Presupuesto'!C226 -> Bisagras | D121: ='06_Presupuesto'!D226 -> UNI | E121: ='06_Presupuesto'!E226 -> 28 | F121: =E57 -> 16.666667 | G121: =F57 -> 0 | H121: =G57 -> 16.666667 | I121: =H57 -> 33.333333 | J121: =I57 -> 50 | K121: =J57 -> 33.333333 | L121: =L57 -> NO
A122: ='06_Presupuesto'!A227 -> B.2.8/b) | B122: ='06_Presupuesto'!B227 -> U | C122: ='06_Presupuesto'!C227 -> Topes de Goma | D122: ='06_Presupuesto'!D227 -> UNI | E122: ='06_Presupuesto'!E227 -> 8 | F122: =E57 -> 16.666667 | G122: =F57 -> 0 | H122: =G57 -> 16.666667 | I122: =H57 -> 33.333333 | J122: =I57 -> 50 | K122: =J57 -> 33.333333 | L122: =L57 -> NO
A123: ='06_Presupuesto'!A228 -> B.2.8/c) | B123: ='06_Presupuesto'!B228 -> U | C123: ='06_Presupuesto'!C228 -> Cerraduras | D123: ='06_Presupuesto'!D228 -> UNI | E123: ='06_Presupuesto'!E228 -> 7 | F123: =E57 -> 16.666667 | G123: =F57 -> 0 | H123: =G57 -> 16.666667 | I123: =H57 -> 33.333333 | J123: =I57 -> 50 | K123: =J57 -> 33.333333 | L123: =L57 -> NO
A124: ='06_Presupuesto'!A229 -> B.2.8/d) | B124: ='06_Presupuesto'!B229 -> U | C124: ='06_Presupuesto'!C229 -> Picaporte de Uñeta | D124: ='06_Presupuesto'!D229 -> UNI | E124: ='06_Presupuesto'!E229 -> 2 | F124: =E57 -> 16.666667 | G124: =F57 -> 0 | H124: =G57 -> 16.666667 | I124: =H57 -> 33.333333 | J124: =I57 -> 50 | K124: =J57 -> 33.333333 | L124: =L57 -> NO
A125: ='06_Presupuesto'!A230 -> B.2.9.1 | B125: ='06_Presupuesto'!B230 -> U | C125: ='06_Presupuesto'!C230 -> Ventanas Con Marco De Aluminio Blanco | D125: ='06_Presupuesto'!D230 -> M2 | E125: ='06_Presupuesto'!E230 -> 15 | F125: =E57 -> 16.666667 | G125: =F57 -> 0 | H125: =G57 -> 16.666667 | I125: =H57 -> 33.333333 | J125: =I57 -> 50 | K125: =J57 -> 33.333333 | L125: =L57 -> NO
A126: ='06_Presupuesto'!A231 -> B.2.9.2 | B126: ='06_Presupuesto'!B231 -> U | C126: ='06_Presupuesto'!C231 -> Quincallería | D126: ='06_Presupuesto'!D231 -> UNI | E126: ='06_Presupuesto'!E231 -> 1 | F126: =E57 -> 16.666667 | G126: =F57 -> 0 | H126: =G57 -> 16.666667 | I126: =H57 -> 33.333333 | J126: =I57 -> 50 | K126: =J57 -> 33.333333 | L126: =L57 -> NO
A127: ='06_Presupuesto'!A232 -> B.2.10 | B127: ='06_Presupuesto'!B232 -> U | C127: ='06_Presupuesto'!C232 -> PROTECCIONES METALICAS TIPO QUEBRAVISTA | D127: ='06_Presupuesto'!D232 -> M2 | E127: ='06_Presupuesto'!E232 -> 15 | F127: =E57 -> 16.666667 | G127: =F57 -> 0 | H127: =G57 -> 16.666667 | I127: =H57 -> 33.333333 | J127: =I57 -> 50 | K127: =J57 -> 33.333333 | L127: =L57 -> NO
A128: ='06_Presupuesto'!A233 -> B.2.11 | B128: ='06_Presupuesto'!B233 -> R | C128: ='06_Presupuesto'!C233 -> CORNISAS | D128: ='06_Presupuesto'!D233 -> ML | E128: ='06_Presupuesto'!E233 -> 78.3 | F128: =E54 -> 12.5 | G128: =F54 -> 16.666667 | H128: =G54 -> 29.166667 | I128: =H54 -> 16.666667 | J128: =I54 -> 29.166667 | K128: =J54 -> 0 | L128: =L54 -> SÍ
A129: ='06_Presupuesto'!A302 -> D.1 | B129: ='06_Presupuesto'!B302 -> U | C129: ='06_Presupuesto'!C302 -> CIERRE PERIMETRAL | D129: ='06_Presupuesto'!D302 -> ML | E129: ='06_Presupuesto'!E302 -> 84 | F129: =E57 -> 16.666667 | G129: =F57 -> 0 | H129: =G57 -> 16.666667 | I129: =H57 -> 33.333333 | J129: =I57 -> 50 | K129: =J57 -> 33.333333 | L129: =L57 -> NO
A130: ='06_Presupuesto'!A303 -> D.2 | B130: ='06_Presupuesto'!B303 -> U | C130: ='06_Presupuesto'!C303 -> PUERTA DE ACCESO | D130: ='06_Presupuesto'!D303 -> UNI | E130: ='06_Presupuesto'!E303 -> 1 | F130: =E57 -> 16.666667 | G130: =F57 -> 0 | H130: =G57 -> 16.666667 | I130: =H57 -> 33.333333 | J130: =I57 -> 50 | K130: =J57 -> 33.333333 | L130: =L57 -> NO
A131: ='06_Presupuesto'!A304 -> D.3 | B131: ='06_Presupuesto'!B304 -> U | C131: ='06_Presupuesto'!C304 -> DEFENSAS DE MURO | D131: ='06_Presupuesto'!D304 -> ML | E131: ='06_Presupuesto'!E304 -> 84 | F131: =E57 -> 16.666667 | G131: =F57 -> 0 | H131: =G57 -> 16.666667 | I131: =H57 -> 33.333333 | J131: =I57 -> 50 | K131: =J57 -> 33.333333 | L131: =L57 -> NO
A132: ='06_Presupuesto'!A305 -> D.4 | B132: ='06_Presupuesto'!B305 -> S | C132: ='06_Presupuesto'!C305 -> TERRAZA ACCESO | D132: ='06_Presupuesto'!D305 -> M2 | E132: ='06_Presupuesto'!E305 -> 18 | F132: =E55 -> 10.5 | G132: =F55 -> 16.666667 | H132: =G55 -> 27.166667 | I132: =H55 -> 18.666667 | J132: =I55 -> 29.166667 | K132: =J55 -> 2 | L132: =L55 -> NO
A133: ='06_Presupuesto'!A306 -> E.1 | B133: ='06_Presupuesto'!B306 -> U | C133: ='06_Presupuesto'!C306 -> ESCAÑO INCLUSIVO | D133: ='06_Presupuesto'!D306 -> UNI | E133: ='06_Presupuesto'!E306 -> 4 | F133: =E57 -> 16.666667 | G133: =F57 -> 0 | H133: =G57 -> 16.666667 | I133: =H57 -> 33.333333 | J133: =I57 -> 50 | K133: =J57 -> 33.333333 | L133: =L57 -> NO
A134: ='06_Presupuesto'!A307 -> F.1 | B134: ='06_Presupuesto'!B307 -> S | C134: ='06_Presupuesto'!C307 -> PREPARACIÓN DE SUELO | D134: ='06_Presupuesto'!D307 -> M2 | E134: ='06_Presupuesto'!E307 -> 210 | F134: =E55 -> 10.5 | G134: =F55 -> 16.666667 | H134: =G55 -> 27.166667 | I134: =H55 -> 18.666667 | J134: =I55 -> 29.166667 | K134: =J55 -> 2 | L134: =L55 -> NO
A135: ='06_Presupuesto'!A308 -> F.2 | B135: ='06_Presupuesto'!B308 -> V | C135: ='06_Presupuesto'!C308 -> AGAVE ATTENUATA | D135: ='06_Presupuesto'!D308 -> UNI | E135: ='06_Presupuesto'!E308 -> 12 | F135: =E58 -> 7.5 | G135: =F58 -> 50 | H135: =G58 -> 57.5 | I135: =H58 -> 50 | J135: =I58 -> 57.5 | K135: =J58 -> 0 | L135: =L58 -> SÍ
A136: ='06_Presupuesto'!A309 -> F.3 | B136: ='06_Presupuesto'!B309 -> V | C136: ='06_Presupuesto'!C309 -> CARDENAL | D136: ='06_Presupuesto'!D309 -> UNI | E136: ='06_Presupuesto'!E309 -> 9 | F136: =E58 -> 7.5 | G136: =F58 -> 50 | H136: =G58 -> 57.5 | I136: =H58 -> 50 | J136: =I58 -> 57.5 | K136: =J58 -> 0 | L136: =L58 -> SÍ
A137: ='06_Presupuesto'!A310 -> F.4 | B137: ='06_Presupuesto'!B310 -> V | C137: ='06_Presupuesto'!C310 -> ADELFA | D137: ='06_Presupuesto'!D310 -> UNI | E137: ='06_Presupuesto'!E310 -> 4 | F137: =E58 -> 7.5 | G137: =F58 -> 50 | H137: =G58 -> 57.5 | I137: =H58 -> 50 | J137: =I58 -> 57.5 | K137: =J58 -> 0 | L137: =L58 -> SÍ
A138: ='06_Presupuesto'!A311 -> F.5 | B138: ='06_Presupuesto'!B311 -> V | C138: ='06_Presupuesto'!C311 -> VISCOTE | D138: ='06_Presupuesto'!D311 -> UNI | E138: ='06_Presupuesto'!E311 -> 5 | F138: =E58 -> 7.5 | G138: =F58 -> 50 | H138: =G58 -> 57.5 | I138: =H58 -> 50 | J138: =I58 -> 57.5 | K138: =J58 -> 0 | L138: =L58 -> SÍ
A139: ='06_Presupuesto'!A312 -> F.6 | B139: ='06_Presupuesto'!B312 -> V | C139: ='06_Presupuesto'!C312 -> JACARANDÁ | D139: ='06_Presupuesto'!D312 -> UNI | E139: ='06_Presupuesto'!E312 -> 4 | F139: =E58 -> 7.5 | G139: =F58 -> 50 | H139: =G58 -> 57.5 | I139: =H58 -> 50 | J139: =I58 -> 57.5 | K139: =J58 -> 0 | L139: =L58 -> SÍ
A140: ='06_Presupuesto'!A313 -> G.1 | B140: ='06_Presupuesto'!B313 -> V | C140: ='06_Presupuesto'!C313 -> INSTALACIÓN PLACA RECORDATORIA | D140: ='06_Presupuesto'!D313 -> UNI | E140: ='06_Presupuesto'!E313 -> 1 | F140: =E58 -> 7.5 | G140: =F58 -> 50 | H140: =G58 -> 57.5 | I140: =H58 -> 50 | J140: =I58 -> 57.5 | K140: =J58 -> 0 | L140: =L58 -> SÍ
A141: ='06_Presupuesto'!A314 -> G.2 | B141: ='06_Presupuesto'!B314 -> V | C141: ='06_Presupuesto'!C314 -> ASEO GENERAL | D141: ='06_Presupuesto'!D314 -> M2 | E141: ='06_Presupuesto'!E314 -> 444.51 | F141: =E58 -> 7.5 | G141: =F58 -> 50 | H141: =G58 -> 57.5 | I141: =H58 -> 50 | J141: =I58 -> 57.5 | K141: =J58 -> 0 | L141: =L58 -> SÍ
A147: RED PERT DEL PROYECTO COMPLETO · ANÁLISIS COMPLEMENTARIO
A150: PASO 4 · MALLA PERT PROBABILÍSTICA · ES3 IND. 4
A151: Estimaciones de tres puntos para riesgos reales de obra: suministro, clima, liberaciones, interferencias, retrabajos y recepción.
A152: te = (to + 4 tm + tp) / 6; varianza = ((tp − to) / 6)². IT/FT: inicio/término temprano; ITa/FTa: inicio/término tardío. Malla exigida de terminaciones y desglose: 06A_PERT_Mallas.
A154: Act. | B154: EDT | C154: Macro-etapa | D154: Partida | E154: Predecesoras | F154: Optimista (to) | G154: Más probable (tm) | H154: Pesimista (tp) | I154: te esperado | J154: Varianza | K154: Desv. estándar | L154: IT | M154: FT | N154: ITa | O154: FTa | P154: Holgura | Q154: Crítica | R154: Riesgo dominante
A155: A | B155: 1.1 | C155: Instalación de faenas | D155: Instalación de faenas y cierre perimetral | E155: — | F155: 5 | G155: ='02_Rendimientos'!K6 -> 6 | H155: 7 | I155: =(F155+4*G155+H155)/6 -> 6 | J155: =((H155-F155)/6)^2 -> 0.11111111 | K155: =SQRT(J155) -> 0.33333333 | L155: =0 -> 0 | M155: =L155+I155 -> 6 | N155: =O155-I155 -> 2.3980817e-14 | O155: =MIN(N156,N157) -> 6 | P155: =ROUND(N155-L155,3) -> 0 | Q155: =IF(ABS(P155)<0.001,"SÍ","NO") -> SÍ | R155: Montaje de faenas y logística
A156: B | B156: 1.2 | C156: Instalación de faenas | D156: Replanteo y nivelación del área de trabajo | E156: A | F156: 4 | G156: ='02_Rendimientos'!K7 -> 5 | H156: 7 | I156: =(F156+4*G156+H156)/6 -> 5.1666667 | J156: =((H156-F156)/6)^2 -> 0.25 | K156: =SQRT(J156) -> 0.5 | L156: =MAX(M155) -> 6 | M156: =L156+I156 -> 11.166667 | N156: =O156-I156 -> 6 | O156: =MIN(N158) -> 11.166667 | P156: =ROUND(N156-L156,3) -> 0 | Q156: =IF(ABS(P156)<0.001,"SÍ","NO") -> SÍ | R156: Disponibilidad topográfica
A157: C | B157: 1.3 | C157: Instalación de faenas | D157: Servicios provisorios y habilitación de instalaciones | E157: A | F157: 7 | G157: ='02_Rendimientos'!K8 -> 10 | H157: 15 | I157: =(F157+4*G157+H157)/6 -> 10.333333 | J157: =((H157-F157)/6)^2 -> 1.7777778 | K157: =SQRT(J157) -> 1.3333333 | L157: =MAX(M155) -> 6 | M157: =L157+I157 -> 16.333333 | N157: =O157-I157 -> 144.83333 | O157: =O177 -> 155.16667 | P157: =ROUND(N157-L157,3) -> 138.833 | Q157: =IF(ABS(P157)<0.001,"SÍ","NO") -> NO | R157: Conexiones provisorias y permisos
A158: D | B158: 2.1 | C158: Obra Gruesa | D158: Excavación y retiro de material | E158: B | F158: 8 | G158: ='02_Rendimientos'!K9 -> 11 | H158: 15 | I158: =(F158+4*G158+H158)/6 -> 11.166667 | J158: =((H158-F158)/6)^2 -> 1.3611111 | K158: =SQRT(J158) -> 1.1666667 | L158: =MAX(M156) -> 11.166667 | M158: =L158+I158 -> 22.333333 | N158: =O158-I158 -> 11.166667 | O158: =MIN(N159) -> 22.333333 | P158: =ROUND(N158-L158,3) -> 0 | Q158: =IF(ABS(P158)<0.001,"SÍ","NO") -> SÍ | R158: Sello de excavación / napa
A159: E | B159: 2.2 | C159: Obra Gruesa | D159: Relleno, humectación y compactación | E159: D | F159: 7 | G159: ='02_Rendimientos'!K10 -> 9 | H159: 13 | I159: =(F159+4*G159+H159)/6 -> 9.3333333 | J159: =((H159-F159)/6)^2 -> 1 | K159: =SQRT(J159) -> 1 | L159: =MAX(M158) -> 22.333333 | M159: =L159+I159 -> 31.666667 | N159: =O159-I159 -> 22.333333 | O159: =MIN(N160,N168) -> 31.666667 | P159: =ROUND(N159-L159,3) -> 0 | Q159: =IF(ABS(P159)<0.001,"SÍ","NO") -> SÍ | R159: Humedad y compactación
A160: F | B160: 2.3 | C160: Obra Gruesa | D160: Emplantillado de hormigón | E160: E | F160: 4 | G160: ='02_Rendimientos'!K11 -> 5 | H160: 8 | I160: =(F160+4*G160+H160)/6 -> 5.3333333 | J160: =((H160-F160)/6)^2 -> 0.44444444 | K160: =SQRT(J160) -> 0.66666667 | L160: =MAX(M159) -> 31.666667 | M160: =L160+I160 -> 37 | N160: =O160-I160 -> 31.666667 | O160: =MIN(N161) -> 37 | P160: =ROUND(N160-L160,3) -> 0 | Q160: =IF(ABS(P160)<0.001,"SÍ","NO") -> SÍ | R160: Curado y liberación de hormigón
A161: G | B161: 2.4 | C161: Obra Gruesa | D161: Fundaciones de hormigón armado | E161: F | F161: 10 | G161: ='02_Rendimientos'!K12 -> 13 | H161: 18 | I161: =(F161+4*G161+H161)/6 -> 13.333333 | J161: =((H161-F161)/6)^2 -> 1.7777778 | K161: =SQRT(J161) -> 1.3333333 | L161: =MAX(M160) -> 37 | M161: =L161+I161 -> 50.333333 | N161: =O161-I161 -> 37 | O161: =MIN(N162,N163,N165) -> 50.333333 | P161: =ROUND(N161-L161,3) -> 0 | Q161: =IF(ABS(P161)<0.001,"SÍ","NO") -> SÍ | R161: Acero, moldajes e inspección
A162: H | B162: 2.5 | C162: Obra Gruesa | D162: Radier y losas de hormigón | E162: G | F162: 9 | G162: ='02_Rendimientos'!K13 -> 12 | H162: 17 | I162: =(F162+4*G162+H162)/6 -> 12.333333 | J162: =((H162-F162)/6)^2 -> 1.7777778 | K162: =SQRT(J162) -> 1.3333333 | L162: =MAX(M161) -> 50.333333 | M162: =L162+I162 -> 62.666667 | N162: =O162-I162 -> 71 | O162: =MIN(N166) -> 83.333333 | P162: =ROUND(N162-L162,3) -> 20.667 | Q162: =IF(ABS(P162)<0.001,"SÍ","NO") -> NO | R162: Clima y curado
A163: I | B163: 2.6 | C163: Obra Gruesa | D163: Estructura metálica y viga reticulada | E163: G | F163: 16 | G163: ='02_Rendimientos'!K14 -> 20 | H163: 28 | I163: =(F163+4*G163+H163)/6 -> 20.666667 | J163: =((H163-F163)/6)^2 -> 4 | K163: =SQRT(J163) -> 2 | L163: =MAX(M161) -> 50.333333 | M163: =L163+I163 -> 71 | N163: =O163-I163 -> 50.333333 | O163: =MIN(N164,N166) -> 71 | P163: =ROUND(N163-L163,3) -> 0 | Q163: =IF(ABS(P163)<0.001,"SÍ","NO") -> SÍ | R163: Suministro y montaje de acero
A164: J | B164: 2.7 | C164: Obra Gruesa | D164: Cubierta y hojalatería | E164: I | F164: 9 | G164: ='02_Rendimientos'!K15 -> 12 | H164: 17 | I164: =(F164+4*G164+H164)/6 -> 12.333333 | J164: =((H164-F164)/6)^2 -> 1.7777778 | K164: =SQRT(J164) -> 1.3333333 | L164: =MAX(M163) -> 71 | M164: =L164+I164 -> 83.333333 | N164: =O164-I164 -> 71 | O164: =MIN(N166,N175) -> 83.333333 | P164: =ROUND(N164-L164,3) -> 0 | Q164: =IF(ABS(P164)<0.001,"SÍ","NO") -> SÍ | R164: Viento y sellos de cubierta
A165: K | B165: 2.8 | C165: Obra Gruesa | D165: Muros y tabiques Metalcon | E165: G | F165: 14 | G165: ='02_Rendimientos'!K16 -> 18 | H165: 25 | I165: =(F165+4*G165+H165)/6 -> 18.5 | J165: =((H165-F165)/6)^2 -> 3.3611111 | K165: =SQRT(J165) -> 1.8333333 | L165: =MAX(M161) -> 50.333333 | M165: =L165+I165 -> 68.833333 | N165: =O165-I165 -> 64.833333 | O165: =MIN(N166,N167,N171,N175) -> 83.333333 | P165: =ROUND(N165-L165,3) -> 14.5 | Q165: =IF(ABS(P165)<0.001,"SÍ","NO") -> NO | R165: Interferencias de modulación
A166: L | B166: 3.1 | C166: Instalaciones | D166: Instalación eléctrica interior | E166: H - I - J - K | F166: 10 | G166: ='02_Rendimientos'!K17 -> 14 | H166: 20 | I166: =(F166+4*G166+H166)/6 -> 14.333333 | J166: =((H166-F166)/6)^2 -> 2.7777778 | K166: =SQRT(J166) -> 1.6666667 | L166: =MAX(M162,M163,M164,M165) -> 83.333333 | M166: =L166+I166 -> 97.666667 | N166: =O166-I166 -> 83.333333 | O166: =MIN(N170,N171) -> 97.666667 | P166: =ROUND(N166-L166,3) -> 0 | Q166: =IF(ABS(P166)<0.001,"SÍ","NO") -> SÍ | R166: Interferencias y pruebas de continuidad
A167: M | B167: 3.2 | C167: Instalaciones | D167: Red de agua potable | E167: K | F167: 9 | G167: ='02_Rendimientos'!K18 -> 12 | H167: 18 | I167: =(F167+4*G167+H167)/6 -> 12.5 | J167: =((H167-F167)/6)^2 -> 2.25 | K167: =SQRT(J167) -> 1.5 | L167: =MAX(M165) -> 68.833333 | M167: =L167+I167 -> 81.333333 | N167: =O167-I167 -> 118.5 | O167: =MIN(N169) -> 131 | P167: =ROUND(N167-L167,3) -> 49.667 | Q167: =IF(ABS(P167)<0.001,"SÍ","NO") -> NO | R167: Materiales y trazado de redes
A168: N | B168: 3.3 | C168: Instalaciones | D168: Red de alcantarillado | E168: E | F168: 10 | G168: ='02_Rendimientos'!K19 -> 14 | H168: 21 | I168: =(F168+4*G168+H168)/6 -> 14.5 | J168: =((H168-F168)/6)^2 -> 3.3611111 | K168: =SQRT(J168) -> 1.8333333 | L168: =MAX(M159) -> 31.666667 | M168: =L168+I168 -> 46.166667 | N168: =O168-I168 -> 116.5 | O168: =MIN(N169) -> 131 | P168: =ROUND(N168-L168,3) -> 84.833 | Q168: =IF(ABS(P168)<0.001,"SÍ","NO") -> NO | R168: Pendientes, lluvias y pruebas
A169: O | B169: 3.4 | C169: Instalaciones | D169: Instalación de artefactos sanitarios | E169: M - N | F169: 6 | G169: ='02_Rendimientos'!K20 -> 8 | H169: 12 | I169: =(F169+4*G169+H169)/6 -> 8.3333333 | J169: =((H169-F169)/6)^2 -> 1 | K169: =SQRT(J169) -> 1 | L169: =MAX(M167,M168) -> 81.333333 | M169: =L169+I169 -> 89.666667 | N169: =O169-I169 -> 131 | O169: =MIN(N170) -> 139.33333 | P169: =ROUND(N169-L169,3) -> 49.667 | Q169: =IF(ABS(P169)<0.001,"SÍ","NO") -> NO | R169: Disponibilidad de artefactos
A170: P | B170: 3.5 | C170: Instalaciones | D170: Pruebas, conexiones y certificaciones | E170: L - O | F170: 6 | G170: ='02_Rendimientos'!K21 -> 8 | H170: 12 | I170: =(F170+4*G170+H170)/6 -> 8.3333333 | J170: =((H170-F170)/6)^2 -> 1 | K170: =SQRT(J170) -> 1 | L170: =MAX(M166,M169) -> 97.666667 | M170: =L170+I170 -> 106 | N170: =O170-I170 -> 139.33333 | O170: =MIN(N176) -> 147.66667 | P170: =ROUND(N170-L170,3) -> 41.667 | Q170: =IF(ABS(P170)<0.001,"SÍ","NO") -> NO | R170: Observaciones de inspección
A171: Q | B171: 4.1 | C171: Terminaciones | D171: Revestimientos interiores | E171: L - K | F171: 12 | G171: ='02_Rendimientos'!K22 -> 16 | H171: 24 | I171: =(F171+4*G171+H171)/6 -> 16.666667 | J171: =((H171-F171)/6)^2 -> 4 | K171: =SQRT(J171) -> 2 | L171: =MAX(M166,M165) -> 97.666667 | M171: =L171+I171 -> 114.33333 | N171: =O171-I171 -> 97.666667 | O171: =MIN(N172,N173) -> 114.33333 | P171: =ROUND(N171-L171,3) -> 0 | Q171: =IF(ABS(P171)<0.001,"SÍ","NO") -> SÍ | R171: Disponibilidad de cuadrillas
A172: R | B172: 4.2 | C172: Terminaciones | D172: Cielos y elementos complementarios | E172: Q | F172: 9 | G172: ='02_Rendimientos'!K23 -> 12 | H172: 18 | I172: =(F172+4*G172+H172)/6 -> 12.5 | J172: =((H172-F172)/6)^2 -> 2.25 | K172: =SQRT(J172) -> 1.5 | L172: =MAX(M171) -> 114.33333 | M172: =L172+I172 -> 126.83333 | N172: =O172-I172 -> 114.33333 | O172: =MIN(N174) -> 126.83333 | P172: =ROUND(N172-L172,3) -> 0 | Q172: =IF(ABS(P172)<0.001,"SÍ","NO") -> SÍ | R172: Secuencia de recintos
A173: S | B173: 4.3 | C173: Terminaciones | D173: Pavimentos | E173: Q | F173: 8 | G173: ='02_Rendimientos'!K24 -> 10 | H173: 15 | I173: =(F173+4*G173+H173)/6 -> 10.5 | J173: =((H173-F173)/6)^2 -> 1.3611111 | K173: =SQRT(J173) -> 1.1666667 | L173: =MAX(M171) -> 114.33333 | M173: =L173+I173 -> 124.83333 | N173: =O173-I173 -> 116.33333 | O173: =MIN(N174) -> 126.83333 | P173: =ROUND(N173-L173,3) -> 2 | Q173: =IF(ABS(P173)<0.001,"SÍ","NO") -> NO | R173: Curado, nivelación y protección
A174: T | B174: 4.4 | C174: Terminaciones | D174: Pinturas interiores y exteriores | E174: R - S | F174: 15 | G174: ='02_Rendimientos'!K25 -> 20 | H174: 30 | I174: =(F174+4*G174+H174)/6 -> 20.833333 | J174: =((H174-F174)/6)^2 -> 6.25 | K174: =SQRT(J174) -> 2.5 | L174: =MAX(M172,M173) -> 126.83333 | M174: =L174+I174 -> 147.66667 | N174: =O174-I174 -> 126.83333 | O174: =MIN(N176) -> 147.66667 | P174: =ROUND(N174-L174,3) -> 0 | Q174: =IF(ABS(P174)<0.001,"SÍ","NO") -> SÍ | R174: Número de manos y clima
A175: U | B175: 4.5 | C175: Terminaciones | D175: Puertas, ventanas y quincallería | E175: J - K | F175: 12 | G175: ='02_Rendimientos'!K26 -> 16 | H175: 24 | I175: =(F175+4*G175+H175)/6 -> 16.666667 | J175: =((H175-F175)/6)^2 -> 4 | K175: =SQRT(J175) -> 2 | L175: =MAX(M164,M165) -> 83.333333 | M175: =L175+I175 -> 100 | N175: =O175-I175 -> 131 | O175: =MIN(N176) -> 147.66667 | P175: =ROUND(N175-L175,3) -> 47.667 | Q175: =IF(ABS(P175)<0.001,"SÍ","NO") -> NO | R175: Fabricación y despacho
A176: V | B176: 4.6 | C176: Terminaciones | D176: Limpieza, remates y entrega | E176: T - U - P | F176: 5 | G176: ='02_Rendimientos'!K27 -> 7 | H176: 12 | I176: =(F176+4*G176+H176)/6 -> 7.5 | J176: =((H176-F176)/6)^2 -> 1.3611111 | K176: =SQRT(J176) -> 1.1666667 | L176: =MAX(M174,M175,M170) -> 147.66667 | M176: =L176+I176 -> 155.16667 | N176: =O176-I176 -> 147.66667 | O176: =O177 -> 155.16667 | P176: =ROUND(N176-L176,3) -> 0 | Q176: =IF(ABS(P176)<0.001,"SÍ","NO") -> SÍ | R176: Punch list y recepción
A177: FIN | B177: — | C177: — | D177: Fin esperado | E177: V | F177: 0 | G177: 0 | H177: 0 | I177: 0 | J177: 0 | K177: 0 | L177: =M177 -> 155.16667 | M177: =MAX(M155:M176) -> 155.16667 | N177: =M177 -> 155.16667 | O177: =M177 -> 155.16667 | P177: 0 | Q177: SÍ | R177: Plazo contractual
A180: RESULTADOS PERT Y DECISIÓN DE PLAZO
A181: Indicador | B181: Resultado | C181: Unidad | D181: Interpretación | F181: Ruta crítica PERT esperada
A182: Plazo determinístico contractual | B182: 150 | C182: días | D182: Plan base cumple el mínimo | F182: A → B → D → E → F → G → I → J → L → Q → R → T → V
A183: Plazo esperado PERT | B183: =M177 -> 155.16667 | C183: días | D183: Promedio ponderado con incertidumbre
A184: Desviación estándar ruta crítica | B184: =SQRT(SUMIF(Q155:Q176,"SÍ",J155:J176)) -> 5.2307849 | C184: días | D184: Variabilidad acumulada
A185: Probabilidad aproximada de terminar ≤ 150 | B185: =NORMDIST('02_Rendimientos'!B80,B183,B184,TRUE) -> 0.16163948 | C185: 0 a 1 | D185: Probabilidad teórica de término ≤150; 150 es mínimo, no máximo contractual. | F185: La aproximación normal usa la ruta crítica esperada y supone independencia. Los tiempos son estimaciones de planificación, no frecuencias observadas. Eventos compartidos pueden correlacionar atrasos.
A193: PERT ESPECÍFICO DE TERMINACIONES | PASO 4
A194: Red sectorial con inicio relativo en día 0. Las predecesoras externas liberan el frente. La correspondencia de los paquetes con el itemizado está en el Paso 6.
A196: Act. | B196: Duración | C196: Predecesoras internas | D196: Partida | E196: IT | F196: FT | G196: ITa | H196: FTa | I196: HT | J196: Crítica
A197: Q | B197: =I171 -> 16.666667 | C197: Inicio del sector | D197: ='03_CPM_Obra_Gruesa'!D161 -> Revestimientos interiores | E197: =0 -> 0 | F197: =E197+B197 -> 16.666667 | G197: =H197-B197 -> 0 | H197: =MIN(G198,G199) -> 16.666667 | I197: =ROUND(G197-E197,6) -> 0 | J197: =IF(ABS(I197)<0.00001,"SÍ","NO") -> SÍ
A198: R | B198: =I172 -> 12.5 | C198: Q | D198: ='03_CPM_Obra_Gruesa'!D162 -> Cielos y elementos complementarios | E198: =MAX(F197) -> 16.666667 | F198: =E198+B198 -> 29.166667 | G198: =H198-B198 -> 16.666667 | H198: =MIN(G200) -> 29.166667 | I198: =ROUND(G198-E198,6) -> 0 | J198: =IF(ABS(I198)<0.00001,"SÍ","NO") -> SÍ
A199: S | B199: =I173 -> 10.5 | C199: Q | D199: ='03_CPM_Obra_Gruesa'!D163 -> Pavimentos | E199: =MAX(F197) -> 16.666667 | F199: =E199+B199 -> 27.166667 | G199: =H199-B199 -> 18.666667 | H199: =MIN(G200) -> 29.166667 | I199: =ROUND(G199-E199,6) -> 2 | J199: =IF(ABS(I199)<0.00001,"SÍ","NO") -> NO
A200: T | B200: =I174 -> 20.833333 | C200: R - S | D200: ='03_CPM_Obra_Gruesa'!D164 -> Pinturas interiores y exteriores | E200: =MAX(F198,F199) -> 29.166667 | F200: =E200+B200 -> 50 | G200: =H200-B200 -> 29.166667 | H200: =MIN(G202) -> 50 | I200: =ROUND(G200-E200,6) -> 0 | J200: =IF(ABS(I200)<0.00001,"SÍ","NO") -> SÍ
A201: U | B201: =I175 -> 16.666667 | C201: Inicio del sector | D201: ='03_CPM_Obra_Gruesa'!D165 -> Puertas, ventanas y quincallería | E201: =0 -> 0 | F201: =E201+B201 -> 16.666667 | G201: =H201-B201 -> 33.333333 | H201: =MIN(G202) -> 50 | I201: =ROUND(G201-E201,6) -> 33.333333 | J201: =IF(ABS(I201)<0.00001,"SÍ","NO") -> NO
A202: V | B202: =I176 -> 7.5 | C202: T - U | D202: ='03_CPM_Obra_Gruesa'!D166 -> Limpieza, remates y entrega | E202: =MAX(F200,F201) -> 50 | F202: =E202+B202 -> 57.5 | G202: =H202-B202 -> 50 | H202: =F203 -> 57.5 | I202: =ROUND(G202-E202,6) -> 0 | J202: =IF(ABS(I202)<0.00001,"SÍ","NO") -> SÍ
D203: Duración del sector | F203: =MAX(F197:F202) -> 57.5
...

Sheet 05_Carta_Gantt
A1: PASO 5 · CARTA GANTT MAESTRA · ES3 IND. 5
A2: Inicio 02-11-2026. Las fechas se enlazan al CPM. Días corridos incluyen fines de semana; no se asume trabajo diario de cada persona.
A5: Inicio del plan | B5: ='02_Rendimientos'!B79 -> 46328 | D5: Duración total | E5: ='03_CPM_Obra_Gruesa'!H167 -> 150 | G5: Término | H5: =B5+E5-1 -> 46477
A8: EDT | B8: Macro-etapa | C8: Nombre de actividad | D8: Duración (d) | E8: Fecha inicio | F8: Fecha fin | G8: Predecesoras | H8: Crítica CPM | I8: Sucesoras | J8: Control / frente | K8: =$B$5+0 -> 46328 | L8: =$B$5+7 -> 46335 | M8: =$B$5+14 -> 46342 | N8: =$B$5+21 -> 46349 | O8: =$B$5+28 -> 46356 | P8: =$B$5+35 -> 46363 | Q8: =$B$5+42 -> 46370 | R8: =$B$5+49 -> 46377 | S8: =$B$5+56 -> 46384 | T8: =$B$5+63 -> 46391 | U8: =$B$5+70 -> 46398 | V8: =$B$5+77 -> 46405 | W8: =$B$5+84 -> 46412 | X8: =$B$5+91 -> 46419 | Y8: =$B$5+98 -> 46426 | Z8: =$B$5+105 -> 46433 | AA8: =$B$5+112 -> 46440 | AB8: =$B$5+119 -> 46447 | AC8: =$B$5+126 -> 46454 | AD8: =$B$5+133 -> 46461 | AE8: =$B$5+140 -> 46468 | AF8: =$B$5+147 -> 46475
A9: 1.1 | B9: Instalación de faenas | C9: Instalación de faenas y cierre perimetral | D9: ='03_CPM_Obra_Gruesa'!E145 -> 6 | E9: =$B$5+'03_CPM_Obra_Gruesa'!G145 -> 46328 | F9: =$B$5+'03_CPM_Obra_Gruesa'!H145-1 -> 46333 | G9: — | H9: ='03_CPM_Obra_Gruesa'!M145 -> SÍ | I9: B, C | J9: Programación por frente paralelo
A10: 1.2 | B10: Instalación de faenas | C10: Replanteo y nivelación del área de trabajo | D10: ='03_CPM_Obra_Gruesa'!E146 -> 5 | E10: =$B$5+'03_CPM_Obra_Gruesa'!G146 -> 46334 | F10: =$B$5+'03_CPM_Obra_Gruesa'!H146-1 -> 46338 | G10: A | H10: ='03_CPM_Obra_Gruesa'!M146 -> SÍ | I10: D | J10: Programación por frente paralelo
A11: 1.3 | B11: Instalación de faenas | C11: Servicios provisorios y habilitación de instalaciones | D11: ='03_CPM_Obra_Gruesa'!E147 -> 10 | E11: =$B$5+'03_CPM_Obra_Gruesa'!G147 -> 46334 | F11: =$B$5+'03_CPM_Obra_Gruesa'!H147-1 -> 46343 | G11: A | H11: ='03_CPM_Obra_Gruesa'!M147 -> NO | I11: FIN | J11: Programación por frente paralelo
A12: 2.1 | B12: Obra Gruesa | C12: Excavación y retiro de material | D12: ='03_CPM_Obra_Gruesa'!E148 -> 11 | E12: =$B$5+'03_CPM_Obra_Gruesa'!G148 -> 46339 | F12: =$B$5+'03_CPM_Obra_Gruesa'!H148-1 -> 46349 | G12: B | H12: ='03_CPM_Obra_Gruesa'!M148 -> SÍ | I12: E | J12: Programación por frente paralelo
A13: 2.2 | B13: Obra Gruesa | C13: Relleno, humectación y compactación | D13: ='03_CPM_Obra_Gruesa'!E149 -> 9 | E13: =$B$5+'03_CPM_Obra_Gruesa'!G149 -> 46350 | F13: =$B$5+'03_CPM_Obra_Gruesa'!H149-1 -> 46358 | G13: D | H13: ='03_CPM_Obra_Gruesa'!M149 -> SÍ | I13: F, N | J13: Programación por frente paralelo
A14: 2.3 | B14: Obra Gruesa | C14: Emplantillado de hormigón | D14: ='03_CPM_Obra_Gruesa'!E150 -> 5 | E14: =$B$5+'03_CPM_Obra_Gruesa'!G150 -> 46359 | F14: =$B$5+'03_CPM_Obra_Gruesa'!H150-1 -> 46363 | G14: E | H14: ='03_CPM_Obra_Gruesa'!M150 -> SÍ | I14: G | J14: Programación por frente paralelo
A15: 2.4 | B15: Obra Gruesa | C15: Fundaciones de hormigón armado | D15: ='03_CPM_Obra_Gruesa'!E151 -> 13 | E15: =$B$5+'03_CPM_Obra_Gruesa'!G151 -> 46364 | F15: =$B$5+'03_CPM_Obra_Gruesa'!H151-1 -> 46376 | G15: F | H15: ='03_CPM_Obra_Gruesa'!M151 -> SÍ | I15: H, I, K | J15: Programación por frente paralelo
A16: 2.5 | B16: Obra Gruesa | C16: Radier y losas de hormigón | D16: ='03_CPM_Obra_Gruesa'!E152 -> 12 | E16: =$B$5+'03_CPM_Obra_Gruesa'!G152 -> 46377 | F16: =$B$5+'03_CPM_Obra_Gruesa'!H152-1 -> 46388 | G16: G | H16: ='03_CPM_Obra_Gruesa'!M152 -> NO | I16: L | J16: Programación por frente paralelo
A17: 2.6 | B17: Obra Gruesa | C17: Estructura metálica y viga reticulada | D17: ='03_CPM_Obra_Gruesa'!E153 -> 20 | E17: =$B$5+'03_CPM_Obra_Gruesa'!G153 -> 46377 | F17: =$B$5+'03_CPM_Obra_Gruesa'!H153-1 -> 46396 | G17: G | H17: ='03_CPM_Obra_Gruesa'!M153 -> SÍ | I17: J, L | J17: Programación por frente paralelo
A18: 2.7 | B18: Obra Gruesa | C18: Cubierta y hojalatería | D18: ='03_CPM_Obra_Gruesa'!E154 -> 12 | E18: =$B$5+'03_CPM_Obra_Gruesa'!G154 -> 46397 | F18: =$B$5+'03_CPM_Obra_Gruesa'!H154-1 -> 46408 | G18: I | H18: ='03_CPM_Obra_Gruesa'!M154 -> SÍ | I18: L, U | J18: Programación por frente paralelo
A19: 2.8 | B19: Obra Gruesa | C19: Muros y tabiques Metalcon | D19: ='03_CPM_Obra_Gruesa'!E155 -> 18 | E19: =$B$5+'03_CPM_Obra_Gruesa'!G155 -> 46377 | F19: =$B$5+'03_CPM_Obra_Gruesa'!H155-1 -> 46394 | G19: G | H19: ='03_CPM_Obra_Gruesa'!M155 -> NO | I19: L, M, Q, U | J19: Programación por frente paralelo
A20: 3.1 | B20: Instalaciones | C20: Instalación eléctrica interior | D20: ='03_CPM_Obra_Gruesa'!E156 -> 14 | E20: =$B$5+'03_CPM_Obra_Gruesa'!G156 -> 46409 | F20: =$B$5+'03_CPM_Obra_Gruesa'!H156-1 -> 46422 | G20: H - I - J - K | H20: ='03_CPM_Obra_Gruesa'!M156 -> SÍ | I20: P, Q | J20: Programación por frente paralelo
... A30: 4.6 | B30: Terminaciones | C30: Limpieza, remates y entrega | D30: ='03_CPM_Obra_Gruesa'!E166 -> 7 | E30: =$B$5+'03_CPM_Obra_Gruesa'!G166 -> 46471 | F30: =$B$5+'03_CPM_Obra_Gruesa'!H166-1 -> 46477 | G30: T - U - P | H30: ='03_CPM_Obra_Gruesa'!M166 -> SÍ | I30: FIN | J30: Programación por frente paralelo
A33: RESUMEN POR MACRO-ETAPA
A34: Macro-etapa | B34: Fecha inicio | C34: Fecha fin | D34: Intervalo (d) | E34: Peso de referencia | F34: Interpretación
A35: Instalación de faenas | B35: =MIN(E9:E11) -> 46328 | C35: =MAX(F9:F11) -> 46343 | D35: =C35-B35+1 -> 16 | E35: 0.08 | F35: Etapas solapadas; no sumar sus intervalos.
A36: Obra Gruesa | B36: =MIN(E12:E19) -> 46339 | C36: =MAX(F12:F19) -> 46408 | D36: =C36-B36+1 -> 70 | E36: 0.38 | F36: Etapas solapadas; no sumar sus intervalos.
A37: Instalaciones | B37: =MIN(E20:E24) -> 46359 | C37: =MAX(F20:F24) -> 46430 | D37: =C37-B37+1 -> 72 | E37: 0.22 | F37: Etapas solapadas; no sumar sus intervalos.
A38: Terminaciones | B38: =MIN(E25:E30) -> 46409 | C38: =MAX(F25:F30) -> 46477 | D38: =C38-B38+1 -> 69 | E38: 0.32 | F38: Etapas solapadas; no sumar sus intervalos.
A40: Ponderaciones por macroetapa del programa base: 8% instalación de faenas, 38% obra gruesa, 22% instalaciones y 32% terminaciones. Las actividades se solapan según sus precedencias.

Sheet 06_Presupuesto
B1: PASO 6 · PRESUPUESTO DETALLADO Y COMPENSADO · ES3 IND. 6
B2: PRESUPUESTO DETALLADO Y COMPENSADO
B3: Sede Social El Bosque · Grupo 4 · 140 partidas · montos CLP · factor único aplicado a cada precio unitario
B5: FACTOR DE COMPENSACIÓN | I5: =(1+'02_Rendimientos'!B83+'02_Rendimientos'!B84)*(1+'02_Rendimientos'!B82) -> 1.4875 | K5: (1 + GG 15% + utilidad 10%) × (1 + IVA 19%)
B7: PRESUPUESTO NORMAL · COSTO DIRECTO NETO | K7: PRESUPUESTO COMPENSADO · PRECIO FINAL CON IVA
B8: Ítem | C8: Partida | D8: Unidad | E8: Cantidad | F8: P. unitario normal neto | G8: Subtotal normal neto | K8: Ítem | L8: Partida | M8: Unidad | N8: Cantidad | O8: P. unitario compensado | P8: Subtotal compensado
B9: ='06_Presupuesto'!A175 -> A.1.1/a) | C9: ='06_Presupuesto'!C175 -> Oficina (con servicios básicos) | D9: ='06_Presupuesto'!D175 -> UNI | E9: ='06_Presupuesto'!E175 -> 1 | F9: ='06_Presupuesto'!G175 -> 1764705.9 | G9: =E9*F9 -> 1764705.9 | K9: =B9 -> A.1.1/a) | L9: =C9 -> Oficina (con servicios básicos) | M9: =D9 -> UNI | N9: =E9 -> 1 | O9: =F9*$I$5 -> 2625000 | P9: =N9*O9 -> 2625000
B10: ='06_Presupuesto'!A176 -> A.1.1/b) | C10: ='06_Presupuesto'!C176 -> Bodega de Materiales | D10: ='06_Presupuesto'!D176 -> UNI | E10: ='06_Presupuesto'!E176 -> 1 | F10: ='06_Presupuesto'!G176 -> 1008403.4 | G10: =E10*F10 -> 1008403.4 | K10: =B10 -> A.1.1/b) | L10: =C10 -> Bodega de Materiales | M10: =D10 -> UNI | N10: =E10 -> 1 | O10: =F10*$I$5 -> 1500000 | P10: =N10*O10 -> 1500000
B11: ='06_Presupuesto'!A177 -> A.1.1/c) | C11: ='06_Presupuesto'!C177 -> Servicios higiénicos tipo químicos | D11: ='06_Presupuesto'!D177 -> UNI | E11: ='06_Presupuesto'!E177 -> 2 | F11: ='06_Presupuesto'!G177 -> 714285.71 | G11: =E11*F11 -> 1428571.4 | K11: =B11 -> A.1.1/c) | L11: =C11 -> Servicios higiénicos tipo químicos | M11: =D11 -> UNI | N11: =E11 -> 2 | O11: =F11*$I$5 -> 1062500 | P11: =N11*O11 -> 2125000
B12: ='06_Presupuesto'!A178 -> A.1.1/d) | C12: ='06_Presupuesto'!C178 -> Comedor | D12: ='06_Presupuesto'!D178 -> M2 | E12: ='06_Presupuesto'!E178 -> 10 | F12: ='06_Presupuesto'!G178 -> 71428.571 | G12: =E12*F12 -> 714285.71 | K12: =B12 -> A.1.1/d) | L12: =C12 -> Comedor | M12: =D12 -> M2 | N12: =E12 -> 10 | O12: =F12*$I$5 -> 106250 | P12: =N12*O12 -> 1062500
B13: ='06_Presupuesto'!A179 -> A.1.2 | C13: ='06_Presupuesto'!C179 -> CIERRE PROVISORIO | D13: ='06_Presupuesto'!D179 -> ML | E13: ='06_Presupuesto'!E179 -> 84 | F13: ='06_Presupuesto'!G179 -> 12184.874 | G13: =E13*F13 -> 1023529.4 | K13: =B13 -> A.1.2 | L13: =C13 -> CIERRE PROVISORIO | M13: =D13 -> ML | N13: =E13 -> 84 | O13: =F13*$I$5 -> 18125 | P13: =N13*O13 -> 1522500
B14: ='06_Presupuesto'!A180 -> A.1.3 | C14: ='06_Presupuesto'!C180 -> LETRERO DE OBRA | D14: ='06_Presupuesto'!D180 -> UNI | E14: ='06_Presupuesto'!E180 -> 1 | F14: ='06_Presupuesto'!G180 -> 327731.09 | G14: =E14*F14 -> 327731.09 | K14: =B14 -> A.1.3 | L14: =C14 -> LETRERO DE OBRA | M14: =D14 -> UNI | N14: =E14 -> 1 | O14: =F14*$I$5 -> 487500 | P14: =N14*O14 -> 487500
B15: ='06_Presupuesto'!A181 -> A.2.1 | C15: ='06_Presupuesto'!C181 -> Limpieza y despeje de Terreno | D15: ='06_Presupuesto'!D181 -> M2 | E15: ='06_Presupuesto'!E181 -> 444.51 | F15: ='06_Presupuesto'!G181 -> 1848.7395 | G15: =E15*F15 -> 821783.19 | K15: =B15 -> A.2.1 | L15: =C15 -> Limpieza y despeje de Terreno | M15: =D15 -> M2 | N15: =E15 -> 444.51 | O15: =F15*$I$5 -> 2750 | P15: =N15*O15 -> 1222402.5
B16: ='06_Presupuesto'!A182 -> A.2.2 | C16: ='06_Presupuesto'!C182 -> Replanteo, trazado y niveles | D16: ='06_Presupuesto'!D182 -> M2 | E16: ='06_Presupuesto'!E182 -> 444.51 | F16: ='06_Presupuesto'!G182 -> 1764.7059 | G16: =E16*F16 -> 784429.41 | K16: =B16 -> A.2.2 | L16: =C16 -> Replanteo, trazado y niveles | M16: =D16 -> M2 | N16: =E16 -> 444.51 | O16: =F16*$I$5 -> 2625 | P16: =N16*O16 -> 1166838.7
B17: ='06_Presupuesto'!A183 -> B.1.1.1 | C17: ='06_Presupuesto'!C183 -> Excavaciones | D17: ='06_Presupuesto'!D183 -> M3 | E17: ='06_Presupuesto'!E183 -> 15 | F17: ='06_Presupuesto'!G183 -> 35294.118 | G17: =E17*F17 -> 529411.76 | K17: =B17 -> B.1.1.1 | L17: =C17 -> Excavaciones | M17: =D17 -> M3 | N17: =E17 -> 15 | O17: =F17*$I$5 -> 52500 | P17: =N17*O17 -> 787500
B18: ='06_Presupuesto'!A184 -> B.1.1.2 | C18: ='06_Presupuesto'!C184 -> Emplantillado | D18: ='06_Presupuesto'!D184 -> M2 | E18: ='06_Presupuesto'!E184 -> 23 | F18: ='06_Presupuesto'!G184 -> 16386.555 | G18: =E18*F18 -> 376890.76 | K18: =B18 -> B.1.1.2 | L18: =C18 -> Emplantillado | M18: =D18 -> M2 | N18: =E18 -> 23 | O18: =F18*$I$5 -> 24375 | P18: =N18*O18 -> 560625
B19: ='06_Presupuesto'!A185 -> B.1.1.3 | C19: ='06_Presupuesto'!C185 -> Cimientos | D19: ='06_Presupuesto'!D185 -> M3 | E19: ='06_Presupuesto'!E185 -> 14 | F19: ='06_Presupuesto'!G185 -> 189075.63 | G19: =E19*F19 -> 2647058.8 | K19: =B19 -> B.1.1.3 | L19: =C19 -> Cimientos | M19: =D19 -> M3 | N19: =E19 -> 14 | O19: =F19*$I$5 -> 281250 | P19: =N19*O19 -> 3937500
B20: ='06_Presupuesto'!A186 -> B.1.2.1 | C20: ='06_Presupuesto'!C186 -> Preparación de la subrasante | D20: ='06_Presupuesto'!D186 -> M2 | E20: ='06_Presupuesto'!E186 -> 143 | F20: ='06_Presupuesto'!G186 -> 2689.0756 | G20: =E20*F20 -> 384537.82 | K20: =B20 -> B.1.2.1 | L20: =C20 -> Preparación de la subrasante | M20: =D20 -> M2 | N20: =E20 -> 143 | O20: =F20*$I$5 -> 4000 | P20: =N20*O20 -> 572000
... B148: ='06_Presupuesto'!A314 -> G.2 | C148: ='06_Presupuesto'!C314 -> ASEO GENERAL | D148: ='06_Presupuesto'!D314 -> M2 | E148: ='06_Presupuesto'!E314 -> 444.51 | F148: ='06_Presupuesto'!G314 -> 1512.605 | G148: =E148*F148 -> 672368.07 | K148: =B148 -> G.2 | L148: =C148 -> ASEO GENERAL | M148: =D148 -> M2 | N148: =E148 -> 444.51 | O148: =F148*$I$5 -> 2250 | P148: =N148*O148 -> 1000147.5
B150: RESUMEN DEL COSTO NORMAL | K150: RESULTADO COMPENSADO
B151: Costo directo neto | G151: =SUM(G9:G148) -> 72760094 | K151: Total compensado | P151: =ROUND(SUM(P9:P148),0) -> 108230640
B152: Gastos generales (15%) | G152: =G151*'02_Rendimientos'!B83 -> 10914014 | K152: Factor aplicado | P152: =I5 -> 1.4875
B153: Utilidad ofertada (10%) | G153: =G151*'02_Rendimientos'!B84 -> 7276009.4 | K153: Diferencia con presupuesto ES3 | P153: =P151-'06_Presupuesto'!H323 -> 0
B154: Subtotal neto | G154: =SUM(G151:G153) -> 90950118 | K154: Presupuesto municipal | P154: ='02_Rendimientos'!B81 -> 114446607
B155: IVA (19%) | G155: =G154*'02_Rendimientos'!B82 -> 17280522 | K155: Ahorro de la propuesta | P155: =P154-P151 -> 6215967
B156: TOTAL DE LA OFERTA | G156: =ROUND(G154+G155,0) -> 108230640 | K156: Ahorro porcentual | P156: =P155/P154 -> 0.054313248
B159: Método: precio unitario compensado = precio unitario normal neto × factor. El subtotal se obtiene multiplicando por la cantidad.
B160: El factor incorpora gastos generales y utilidad sobre el costo directo; después aplica IVA. Los 140 ítems se desglosan a continuación en esta hoja.
B167: DESGLOSE BASE Y CRITERIOS DEL PRESUPUESTO COMPENSADO
A170: PASO 6 | PRESUPUESTO DETALLADO Y OFERTA COMPENSADA
A171: Cantidades: 5-PPTO..xlsx. Precios instalados estimados en CLP, orientados a una oferta competitiva; no son precios oficiales. GG 15%; utilidad propuesta 10% frente a 15% del formulario.
A172: Vista base del presupuesto, incorporada en esta misma hoja.
A174: Código municipal | B174: Act. CPM | C174: Partida / alcance | D174: Unidad | E174: Cantidad | F174: P.U. ref. con IVA | G174: P.U. neto | H174: Costo directo | I174: Venta neta | J174: Inicio plan | K174: Fin plan | L174: Fila fuente / pago
A175: A.1.1/a) | B175: A | C175: Oficina (con servicios básicos) | D175: UNI | E175: 1 | F175: 2100000 | G175: =F175/(1+'02_Rendimientos'!$B$82) -> 1764705.9 | H175: =E175*G175 -> 1764705.9 | I175: =H175*(1+'02_Rendimientos'!$B$83+'02_Rendimientos'!$B$84) -> 2205882.4 | J175: ='05_Carta_Gantt'!E9 -> 46328 | K175: ='05_Carta_Gantt'!F9 -> 46333 | L175: PPTO fila 11
A176: A.1.1/b) | B176: A | C176: Bodega de Materiales | D176: UNI | E176: 1 | F176: 1200000 | G176: =F176/(1+'02_Rendimientos'!$B$82) -> 1008403.4 | H176: =E176*G176 -> 1008403.4 | I176: =H176*(1+'02_Rendimientos'!$B$83+'02_Rendimientos'!$B$84) -> 1260504.2 | J176: ='05_Carta_Gantt'!E9 -> 46328 | K176: ='05_Carta_Gantt'!F9 -> 46333 | L176: PPTO fila 12
A177: A.1.1/c) | B177: A | C177: Servicios higiénicos tipo químicos | D177: UNI | E177: 2 | F177: 850000 | G177: =F177/(1+'02_Rendimientos'!$B$82) -> 714285.71 | H177: =E177*G177 -> 1428571.4 | I177: =H177*(1+'02_Rendimientos'!$B$83+'02_Rendimientos'!$B$84) -> 1785714.3 | J177: ='05_Carta_Gantt'!E9 -> 46328 | K177: ='05_Carta_Gantt'!F9 -> 46333 | L177: PPTO fila 13
A178: A.1.1/d) | B178: A | C178: Comedor | D178: M2 | E178: 10 | F178: 85000 | G178: =F178/(1+'02_Rendimientos'!$B$82) -> 71428.571 | H178: =E178*G178 -> 714285.71 | I178: =H178*(1+'02_Rendimientos'!$B$83+'02_Rendimientos'!$B$84) -> 892857.14 | J178: ='05_Carta_Gantt'!E9 -> 46328 | K178: ='05_Carta_Gantt'!F9 -> 46333 | L178: PPTO fila 14
A179: A.1.2 | B179: A | C179: CIERRE PROVISORIO | D179: ML | E179: 84 | F179: 14500 | G179: =F179/(1+'02_Rendimientos'!$B$82) -> 12184.874 | H179: =E179*G179 -> 1023529.4 | I179: =H179*(1+'02_Rendimientos'!$B$83+'02_Rendimientos'!$B$84) -> 1279411.8 | J179: ='05_Carta_Gantt'!E9 -> 46328 | K179: ='05_Carta_Gantt'!F9 -> 46333 | L179: PPTO fila 15
A180: A.1.3 | B180: A | C180: LETRERO DE OBRA | D180: UNI | E180: 1 | F180: 390000 | G180: =F180/(1+'02_Rendimientos'!$B$82) -> 327731.09 | H180: =E180*G180 -> 327731.09 | I180: =H180*(1+'02_Rendimientos'!$B$83+'02_Rendimientos'!$B$84) -> 409663.87 | J180: ='05_Carta_Gantt'!E9 -> 46328 | K180: ='05_Carta_Gantt'!F9 -> 46333 | L180: PPTO fila 16
A181: A.2.1 | B181: A | C181: Limpieza y despeje de Terreno | D181: M2 | E181: 444.51 | F181: 2200 | G181: =F181/(1+'02_Rendimientos'!$B$82) -> 1848.7395 | H181: =E181*G181 -> 821783.19 | I181: =H181*(1+'02_Rendimientos'!$B$83+'02_Rendimientos'!$B$84) -> 1027229 | J181: ='05_Carta_Gantt'!E9 -> 46328 | K181: ='05_Carta_Gantt'!F9 -> 46333 | L181: PPTO fila 18
A182: A.2.2 | B182: B | C182: Replanteo, trazado y niveles | D182: M2 | E182: 444.51 | F182: 2100 | G182: =F182/(1+'02_Rendimientos'!$B$82) -> 1764.7059 | H182: =E182*G182 -> 784429.41 | I182: =H182*(1+'02_Rendimientos'!$B$83+'02_Rendimientos'!$B$84) -> 980536.76 | J182: ='05_Carta_Gantt'!E10 -> 46334 | K182: ='05_Carta_Gantt'!F10 -> 46338 | L182: PPTO fila 19
A183: B.1.1.1 | B183: D | C183: Excavaciones | D183: M3 | E183: 15 | F183: 42000 | G183: =F183/(1+'02_Rendimientos'!$B$82) -> 35294.118 | H183: =E183*G183 -> 529411.76 | I183: =H183*(1+'02_Rendimientos'!$B$83+'02_Rendimientos'!$B$84) -> 661764.71 | J183: ='05_Carta_Gantt'!E12 -> 46339 | K183: ='05_Carta_Gantt'!F12 -> 46349 | L183: PPTO fila 24
A184: B.1.1.2 | B184: F | C184: Emplantillado | D184: M2 | E184: 23 | F184: 19500 | G184: =F184/(1+'02_Rendimientos'!$B$82) -> 16386.555 | H184: =E184*G184 -> 376890.76 | I184: =H184*(1+'02_Rendimientos'!$B$83+'02_Rendimientos'!$B$84) -> 471113.45 | J184: ='05_Carta_Gantt'!E14 -> 46359 | K184: ='05_Carta_Gantt'!F14 -> 46363 | L184: PPTO fila 25
A185: B.1.1.3 | B185: G | C185: Cimientos | D185: M3 | E185: 14 | F185: 225000 | G185: =F185/(1+'02_Rendimientos'!$B$82) -> 189075.63 | H185: =E185*G185 -> 2647058.8 | I185: =H185*(1+'02_Rendimientos'!$B$83+'02_Rendimientos'!$B$84) -> 3308823.5 | J185: ='05_Carta_Gantt'!E15 -> 46364 | K185: ='05_Carta_Gantt'!F15 -> 46376 | L185: PPTO fila 26
A186: B.1.2.1 | B186: E | C186: Preparación de la subrasante | D186: M2 | E186: 143 | F186: 3200 | G186: =F186/(1+'02_Rendimientos'!$B$82) -> 2689.0756 | H186: =E186*G186 -> 384537.82 | I186: =H186*(1+'02_Rendimientos'!$B$83+'02_Rendimientos'!$B$84) -> 480672.27 | J186: ='05_Carta_Gantt'!E13 -> 46350 | K186: ='05_Carta_Gantt'!F13 -> 46358 | L186: PPTO fila 28
A187: B.1.2.2 | B187: E | C187: Base Estabilizada e=8cm | D187: M3 | E187: 11.44 | F187: 42000 | G187: =F187/(1+'02_Rendimientos'!$B$82) -> 35294.118 | H187: =E187*G187 -> 403764.71 | I187: =H187*(1+'02_Rendimientos'!$B$83+'02_Rendimientos'!$B$84) -> 504705.88 | J187: ='05_Carta_Gantt'!E13 -> 46350 | K187: ='05_Carta_Gantt'!F13 -> 46358 | L187: PPTO fila 29
A188: B.1.2.3 | B188: H | C188: Impermeabilización film de Polietileno e=0,10mm | D188: M2 | E188: 143 | F188: 1600 | G188: =F188/(1+'02_Rendimientos'!$B$82) -> 1344.5378 | H188: =E188*G188 -> 192268.91 | I188: =H188*(1+'02_Rendimientos'!$B$83+'02_Rendimientos'!$B$84) -> 240336.13 | J188: ='05_Carta_Gantt'!E16 -> 46377 | K188: ='05_Carta_Gantt'!F16 -> 46388 | L188: PPTO fila 30
A189: B.1.2.4 | B189: H | C189: Cama de Ripio e=8cm | D189: M3 | E189: 11.44 | F189: 45000 | G189: =F189/(1+'02_Rendimientos'!$B$82) -> 37815.126 | H189: =E189*G189 -> 432605.04 | I189: =H189*(1+'02_Rendimientos'!$B$83+'02_Rendimientos'!$B$84) -> 540756.3 | J189: ='05_Carta_Gantt'!E16 -> 46377 | K189: ='05_Carta_Gantt'!F16 -> 46388 | L189: PPTO fila 31
A190: B.1.2.5 | B190: H | C190: Malla Acma C-92 | D190: M2 | E190: 143 | F190: 5400 | G190: =F190/(1+'02_Rendimientos'!$B$82) -> 4537.8151 | H190: =E190*G190 -> 648907.56 | I190: =H190*(1+'02_Rendimientos'!$B$83+'02_Rendimientos'!$B$84) -> 811134.45 | J190: ='05_Carta_Gantt'!E16 -> 46377 | K190: ='05_Carta_Gantt'!F16 -> 46388 | L190: PPTO fila 32
A191: B.1.2.6 | B191: H | C191: Radier e= 7cm | D191: M2 | E191: 143 | F191: 15800 | G191: =F191/(1+'02_Rendimientos'!$B$82) -> 13277.311 | H191: =E191*G191 -> 1898655.5 | I191: =H191*(1+'02_Rendimientos'!$B$83+'02_Rendimientos'!$B$84) -> 2373319.3 | J191: ='05_Carta_Gantt'!E16 -> 46377 | K191: ='05_Carta_Gantt'!F16 -> 46388 | L191: PPTO fila 33
A192: B.1.3.1 | B192: E | C192: Estabilizado Compactado e=20cm | D192: M3 | E192: 18.65 | F192: 44000 | G192: =F192/(1+'02_Rendimientos'!$B$82) -> 36974.79 | H192: =E192*G192 -> 689579.83 | I192: =H192*(1+'02_Rendimientos'!$B$83+'02_Rendimientos'!$B$84) -> 861974.79 | J192: ='05_Carta_Gantt'!E13 -> 46350 | K192: ='05_Carta_Gantt'!F13 -> 46358 | L192: PPTO fila 35
A193: B.1.3.2 | B193: E | C193: Ripio Compactado e=10cm | D193: M3 | E193: 9.324 | F193: 46000 | G193: =F193/(1+'02_Rendimientos'!$B$82) -> 38655.462 | H193: =E193*G193 -> 360423.53 | I193: =H193*(1+'02_Rendimientos'!$B$83+'02_Rendimientos'!$B$84) -> 450529.41 | J193: ='05_Carta_Gantt'!E13 -> 46350 | K193: ='05_Carta_Gantt'!F13 -> 46358 | L193: PPTO fila 36
A194: B.1.3.3 | B194: H | C194: Polietileno e=0,15mm | D194: M2 | E194: 93.24 | F194: 1800 | G194: =F194/(1+'02_Rendimientos'!$B$82) -> 1512.605 | H194: =E194*G194 -> 141035.29 | I194: =H194*(1+'02_Rendimientos'!$B$83+'02_Rendimientos'!$B$84) -> 176294.12 | J194: ='05_Carta_Gantt'!E16 -> 46377 | K194: ='05_Carta_Gantt'!F16 -> 46388 | L194: PPTO fila 37
A195: B.1.3.4 | B195: H | C195: Radier e=10cm | D195: M2 | E195: 93.24 | F195: 19800 | G195: =F195/(1+'02_Rendimientos'!$B$82) -> 16638.655 | H195: =E195*G195 -> 1551388.2 | I195: =H195*(1+'02_Rendimientos'!$B$83+'02_Rendimientos'!$B$84) -> 1939235.3 | J195: ='05_Carta_Gantt'!E16 -> 46377 | K195: ='05_Carta_Gantt'!F16 -> 46388 | L195: PPTO fila 38
A196: B.1.4.1 | B196: K | C196: Estructura de Metalcon en Muros | D196: M2 | E196: 236 | F196: 25800 | G196: =F196/(1+'02_Rendimientos'!$B$82) -> 21680.672 | H196: =E196*G196 -> 5116638.7 | I196: =H196*(1+'02_Rendimientos'!$B$83+'02_Rendimientos'!$B$84) -> 6395798.3 | J196: ='05_Carta_Gantt'!E19 -> 46377 | K196: ='05_Carta_Gantt'!F19 -> 46394 | L196: PPTO fila 40
A197: B.1.4.2 | B197: K | C197: Planchas de OSB e=11.1mm | D197: M2 | E197: 153 | F197: 13200 | G197: =F197/(1+'02_Rendimientos'!$B$82) -> 11092.437 | H197: =E197*G197 -> 1697142.9 | I197: =H197*(1+'02_Rendimientos'!$B$83+'02_Rendimientos'!$B$84) -> 2121428.6 | J197: ='05_Carta_Gantt'!E19 -> 46377 | K197: ='05_Carta_Gantt'!F19 -> 46394 | L197: PPTO fila 41
A198: B.1.4.3 | B198: K | C198: Forro Exterior | D198: M2 | E198: 153 | F198: 23000 | G198: =F198/(1+'02_Rendimientos'!$B$82) -> 19327.731 | H198: =E198*G198 -> 2957142.9 | I198: =H198*(1+'02_Rendimientos'!$B$83+'02_Rendimientos'!$B$84) -> 3696428.6 | J198: ='05_Carta_Gantt'!E19 -> 46377 | K198: ='05_Carta_Gantt'!F19 -> 46394 | L198: PPTO fila 42
A199: B.1.4.4 | B199: K | C199: Forro Interior Volcanita y Aleros Exteriores | D199: M2 | E199: 180 | F199: 12800 | G199: =F199/(1+'02_Rendimientos'!$B$82) -> 10756.303 | H199: =E199*G199 -> 1936134.5 | I199: =H199*(1+'02_Rendimientos'!$B$83+'02_Rendimientos'!$B$84) -> 2420168.1 | J199: ='05_Carta_Gantt'!E19 -> 46377 | K199: ='05_Carta_Gantt'!F19 -> 46394 | L199: PPTO fila 43
A200: B.1.4.5 | B200: K | C200: Forro Interior Fibrocemento | D200: M2 | E200: 65 | F200: 17800 | G200: =F200/(1+'02_Rendimientos'!$B$82) -> 14957.983 | H200: =E200*G200 -> 972268.91 | I200: =H200*(1+'02_Rendimientos'!$B$83+'02_Rendimientos'!$B$84) -> 1215336.1 | J200: ='05_Carta_Gantt'!E19 -> 46377 | K200: ='05_Carta_Gantt'!F19 -> 46394 | L200: PPTO fila 44
A201: B.1.5.1 | B201: I | C201: Cerchas y Costaneras de Acero Galvanizado | D201: M2 | E201: 78.61 | F201: 34000 | G201: =F201/(1+'02_Rendimientos'!$B$82) -> 28571.429 | H201: =E201*G201 -> 2246000 | I201: =H201*(1+'02_Rendimientos'!$B$83+'02_Rendimientos'!$B$84) -> 2807500 | J201: ='05_Carta_Gantt'!E17 -> 46377 | K201: ='05_Carta_Gantt'!F17 -> 46396 | L201: PPTO fila 46
A202: B.1.6.1 | B202: J | C202: Aislación Papel Impermeabilizante | D202: M2 | E202: 78.61 | F202: 2300 | G202: =F202/(1+'02_Rendimientos'!$B$82) -> 1932.7731 | H202: =E202*G202 -> 151935.29 | I202: =H202*(1+'02_Rendimientos'!$B$83+'02_Rendimientos'!$B$84) -> 189919.12 | J202: ='05_Carta_Gantt'!E18 -> 46397 | K202: ='05_Carta_Gantt'!F18 -> 46408 | L202: PPTO fila 48
A203: B.1.6.2 | B203: J | C203: Planchas OSB e=11.1mm | D203: M2 | E203: 78.61 | F203: 13200 | G203: =F203/(1+'02_Rendimientos'!$B$82) -> 11092.437 | H203: =E203*G203 -> 871976.47 | I203: =H203*(1+'02_Rendimientos'!$B$83+'02_Rendimientos'!$B$84) -> 1089970.6 | J203: ='05_Carta_Gantt'!E18 -> 46397 | K203: ='05_Carta_Gantt'!F18 -> 46408 | L203: PPTO fila 49
A204: B.1.6.3 | B204: J | C204: Cubierta Onda Estándar | D204: M2 | E204: 78.61 | F204: 14800 | G204: =F204/(1+'02_Rendimientos'!$B$82) -> 12436.975 | H204: =E204*G204 -> 977670.59 | I204: =H204*(1+'02_Rendimientos'!$B$83+'02_Rendimientos'!$B$84) -> 1222088.2 | J204: ='05_Carta_Gantt'!E18 -> 46397 | K204: ='05_Carta_Gantt'!F18 -> 46408 | L204: PPTO fila 50
A205: B.2.1.1 | B205: Q | C205: Aislante Térmico Para Muros | D205: M2 | E205: 236 | F205: 7400 | G205: =F205/(1+'02_Rendimientos'!$B$82) -> 6218.4874 | H205: =E205*G205 -> 1467563 | I205: =H205*(1+'02_Rendimientos'!$B$83+'02_Rendimientos'!$B$84) -> 1834453.8 | J205: ='05_Carta_Gantt'!E25 -> 46423 | K205: ='05_Carta_Gantt'!F25 -> 46438 | L205: PPTO fila 53
A206: B.2.1.2 | B206: R | C206: Aislante Térmico Para Cielo | D206: M2 | E206: 78.61 | F206: 7900 | G206: =F206/(1+'02_Rendimientos'!$B$82) -> 6638.6555 | H206: =E206*G206 -> 521864.71 | I206: =H206*(1+'02_Rendimientos'!$B$83+'02_Rendimientos'!$B$84) -> 652330.88 | J206: ='05_Carta_Gantt'!E26 -> 46439 | K206: ='05_Carta_Gantt'!F26 -> 46450 | L206: PPTO fila 54
A207: B.2.1.3 | B207: S | C207: Impermeabilización Bajo Pavimentos | D207: M2 | E207: 85 | F207: 7400 | G207: =F207/(1+'02_Rendimientos'!$B$82) -> 6218.4874 | H207: =E207*G207 -> 528571.43 | I207: =H207*(1+'02_Rendimientos'!$B$83+'02_Rendimientos'!$B$84) -> 660714.29 | J207: ='05_Carta_Gantt'!E27 -> 46439 | K207: ='05_Carta_Gantt'!F27 -> 46448 | L207: PPTO fila 55
A208: B.2.2/a) | B208: R | C208: Yeso Cartón RH | D208: M2 | E208: 34 | F208: 19500 | G208: =F208/(1+'02_Rendimientos'!$B$82) -> 16386.555 | H208: =E208*G208 -> 557142.86 | I208: =H208*(1+'02_Rendimientos'!$B$83+'02_Rendimientos'!$B$84) -> 696428.57 | J208: ='05_Carta_Gantt'!E26 -> 46439 | K208: ='05_Carta_Gantt'!F26 -> 46450 | L208: PPTO fila 57
A209: B.2.3/a) | B209: R | C209: Yeso Cartón | D209: M2 | E209: 50 | F209: 16800 | G209: =F209/(1+'02_Rendimientos'!$B$82) -> 14117.647 | H209: =E209*G209 -> 705882.35 | I209: =H209*(1+'02_Rendimientos'!$B$83+'02_Rendimientos'!$B$84) -> 882352.94 | J209: ='05_Carta_Gantt'!E26 -> 46439 | K209: ='05_Carta_Gantt'!F26 -> 46450 | L209: PPTO fila 59
A210: B.2.4/a) | B210: J | C210: Forros | D210: ML | E210: 25 | F210: 12500 | G210: =F210/(1+'02_Rendimientos'!$B$82) -> 10504.202 | H210: =E210*G210 -> 262605.04 | I210: =H210*(1+'02_Rendimientos'!$B$83+'02_Rendimientos'!$B$84) -> 328256.3 | J210: ='05_Carta_Gantt'!E18 -> 46397 | K210: ='05_Carta_Gantt'!F18 -> 46408 | L210: PPTO fila 61
A211: B.2.4/b) | B211: J | C211: Canales | D211: ML | E211: 45 | F211: 17800 | G211: =F211/(1+'02_Rendimientos'!$B$82) -> 14957.983 | H211: =E211*G211 -> 673109.24 | I211: =H211*(1+'02_Rendimientos'!$B$83+'02_Rendimientos'!$B$84) -> 841386.55 | J211: ='05_Carta_Gantt'!E18 -> 46397 | K211: ='05_Carta_Gantt'!F18 -> 46408 | L211: PPTO fila 62
A212: B.2.4/c) | B212: J | C212: Bajadas | D212: ML | E212: 24 | F212: 13900 | G212: =F212/(1+'02_Rendimientos'!$B$82) -> 11680.672 | H212: =E212*G212 -> 280336.13 | I212: =H212*(1+'02_Rendimientos'!$B$83+'02_Rendimientos'!$B$84) -> 350420.17 | J212: ='05_Carta_Gantt'!E18 -> 46397 | K212: ='05_Carta_Gantt'!F18 -> 46408 | L212: PPTO fila 63
A213: B.2.4/d) | B213: J | C213: Salida Ventilaciones | D213: ML | E213: 6 | F213: 16500 | G213: =F213/(1+'02_Rendimientos'!$B$82) -> 13865.546 | H213: =E213*G213 -> 83193.277 | I213: =H213*(1+'02_Rendimientos'!$B$83+'02_Rendimientos'!$B$84) -> 103991.6 | J213: ='05_Carta_Gantt'!E18 -> 46397 | K213: ='05_Carta_Gantt'!F18 -> 46408 | L213: PPTO fila 64
A214: B.2.5.1 | B214: Q | C214: Cerámicos Muros | D214: M2 | E214: 70 | F214: 27800 | G214: =F214/(1+'02_Rendimientos'!$B$82) -> 23361.345 | H214: =E214*G214 -> 1635294.1 | I214: =H214*(1+'02_Rendimientos'!$B$83+'02_Rendimientos'!$B$84) -> 2044117.6 | J214: ='05_Carta_Gantt'!E25 -> 46423 | K214: ='05_Carta_Gantt'!F25 -> 46438 | L214: PPTO fila 66
A215: B.2.5.2 | B215: S | C215: Cerámicos Pisos | D215: M2 | E215: 84 | F215: 26500 | G215: =F215/(1+'02_Rendimientos'!$B$82) -> 22268.908 | H215: =E215*G215 -> 1870588.2 | I215: =H215*(1+'02_Rendimientos'!$B$83+'02_Rendimientos'!$B$84) -> 2338235.3 | J215: ='05_Carta_Gantt'!E27 -> 46439 | K215: ='05_Carta_Gantt'!F27 -> 46448 | L215: PPTO fila 67
A216: B.2.6.1 | B216: T | C216: Pintura Puertas Exteriores Esmalte Sintético | D216: M2 | E216: 35 | F216: 11500 | G216: =F216/(1+'02_Rendimientos'!$B$82) -> 9663.8655 | H216: =E216*G216 -> 338235.29 | I216: =H216*(1+'02_Rendimientos'!$B$83+'02_Rendimientos'!$B$84) -> 422794.12 | J216: ='05_Carta_Gantt'!E28 -> 46451 | K216: ='05_Carta_Gantt'!F28 -> 46470 | L216: PPTO fila 69
A217: B.2.6.2 | B217: T | C217: Pintura Interior | D217: M2 | E217: 250 | F217: 7800 | G217: =F217/(1+'02_Rendimientos'!$B$82) -> 6554.6218 | H217: =E217*G217 -> 1638655.5 | I217: =H217*(1+'02_Rendimientos'!$B$83+'02_Rendimientos'!$B$84) -> 2048319.3 | J217: ='05_Carta_Gantt'!E28 -> 46451 | K217: ='05_Carta_Gantt'!F28 -> 46470 | L217: PPTO fila 70
A218: B.2.7.1/a) | B218: U | C218: P1 / Madera Puertas | D218: UNI | E218: 1 | F218: 245000 | G218: =F218/(1+'02_Rendimientos'!$B$82) -> 205882.35 | H218: =E218*G218 -> 205882.35 | I218: =H218*(1+'02_Rendimientos'!$B$83+'02_Rendimientos'!$B$84) -> 257352.94 | J218: ='05_Carta_Gantt'!E29 -> 46409 | K218: ='05_Carta_Gantt'!F29 -> 46424 | L218: PPTO fila 73
A219: B.2.7.1/b) | B219: U | C219: P2 / Madera Puertas | D219: UNI | E219: 2 | F219: 195000 | G219: =F219/(1+'02_Rendimientos'!$B$82) -> 163865.55 | H219: =E219*G219 -> 327731.09 | I219: =H219*(1+'02_Rendimientos'!$B$83+'02_Rendimientos'!$B$84) -> 409663.87 | J219: ='05_Carta_Gantt'!E29 -> 46409 | K219: ='05_Carta_Gantt'!F29 -> 46424 | L219: PPTO fila 74
A220: B.2.7.1/c) | B220: U | C220: P3 / Madera Puertas | D220: UNI | E220: 3 | F220: 175000 | G220: =F220/(1+'02_Rendimientos'!$B$82) -> 147058.82 | H220: =E220*G220 -> 441176.47 | I220: =H220*(1+'02_Rendimientos'!$B$83+'02_Rendimientos'!$B$84) -> 551470.59 | J220: ='05_Carta_Gantt'!E29 -> 46409 | K220: ='05_Carta_Gantt'!F29 -> 46424 | L220: PPTO fila 75
A221: B.2.7.1/d) | B221: U | C221: P4 / Madera Puertas | D221: UNI | E221: 1 | F221: 265000 | G221: =F221/(1+'02_Rendimientos'!$B$82) -> 222689.08 | H221: =E221*G221 -> 222689.08 | I221: =H221*(1+'02_Rendimientos'!$B$83+'02_Rendimientos'!$B$84) -> 278361.34 | J221: ='05_Carta_Gantt'!E29 -> 46409 | K221: ='05_Carta_Gantt'!F29 -> 46424 | L221: PPTO fila 76
A222: B.2.7.2/a) | B222: U | C222: P1 / Marcos | D222: ML | E222: 6 | F222: 12500 | G222: =F222/(1+'02_Rendimientos'!$B$82) -> 10504.202 | H222: =E222*G222 -> 63025.21 | I222: =H222*(1+'02_Rendimientos'!$B$83+'02_Rendimientos'!$B$84) -> 78781.513 | J222: ='05_Carta_Gantt'!E29 -> 46409 | K222: ='05_Carta_Gantt'!F29 -> 46424 | L222: PPTO fila 78
A223: B.2.7.2/b) | B223: U | C223: P2 / Marcos | D223: ML | E223: 10 | F223: 12500 | G223: =F223/(1+'02_Rendimientos'!$B$82) -> 10504.202 | H223: =E223*G223 -> 105042.02 | I223: =H223*(1+'02_Rendimientos'!$B$83+'02_Rendimientos'!$B$84) -> 131302.52 | J223: ='05_Carta_Gantt'!E29 -> 46409 | K223: ='05_Carta_Gantt'!F29 -> 46424 | L223: PPTO fila 79
A224: B.2.7.2/c) | B224: U | C224: P3 / Marcos | D224: ML | E224: 15 | F224: 12500 | G224: =F224/(1+'02_Rendimientos'!$B$82) -> 10504.202 | H224: =E224*G224 -> 157563.03 | I224: =H224*(1+'02_Rendimientos'!$B$83+'02_Rendimientos'!$B$84) -> 196953.78 | J224: ='05_Carta_Gantt'!E29 -> 46409 | K224: ='05_Carta_Gantt'!F29 -> 46424 | L224: PPTO fila 80
A225: B.2.7.2/d) | B225: U | C225: P4 / Marcos | D225: ML | E225: 5 | F225: 12500 | G225: =F225/(1+'02_Rendimientos'!$B$82) -> 10504.202 | H225: =E225*G225 -> 52521.008 | I225: =H225*(1+'02_Rendimientos'!$B$83+'02_Rendimientos'!$B$84) -> 65651.261 | J225: ='05_Carta_Gantt'!E29 -> 46409 | K225: ='05_Carta_Gantt'!F29 -> 46424 | L225: PPTO fila 81
A226: B.2.8/a) | B226: U | C226: Bisagras | D226: UNI | E226: 28 | F226: 4800 | G226: =F226/(1+'02_Rendimientos'!$B$82) -> 4033.6134 | H226: =E226*G226 -> 112941.18 | I226: =H226*(1+'02_Rendimientos'!$B$83+'02_Rendimientos'!$B$84) -> 141176.47 | J226: ='05_Carta_Gantt'!E29 -> 46409 | K226: ='05_Carta_Gantt'!F29 -> 46424 | L226: PPTO fila 83
A227: B.2.8/b) | B227: U | C227: Topes de Goma | D227: UNI | E227: 8 | F227: 3800 | G227: =F227/(1+'02_Rendimientos'!$B$82) -> 3193.2773 | H227: =E227*G227 -> 25546.218 | I227: =H227*(1+'02_Rendimientos'!$B$83+'02_Rendimientos'!$B$84) -> 31932.773 | J227: ='05_Carta_Gantt'!E29 -> 46409 | K227: ='05_Carta_Gantt'!F29 -> 46424 | L227: PPTO fila 84
A228: B.2.8/c) | B228: U | C228: Cerraduras | D228: UNI | E228: 7 | F228: 28500 | G228: =F228/(1+'02_Rendimientos'!$B$82) -> 23949.58 | H228: =E228*G228 -> 167647.06 | I228: =H228*(1+'02_Rendimientos'!$B$83+'02_Rendimientos'!$B$84) -> 209558.82 | J228: ='05_Carta_Gantt'!E29 -> 46409 | K228: ='05_Carta_Gantt'!F29 -> 46424 | L228: PPTO fila 85
A229: B.2.8/d) | B229: U | C229: Picaporte de Uñeta | D229: UNI | E229: 2 | F229: 7500 | G229: =F229/(1+'02_Rendimientos'!$B$82) -> 6302.521 | H229: =E229*G229 -> 12605.042 | I229: =H229*(1+'02_Rendimientos'!$B$83+'02_Rendimientos'!$B$84) -> 15756.303 | J229: ='05_Carta_Gantt'!E29 -> 46409 | K229: ='05_Carta_Gantt'!F29 -> 46424 | L229: PPTO fila 86
A230: B.2.9.1 | B230: U | C230: Ventanas Con Marco De Aluminio Blanco | D230: M2 | E230: 15 | F230: 145000 | G230: =F230/(1+'02_Rendimientos'!$B$82) -> 121848.74 | H230: =E230*G230 -> 1827731.1 | I230: =H230*(1+'02_Rendimientos'!$B$83+'02_Rendimientos'!$B$84) -> 2284663.9 | J230: ='05_Carta_Gantt'!E29 -> 46409 | K230: ='05_Carta_Gantt'!F29 -> 46424 | L230: PPTO fila 88
A231: B.2.9.2 | B231: U | C231: Quincallería | D231: UNI | E231: 1 | F231: 125000 | G231: =F231/(1+'02_Rendimientos'!$B$82) -> 105042.02 | H231: =E231*G231 -> 105042.02 | I231: =H231*(1+'02_Rendimientos'!$B$83+'02_Rendimientos'!$B$84) -> 131302.52 | J231: ='05_Carta_Gantt'!E29 -> 46409 | K231: ='05_Carta_Gantt'!F29 -> 46424 | L231: PPTO fila 89
A232: B.2.10 | B232: U | C232: PROTECCIONES METALICAS TIPO QUEBRAVISTA | D232: M2 | E232: 15 | F232: 97000 | G232: =F232/(1+'02_Rendimientos'!$B$82) -> 81512.605 | H232: =E232*G232 -> 1222689.1 | I232: =H232*(1+'02_Rendimientos'!$B$83+'02_Rendimientos'!$B$84) -> 1528361.3 | J232: ='05_Carta_Gantt'!E29 -> 46409 | K232: ='05_Carta_Gantt'!F29 -> 46424 | L232: PPTO fila 90
A233: B.2.11 | B233: R | C233: CORNISAS | D233: ML | E233: 78.3 | F233: 5200 | G233: =F233/(1+'02_Rendimientos'!$B$82) -> 4369.7479 | H233: =E233*G233 -> 342151.26 | I233: =H233*(1+'02_Rendimientos'!$B$83+'02_Rendimientos'!$B$84) -> 427689.08 | J233: ='05_Carta_Gantt'!E26 -> 46439 | K233: ='05_Carta_Gantt'!F26 -> 46450 | L233: PPTO fila 91
A234: C.1.1.1 | B234: L | C234: EMT Ø32mm | D234: UNI | E234: 1 | F234: 68000 | G234: =F234/(1+'02_Rendimientos'!$B$82) -> 57142.857 | H234: =E234*G234 -> 57142.857 | I234: =H234*(1+'02_Rendimientos'!$B$83+'02_Rendimientos'!$B$84) -> 71428.571 | J234: ='05_Carta_Gantt'!E20 -> 46409 | K234: ='05_Carta_Gantt'!F20 -> 46422 | L234: PPTO fila 96
A235: C.1.1.2 | B235: L | C235: Conductor Concentrico 2x6mm2 | D235: ML | E235: 23 | F235: 9200 | G235: =F235/(1+'02_Rendimientos'!$B$82) -> 7731.0924 | H235: =E235*G235 -> 177815.13 | I235: =H235*(1+'02_Rendimientos'!$B$83+'02_Rendimientos'!$B$84) -> 222268.91 | J235: ='05_Carta_Gantt'!E20 -> 46409 | K235: ='05_Carta_Gantt'!F20 -> 46422 | L235: PPTO fila 97
A236: C.1.1.3 | B236: L | C236: Medidor BT1 | D236: UNI | E236: 1 | F236: 180000 | G236: =F236/(1+'02_Rendimientos'!$B$82) -> 151260.5 | H236: =E236*G236 -> 151260.5 | I236: =H236*(1+'02_Rendimientos'!$B$83+'02_Rendimientos'!$B$84) -> 189075.63 | J236: ='05_Carta_Gantt'!E20 -> 46409 | K236: ='05_Carta_Gantt'!F20 -> 46422 | L236: PPTO fila 98
A237: C.1.1.4 | B237: L | C237: Automaticos Saime 25 A | D237: UNI | E237: 1 | F237: 28500 | G237: =F237/(1+'02_Rendimientos'!$B$82) -> 23949.58 | H237: =E237*G237 -> 23949.58 | I237: =H237*(1+'02_Rendimientos'!$B$83+'02_Rendimientos'!$B$84) -> 29936.975 | J237: ='05_Carta_Gantt'!E20 -> 46409 | K237: ='05_Carta_Gantt'!F20 -> 46422 | L237: PPTO fila 99
A238: C.1.1.5 | B238: L | C238: Caja proteccion empalme 500×300×250mm | D238: UNI | E238: 1 | F238: 145000 | G238: =F238/(1+'02_Rendimientos'!$B$82) -> 121848.74 | H238: =E238*G238 -> 121848.74 | I238: =H238*(1+'02_Rendimientos'!$B$83+'02_Rendimientos'!$B$84) -> 152310.92 | J238: ='05_Carta_Gantt'!E20 -> 46409 | K238: ='05_Carta_Gantt'!F20 -> 46422 | L238: PPTO fila 100
A239: C.1.1.6 | B239: L | C239: Malla tierra de proteccion y servicio 2×2m | D239: UNI | E239: 1 | F239: 340000 | G239: =F239/(1+'02_Rendimientos'!$B$82) -> 285714.29 | H239: =E239*G239 -> 285714.29 | I239: =H239*(1+'02_Rendimientos'!$B$83+'02_Rendimientos'!$B$84) -> 357142.86 | J239: ='05_Carta_Gantt'!E20 -> 46409 | K239: ='05_Carta_Gantt'!F20 -> 46422 | L239: PPTO fila 101
A240: C.1.2.1 | B240: L | C240: Tablero Metalico 1200x800x300mm | D240: UNI | E240: 1 | F240: 420000 | G240: =F240/(1+'02_Rendimientos'!$B$82) -> 352941.18 | H240: =E240*G240 -> 352941.18 | I240: =H240*(1+'02_Rendimientos'!$B$83+'02_Rendimientos'!$B$84) -> 441176.47 | J240: ='05_Carta_Gantt'!E20 -> 46409 | K240: ='05_Carta_Gantt'!F20 -> 46422 | L240: PPTO fila 103
A241: C.1.2.4 | B241: L | C241: Automaticos 25A | D241: UNI | E241: 1 | F241: 18500 | G241: =F241/(1+'02_Rendimientos'!$B$82) -> 15546.218 | H241: =E241*G241 -> 15546.218 | I241: =H241*(1+'02_Rendimientos'!$B$83+'02_Rendimientos'!$B$84) -> 19432.773 | J241: ='05_Carta_Gantt'!E20 -> 46409 | K241: ='05_Carta_Gantt'!F20 -> 46422 | L241: PPTO fila 104
...

Sheet 07_Curvas_S
A1: CURVAS S · PANEL INTEGRADO · ES3 IND. 7 Y 8
A4: PASO 7 · AVANCE FÍSICO Y FINANCIERO
A5: Avance físico ponderado por jornadas base de las 22 actividades (no suma unidades heterogéneas). Avance financiero: costo directo y venta neta distribuidos uniformemente en el intervalo de cada partida.
A6: Resumen semanal y gráficos. El desarrollo diario por partida se presenta debajo: curva física desde la fila 69 y financiera desde la fila 147.
A8: Semana | B8: Desde | C8: Hasta | D8: Físico período | E8: Físico acumulado | F8: CD período | G8: CD acumulado | H8: Venta neta período | I8: Venta neta acum.
A9: 1 | B9: ='02_Rendimientos'!B79+0 -> 46328 | C9: =MIN(B9+6,'05_Carta_Gantt'!$F$30) -> 46334 | D9: =SUMPRODUCT($B$38:$B$59,H38:H59) -> 0.015545137 | E9: =SUM(D$9:D9) -> 0.015545137 | F9: =SUMPRODUCT($C$38:$C$59,H38:H59) -> 7245896 | G9: =SUM(F$9:F9) -> 7245896 | H9: =SUMPRODUCT($D$38:$D$59,H38:H59) -> 9057370 | I9: =SUM(H$9:H9) -> 9057370
A10: 2 | B10: ='02_Rendimientos'!B79+7 -> 46335 | C10: =MIN(B10+6,'05_Carta_Gantt'!$F$30) -> 46341 | D10: =SUMPRODUCT($B$38:$B$59,I38:I59) -> 0.033512893 | E10: =SUM(D$9:D10) -> 0.049058031 | F10: =SUMPRODUCT($C$38:$C$59,I38:I59) -> 771928.56 | G10: =SUM(F$9:F10) -> 8017824.5 | H10: =SUMPRODUCT($D$38:$D$59,I38:I59) -> 964910.7 | I10: =SUM(H$9:H10) -> 10022281
A11: 3 | B11: ='02_Rendimientos'!B79+14 -> 46342 | C11: =MIN(B11+6,'05_Carta_Gantt'!$F$30) -> 46348 | D11: =SUMPRODUCT($B$38:$B$59,J38:J59) -> 0.025639382 | E11: =SUM(D$9:D11) -> 0.074697413 | F11: =SUMPRODUCT($C$38:$C$59,J38:J59) -> 336898.4 | G11: =SUM(F$9:F11) -> 8354722.9 | H11: =SUMPRODUCT($D$38:$D$59,J38:J59) -> 421122.99 | I11: =SUM(H$9:H11) -> 10443404
A12: 4 | B12: ='02_Rendimientos'!B79+21 -> 46349 | C12: =MIN(B12+6,'05_Carta_Gantt'!$F$30) -> 46355 | D12: =SUMPRODUCT($B$38:$B$59,K38:K59) -> 0.024618742 | E12: =SUM(D$9:D12) -> 0.099316155 | F12: =SUMPRODUCT($C$38:$C$59,K38:K59) -> 1273665.6 | G12: =SUM(F$9:F12) -> 9628388.5 | H12: =SUMPRODUCT($D$38:$D$59,K38:K59) -> 1592082 | I12: =SUM(H$9:H12) -> 12035486
A13: 5 | B13: ='02_Rendimientos'!B79+28 -> 46356 | C13: =MIN(B13+6,'05_Carta_Gantt'!$F$30) -> 46362 | D13: =SUMPRODUCT($B$38:$B$59,L38:L59) -> 0.048864958 | E13: =SUM(D$9:D13) -> 0.14818111 | F13: =SUMPRODUCT($C$38:$C$59,L38:L59) -> 1678259.4 | G13: =SUM(F$9:F13) -> 11306648 | H13: =SUMPRODUCT($D$38:$D$59,L38:L59) -> 2097824.2 | I13: =SUM(H$9:H13) -> 14133310
A14: 6 | B14: ='02_Rendimientos'!B79+35 -> 46363 | C14: =MIN(B14+6,'05_Carta_Gantt'!$F$30) -> 46369 | D14: =SUMPRODUCT($B$38:$B$59,M38:M59) -> 0.047147889 | E14: =SUM(D$9:D14) -> 0.195329 | F14: =SUMPRODUCT($C$38:$C$59,M38:M59) -> 2634059.4 | G14: =SUM(F$9:F14) -> 13940707 | H14: =SUMPRODUCT($D$38:$D$59,M38:M59) -> 3292574.2 | I14: =SUM(H$9:H14) -> 17425884
A15: 7 | B15: ='02_Rendimientos'!B79+42 -> 46370 | C15: =MIN(B15+6,'05_Carta_Gantt'!$F$30) -> 46376 | D15: =SUMPRODUCT($B$38:$B$59,N38:N59) -> 0.032481284 | E15: =SUM(D$9:D15) -> 0.22781029 | F15: =SUMPRODUCT($C$38:$C$59,N38:N59) -> 1998323 | G15: =SUM(F$9:F15) -> 15939030 | H15: =SUMPRODUCT($D$38:$D$59,N38:N59) -> 2497903.7 | I15: =SUM(H$9:H15) -> 19923788
A16: 8 | B16: ='02_Rendimientos'!B79+49 -> 46377 | C16: =MIN(B16+6,'05_Carta_Gantt'!$F$30) -> 46383 | D16: =SUMPRODUCT($B$38:$B$59,O38:O59) -> 0.070338662 | E16: =SUM(D$9:D16) -> 0.29814895 | F16: =SUMPRODUCT($C$38:$C$59,O38:O59) -> 8554785 | G16: =SUM(F$9:F16) -> 24493815 | H16: =SUMPRODUCT($D$38:$D$59,O38:O59) -> 10693481 | I16: =SUM(H$9:H16) -> 30617269
A17: 9 | B17: ='02_Rendimientos'!B79+56 -> 46384 | C17: =MIN(B17+6,'05_Carta_Gantt'!$F$30) -> 46390 | D17: =SUMPRODUCT($B$38:$B$59,P38:P59) -> 0.064059801 | E17: =SUM(D$9:D17) -> 0.36220875 | F17: =SUMPRODUCT($C$38:$C$59,P38:P59) -> 7743974.9 | G17: =SUM(F$9:F17) -> 32237790 | H17: =SUMPRODUCT($D$38:$D$59,P38:P59) -> 9679968.6 | I17: =SUM(H$9:H17) -> 40297238
A18: 10 | B18: ='02_Rendimientos'!B79+63 -> 46391 | C18: =MIN(B18+6,'05_Carta_Gantt'!$F$30) -> 46397 | D18: =SUMPRODUCT($B$38:$B$59,Q38:Q59) -> 0.051529251 | E18: =SUM(D$9:D18) -> 0.413738 | F18: =SUMPRODUCT($C$38:$C$59,Q38:Q59) -> 4421111.1 | G18: =SUM(F$9:F18) -> 36658901 | H18: =SUMPRODUCT($D$38:$D$59,Q38:Q59) -> 5526388.9 | I18: =SUM(H$9:H18) -> 45823626
A19: 11 | B19: ='02_Rendimientos'!B79+70 -> 46398 | C19: =MIN(B19+6,'05_Carta_Gantt'!$F$30) -> 46404 | D19: =SUMPRODUCT($B$38:$B$59,R38:R59) -> 0.053256489 | E19: =SUM(D$9:D19) -> 0.46699449 | F19: =SUMPRODUCT($C$38:$C$59,R38:R59) -> 3452914.2 | G19: =SUM(F$9:F19) -> 40111815 | H19: =SUMPRODUCT($D$38:$D$59,R38:R59) -> 4316142.8 | I19: =SUM(H$9:H19) -> 50139769
A20: 12 | B20: ='02_Rendimientos'!B79+77 -> 46405 | C20: =MIN(B20+6,'05_Carta_Gantt'!$F$30) -> 46411 | D20: =SUMPRODUCT($B$38:$B$59,S38:S59) -> 0.058918479 | E20: =SUM(D$9:D20) -> 0.52591297 | F20: =SUMPRODUCT($C$38:$C$59,S38:S59) -> 5755007.7 | G20: =SUM(F$9:F20) -> 45866823 | H20: =SUMPRODUCT($D$38:$D$59,S38:S59) -> 7193759.6 | I20: =SUM(H$9:H20) -> 57333529
A21: 13 | B21: ='02_Rendimientos'!B79+84 -> 46412 | C21: =MIN(B21+6,'05_Carta_Gantt'!$F$30) -> 46418 | D21: =SUMPRODUCT($B$38:$B$59,T38:T59) -> 0.059682224 | E21: =SUM(D$9:D21) -> 0.58559519 | F21: =SUMPRODUCT($C$38:$C$59,T38:T59) -> 8345204.8 | G21: =SUM(F$9:F21) -> 54212028 | H21: =SUMPRODUCT($D$38:$D$59,T38:T59) -> 10431506 | I21: =SUM(H$9:H21) -> 67765035
A22: 14 | B22: ='02_Rendimientos'!B79+91 -> 46419 | C22: =MIN(B22+6,'05_Carta_Gantt'!$F$30) -> 46425 | D22: =SUMPRODUCT($B$38:$B$59,U38:U59) -> 0.067861266 | E22: =SUM(D$9:D22) -> 0.65345646 | F22: =SUMPRODUCT($C$38:$C$59,U38:U59) -> 6711535.1 | G22: =SUM(F$9:F22) -> 60923563 | H22: =SUMPRODUCT($D$38:$D$59,U38:U59) -> 8389418.9 | I22: =SUM(H$9:H22) -> 76154454
A23: 15 | B23: ='02_Rendimientos'!B79+98 -> 46426 | C23: =MIN(B23+6,'05_Carta_Gantt'!$F$30) -> 46432 | D23: =SUMPRODUCT($B$38:$B$59,V38:V59) -> 0.064887069 | E23: =SUM(D$9:D23) -> 0.71834353 | F23: =SUMPRODUCT($C$38:$C$59,V38:V59) -> 1357500 | G23: =SUM(F$9:F23) -> 62281063 | H23: =SUMPRODUCT($D$38:$D$59,V38:V59) -> 1696875 | I23: =SUM(H$9:H23) -> 77851329
A24: 16 | B24: ='02_Rendimientos'!B79+105 -> 46433 | C24: =MIN(B24+6,'05_Carta_Gantt'!$F$30) -> 46439 | D24: =SUMPRODUCT($B$38:$B$59,W38:W59) -> 0.055405989 | E24: =SUM(D$9:D24) -> 0.77374952 | F24: =SUMPRODUCT($C$38:$C$59,W38:W59) -> 1722169.4 | G24: =SUM(F$9:F24) -> 64003232 | H24: =SUMPRODUCT($D$38:$D$59,W38:W59) -> 2152711.7 | I24: =SUM(H$9:H24) -> 80004041
A25: 17 | B25: ='02_Rendimientos'!B79+112 -> 46440 | C25: =MIN(B25+6,'05_Carta_Gantt'!$F$30) -> 46446 | D25: =SUMPRODUCT($B$38:$B$59,X38:X59) -> 0.081797032 | E25: =SUM(D$9:D25) -> 0.85554655 | F25: =SUMPRODUCT($C$38:$C$59,X38:X59) -> 3910185.8 | G25: =SUM(F$9:F25) -> 67913418 | H25: =SUMPRODUCT($D$38:$D$59,X38:X59) -> 4887732.2 | I25: =SUM(H$9:H25) -> 84891773
A26: 18 | B26: ='02_Rendimientos'!B79+119 -> 46447 | C26: =MIN(B26+6,'05_Carta_Gantt'!$F$30) -> 46453 | D26: =SUMPRODUCT($B$38:$B$59,Y38:Y59) -> 0.046741161 | E26: =SUM(D$9:D26) -> 0.90228771 | F26: =SUMPRODUCT($C$38:$C$59,Y38:Y59) -> 1768236.4 | G26: =SUM(F$9:F26) -> 69681655 | H26: =SUMPRODUCT($D$38:$D$59,Y38:Y59) -> 2210295.5 | I26: =SUM(H$9:H26) -> 87102068
A27: 19 | B27: ='02_Rendimientos'!B79+126 -> 46454 | C27: =MIN(B27+6,'05_Carta_Gantt'!$F$30) -> 46460 | D27: =SUMPRODUCT($B$38:$B$59,Z38:Z59) -> 0.031090275 | E27: =SUM(D$9:D27) -> 0.93337798 | F27: =SUMPRODUCT($C$38:$C$59,Z38:Z59) -> 691911.76 | G27: =SUM(F$9:F27) -> 70373566 | H27: =SUMPRODUCT($D$38:$D$59,Z38:Z59) -> 864889.71 | I27: =SUM(H$9:H27) -> 87966958
A28: 20 | B28: ='02_Rendimientos'!B79+133 -> 46461 | C28: =MIN(B28+6,'05_Carta_Gantt'!$F$30) -> 46467 | D28: =SUMPRODUCT($B$38:$B$59,AA38:AA59) -> 0.031090275 | E28: =SUM(D$9:D28) -> 0.96446826 | F28: =SUMPRODUCT($C$38:$C$59,AA38:AA59) -> 691911.76 | G28: =SUM(F$9:F28) -> 71065478 | H28: =SUMPRODUCT($D$38:$D$59,AA38:AA59) -> 864889.71 | I28: =SUM(H$9:H28) -> 88831848
A29: 21 | B29: ='02_Rendimientos'!B79+140 -> 46468 | C29: =MIN(B29+6,'05_Carta_Gantt'!$F$30) -> 46474 | D29: =SUMPRODUCT($B$38:$B$59,AB38:AB59) -> 0.026014311 | E29: =SUM(D$9:D29) -> 0.99048257 | F29: =SUMPRODUCT($C$38:$C$59,AB38:AB59) -> 1095437.8 | G29: =SUM(F$9:F29) -> 72160916 | H29: =SUMPRODUCT($D$38:$D$59,AB38:AB59) -> 1369297.3 | I29: =SUM(H$9:H29) -> 90201145
A30: 22 | B30: ='02_Rendimientos'!B79+147 -> 46475 | C30: =MIN(B30+6,'05_Carta_Gantt'!$F$30) -> 46477 | D30: =SUMPRODUCT($B$38:$B$59,AC38:AC59) -> 0.009517431 | E30: =SUM(D$9:D30) -> 1 | F30: =SUMPRODUCT($C$38:$C$59,AC38:AC59) -> 599178.15 | G30: =SUM(F$9:F30) -> 72760094 | H30: =SUMPRODUCT($D$38:$D$59,AC38:AC59) -> 748972.69 | I30: =SUM(H$9:H30) -> 90950118
A37: Act. | B37: Peso físico | C37: Costo directo | D37: Venta neta | E37: Inicio | F37: Fin | G37: Duración | H37: Sem 1 | I37: Sem 2 | J37: Sem 3 | K37: Sem 4 | L37: Sem 5 | M37: Sem 6 | N37: Sem 7 | O37: Sem 8 | P37: Sem 9 | Q37: Sem 10 | R37: Sem 11 | S37: Sem 12 | T37: Sem 13 | U37: Sem 14 | V37: Sem 15 | W37: Sem 16 | X37: Sem 17 | Y37: Sem 18 | Z37: Sem 19 | AA37: Sem 20 | AB37: Sem 21 | AC37: Sem 22
A38: ='06_Presupuesto'!A343 -> A | B38: ='06_Presupuesto'!E343 -> 0.011103669 | C38: ='06_Presupuesto'!C343 -> 7089010.1 | D38: ='06_Presupuesto'!D343 -> 8861262.6 | E38: ='06_Presupuesto'!F343 -> 46328 | F38: ='06_Presupuesto'!G343 -> 46333 | G38: =F38-E38+1 -> 6 | H38: =MAX(0,MIN($F38,$C9)-MAX($E38,$B9)+1)/$G38 -> 1 | I38: =MAX(0,MIN($F38,$C10)-MAX($E38,$B10)+1)/$G38 -> 0 | J38: =MAX(0,MIN($F38,$C11)-MAX($E38,$B11)+1)/$G38 -> 0 | K38: =MAX(0,MIN($F38,$C12)-MAX($E38,$B12)+1)/$G38 -> 0 | L38: =MAX(0,MIN($F38,$C13)-MAX($E38,$B13)+1)/$G38 -> 0 | M38: =MAX(0,MIN($F38,$C14)-MAX($E38,$B14)+1)/$G38 -> 0 | N38: =MAX(0,MIN($F38,$C15)-MAX($E38,$B15)+1)/$G38 -> 0 | O38: =MAX(0,MIN($F38,$C16)-MAX($E38,$B16)+1)/$G38 -> 0 | P38: =MAX(0,MIN($F38,$C17)-MAX($E38,$B17)+1)/$G38 -> 0 | Q38: =MAX(0,MIN($F38,$C18)-MAX($E38,$B18)+1)/$G38 -> 0 | R38: =MAX(0,MIN($F38,$C19)-MAX($E38,$B19)+1)/$G38 -> 0 | S38: =MAX(0,MIN($F38,$C20)-MAX($E38,$B20)+1)/$G38 -> 0 | T38: =MAX(0,MIN($F38,$C21)-MAX($E38,$B21)+1)/$G38 -> 0 | U38: =MAX(0,MIN($F38,$C22)-MAX($E38,$B22)+1)/$G38 -> 0 | V38: =MAX(0,MIN($F38,$C23)-MAX($E38,$B23)+1)/$G38 -> 0 | W38: =MAX(0,MIN($F38,$C24)-MAX($E38,$B24)+1)/$G38 -> 0 | X38: =MAX(0,MIN($F38,$C25)-MAX($E38,$B25)+1)/$G38 -> 0 | Y38: =MAX(0,MIN($F38,$C26)-MAX($E38,$B26)+1)/$G38 -> 0 | Z38: =MAX(0,MIN($F38,$C27)-MAX($E38,$B27)+1)/$G38 -> 0 | AA38: =MAX(0,MIN($F38,$C28)-MAX($E38,$B28)+1)/$G38 -> 0 | AB38: =MAX(0,MIN($F38,$C29)-MAX($E38,$B29)+1)/$G38 -> 0 | AC38: =MAX(0,MIN($F38,$C30)-MAX($E38,$B30)+1)/$G38 -> 0
A39: ='06_Presupuesto'!A344 -> B | B39: ='06_Presupuesto'!E344 -> 0.011103669 | C39: ='06_Presupuesto'!C344 -> 784429.41 | D39: ='06_Presupuesto'!D344 -> 980536.76 | E39: ='06_Presupuesto'!F344 -> 46334 | F39: ='06_Presupuesto'!G344 -> 46338 | G39: =F39-E39+1 -> 5 | H39: =MAX(0,MIN($F39,$C9)-MAX($E39,$B9)+1)/$G39 -> 0.2 | I39: =MAX(0,MIN($F39,$C10)-MAX($E39,$B10)+1)/$G39 -> 0.8 | J39: =MAX(0,MIN($F39,$C11)-MAX($E39,$B11)+1)/$G39 -> 0 | K39: =MAX(0,MIN($F39,$C12)-MAX($E39,$B12)+1)/$G39 -> 0 | L39: =MAX(0,MIN($F39,$C13)-MAX($E39,$B13)+1)/$G39 -> 0 | M39: =MAX(0,MIN($F39,$C14)-MAX($E39,$B14)+1)/$G39 -> 0 | N39: =MAX(0,MIN($F39,$C15)-MAX($E39,$B15)+1)/$G39 -> 0 | O39: =MAX(0,MIN($F39,$C16)-MAX($E39,$B16)+1)/$G39 -> 0 | P39: =MAX(0,MIN($F39,$C17)-MAX($E39,$B17)+1)/$G39 -> 0 | Q39: =MAX(0,MIN($F39,$C18)-MAX($E39,$B18)+1)/$G39 -> 0 | R39: =MAX(0,MIN($F39,$C19)-MAX($E39,$B19)+1)/$G39 -> 0 | S39: =MAX(0,MIN($F39,$C20)-MAX($E39,$B20)+1)/$G39 -> 0 | T39: =MAX(0,MIN($F39,$C21)-MAX($E39,$B21)+1)/$G39 -> 0 | U39: =MAX(0,MIN($F39,$C22)-MAX($E39,$B22)+1)/$G39 -> 0 | V39: =MAX(0,MIN($F39,$C23)-MAX($E39,$B23)+1)/$G39 -> 0 | W39: =MAX(0,MIN($F39,$C24)-MAX($E39,$B24)+1)/$G39 -> 0 | X39: =MAX(0,MIN($F39,$C25)-MAX($E39,$B25)+1)/$G39 -> 0 | Y39: =MAX(0,MIN($F39,$C26)-MAX($E39,$B26)+1)/$G39 -> 0 | Z39: =MAX(0,MIN($F39,$C27)-MAX($E39,$B27)+1)/$G39 -> 0 | AA39: =MAX(0,MIN($F39,$C28)-MAX($E39,$B28)+1)/$G39 -> 0 | AB39: =MAX(0,MIN($F39,$C29)-MAX($E39,$B29)+1)/$G39 -> 0 | AC39: =MAX(0,MIN($F39,$C30)-MAX($E39,$B30)+1)/$G39 -> 0
A40: ='06_Presupuesto'!A345 -> C | B40: ='06_Presupuesto'!E345 -> 0.022207339 | C40: ='06_Presupuesto'!C345 -> 0 | D40: ='06_Presupuesto'!D345 -> 0 | E40: ='06_Presupuesto'!F345 -> 46334 | F40: ='06_Presupuesto'!G345 -> 46343 | G40: =F40-E40+1 -> 10 | H40: =MAX(0,MIN($F40,$C9)-MAX($E40,$B9)+1)/$G40 -> 0.1 | I40: =MAX(0,MIN($F40,$C10)-MAX($E40,$B10)+1)/$G40 -> 0.7 | J40: =MAX(0,MIN($F40,$C11)-MAX($E40,$B11)+1)/$G40 -> 0.2 | K40: =MAX(0,MIN($F40,$C12)-MAX($E40,$B12)+1)/$G40 -> 0 | L40: =MAX(0,MIN($F40,$C13)-MAX($E40,$B13)+1)/$G40 -> 0 | M40: =MAX(0,MIN($F40,$C14)-MAX($E40,$B14)+1)/$G40 -> 0 | N40: =MAX(0,MIN($F40,$C15)-MAX($E40,$B15)+1)/$G40 -> 0 | O40: =MAX(0,MIN($F40,$C16)-MAX($E40,$B16)+1)/$G40 -> 0 | P40: =MAX(0,MIN($F40,$C17)-MAX($E40,$B17)+1)/$G40 -> 0 | Q40: =MAX(0,MIN($F40,$C18)-MAX($E40,$B18)+1)/$G40 -> 0 | R40: =MAX(0,MIN($F40,$C19)-MAX($E40,$B19)+1)/$G40 -> 0 | S40: =MAX(0,MIN($F40,$C20)-MAX($E40,$B20)+1)/$G40 -> 0 | T40: =MAX(0,MIN($F40,$C21)-MAX($E40,$B21)+1)/$G40 -> 0 | U40: =MAX(0,MIN($F40,$C22)-MAX($E40,$B22)+1)/$G40 -> 0 | V40: =MAX(0,MIN($F40,$C23)-MAX($E40,$B23)+1)/$G40 -> 0 | W40: =MAX(0,MIN($F40,$C24)-MAX($E40,$B24)+1)/$G40 -> 0 | X40: =MAX(0,MIN($F40,$C25)-MAX($E40,$B25)+1)/$G40 -> 0 | Y40: =MAX(0,MIN($F40,$C26)-MAX($E40,$B26)+1)/$G40 -> 0 | Z40: =MAX(0,MIN($F40,$C27)-MAX($E40,$B27)+1)/$G40 -> 0 | AA40: =MAX(0,MIN($F40,$C28)-MAX($E40,$B28)+1)/$G40 -> 0 | AB40: =MAX(0,MIN($F40,$C29)-MAX($E40,$B29)+1)/$G40 -> 0 | AC40: =MAX(0,MIN($F40,$C30)-MAX($E40,$B30)+1)/$G40 -> 0
A41: ='06_Presupuesto'!A346 -> D | B41: ='06_Presupuesto'!E346 -> 0.033311008 | C41: ='06_Presupuesto'!C346 -> 529411.76 | D41: ='06_Presupuesto'!D346 -> 661764.71 | E41: ='06_Presupuesto'!F346 -> 46339 | F41: ='06_Presupuesto'!G346 -> 46349 | G41: =F41-E41+1 -> 11 | H41: =MAX(0,MIN($F41,$C9)-MAX($E41,$B9)+1)/$G41 -> 0 | I41: =MAX(0,MIN($F41,$C10)-MAX($E41,$B10)+1)/$G41 -> 0.27272727 | J41: =MAX(0,MIN($F41,$C11)-MAX($E41,$B11)+1)/$G41 -> 0.63636364 | K41: =MAX(0,MIN($F41,$C12)-MAX($E41,$B12)+1)/$G41 -> 0.090909091 | L41: =MAX(0,MIN($F41,$C13)-MAX($E41,$B13)+1)/$G41 -> 0 | M41: =MAX(0,MIN($F41,$C14)-MAX($E41,$B14)+1)/$G41 -> 0 | N41: =MAX(0,MIN($F41,$C15)-MAX($E41,$B15)+1)/$G41 -> 0 | O41: =MAX(0,MIN($F41,$C16)-MAX($E41,$B16)+1)/$G41 -> 0 | P41: =MAX(0,MIN($F41,$C17)-MAX($E41,$B17)+1)/$G41 -> 0 | Q41: =MAX(0,MIN($F41,$C18)-MAX($E41,$B18)+1)/$G41 -> 0 | R41: =MAX(0,MIN($F41,$C19)-MAX($E41,$B19)+1)/$G41 -> 0 | S41: =MAX(0,MIN($F41,$C20)-MAX($E41,$B20)+1)/$G41 -> 0 | T41: =MAX(0,MIN($F41,$C21)-MAX($E41,$B21)+1)/$G41 -> 0 | U41: =MAX(0,MIN($F41,$C22)-MAX($E41,$B22)+1)/$G41 -> 0 | V41: =MAX(0,MIN($F41,$C23)-MAX($E41,$B23)+1)/$G41 -> 0 | W41: =MAX(0,MIN($F41,$C24)-MAX($E41,$B24)+1)/$G41 -> 0 | X41: =MAX(0,MIN($F41,$C25)-MAX($E41,$B25)+1)/$G41 -> 0 | Y41: =MAX(0,MIN($F41,$C26)-MAX($E41,$B26)+1)/$G41 -> 0 | Z41: =MAX(0,MIN($F41,$C27)-MAX($E41,$B27)+1)/$G41 -> 0 | AA41: =MAX(0,MIN($F41,$C28)-MAX($E41,$B28)+1)/$G41 -> 0 | AB41: =MAX(0,MIN($F41,$C29)-MAX($E41,$B29)+1)/$G41 -> 0 | AC41: =MAX(0,MIN($F41,$C30)-MAX($E41,$B30)+1)/$G41 -> 0
A42: ='06_Presupuesto'!A347 -> E | B42: ='06_Presupuesto'!E347 -> 0.032385703 | C42: ='06_Presupuesto'!C347 -> 1838305.9 | D42: ='06_Presupuesto'!D347 -> 2297882.4 | E42: ='06_Presupuesto'!F347 -> 46350 | F42: ='06_Presupuesto'!G347 -> 46358 | G42: =F42-E42+1 -> 9 | H42: =MAX(0,MIN($F42,$C9)-MAX($E42,$B9)+1)/$G42 -> 0 | I42: =MAX(0,MIN($F42,$C10)-MAX($E42,$B10)+1)/$G42 -> 0 | J42: =MAX(0,MIN($F42,$C11)-MAX($E42,$B11)+1)/$G42 -> 0 | K42: =MAX(0,MIN($F42,$C12)-MAX($E42,$B12)+1)/$G42 -> 0.66666667 | L42: =MAX(0,MIN($F42,$C13)-MAX($E42,$B13)+1)/$G42 -> 0.33333333 | M42: =MAX(0,MIN($F42,$C14)-MAX($E42,$B14)+1)/$G42 -> 0 | N42: =MAX(0,MIN($F42,$C15)-MAX($E42,$B15)+1)/$G42 -> 0 | O42: =MAX(0,MIN($F42,$C16)-MAX($E42,$B16)+1)/$G42 -> 0 | P42: =MAX(0,MIN($F42,$C17)-MAX($E42,$B17)+1)/$G42 -> 0 | Q42: =MAX(0,MIN($F42,$C18)-MAX($E42,$B18)+1)/$G42 -> 0 | R42: =MAX(0,MIN($F42,$C19)-MAX($E42,$B19)+1)/$G42 -> 0 | S42: =MAX(0,MIN($F42,$C20)-MAX($E42,$B20)+1)/$G42 -> 0 | T42: =MAX(0,MIN($F42,$C21)-MAX($E42,$B21)+1)/$G42 -> 0 | U42: =MAX(0,MIN($F42,$C22)-MAX($E42,$B22)+1)/$G42 -> 0 | V42: =MAX(0,MIN($F42,$C23)-MAX($E42,$B23)+1)/$G42 -> 0 | W42: =MAX(0,MIN($F42,$C24)-MAX($E42,$B24)+1)/$G42 -> 0 | X42: =MAX(0,MIN($F42,$C25)-MAX($E42,$B25)+1)/$G42 -> 0 | Y42: =MAX(0,MIN($F42,$C26)-MAX($E42,$B26)+1)/$G42 -> 0 | Z42: =MAX(0,MIN($F42,$C27)-MAX($E42,$B27)+1)/$G42 -> 0 | AA42: =MAX(0,MIN($F42,$C28)-MAX($E42,$B28)+1)/$G42 -> 0 | AB42: =MAX(0,MIN($F42,$C29)-MAX($E42,$B29)+1)/$G42 -> 0 | AC42: =MAX(0,MIN($F42,$C30)-MAX($E42,$B30)+1)/$G42 -> 0
A43: ='06_Presupuesto'!A348 -> F | B43: ='06_Presupuesto'!E348 -> 0.033311008 | C43: ='06_Presupuesto'!C348 -> 376890.76 | D43: ='06_Presupuesto'!D348 -> 471113.45 | E43: ='06_Presupuesto'!F348 -> 46359 | F43: ='06_Presupuesto'!G348 -> 46363 | G43: =F43-E43+1 -> 5 | H43: =MAX(0,MIN($F43,$C9)-MAX($E43,$B9)+1)/$G43 -> 0 | I43: =MAX(0,MIN($F43,$C10)-MAX($E43,$B10)+1)/$G43 -> 0 | J43: =MAX(0,MIN($F43,$C11)-MAX($E43,$B11)+1)/$G43 -> 0 | K43: =MAX(0,MIN($F43,$C12)-MAX($E43,$B12)+1)/$G43 -> 0 | L43: =MAX(0,MIN($F43,$C13)-MAX($E43,$B13)+1)/$G43 -> 0.8 | M43: =MAX(0,MIN($F43,$C14)-MAX($E43,$B14)+1)/$G43 -> 0.2 | N43: =MAX(0,MIN($F43,$C15)-MAX($E43,$B15)+1)/$G43 -> 0 | O43: =MAX(0,MIN($F43,$C16)-MAX($E43,$B16)+1)/$G43 -> 0 | P43: =MAX(0,MIN($F43,$C17)-MAX($E43,$B17)+1)/$G43 -> 0 | Q43: =MAX(0,MIN($F43,$C18)-MAX($E43,$B18)+1)/$G43 -> 0 | R43: =MAX(0,MIN($F43,$C19)-MAX($E43,$B19)+1)/$G43 -> 0 | S43: =MAX(0,MIN($F43,$C20)-MAX($E43,$B20)+1)/$G43 -> 0 | T43: =MAX(0,MIN($F43,$C21)-MAX($E43,$B21)+1)/$G43 -> 0 | U43: =MAX(0,MIN($F43,$C22)-MAX($E43,$B22)+1)/$G43 -> 0 | V43: =MAX(0,MIN($F43,$C23)-MAX($E43,$B23)+1)/$G43 -> 0 | W43: =MAX(0,MIN($F43,$C24)-MAX($E43,$B24)+1)/$G43 -> 0 | X43: =MAX(0,MIN($F43,$C25)-MAX($E43,$B25)+1)/$G43 -> 0 | Y43: =MAX(0,MIN($F43,$C26)-MAX($E43,$B26)+1)/$G43 -> 0 | Z43: =MAX(0,MIN($F43,$C27)-MAX($E43,$B27)+1)/$G43 -> 0 | AA43: =MAX(0,MIN($F43,$C28)-MAX($E43,$B28)+1)/$G43 -> 0 | AB43: =MAX(0,MIN($F43,$C29)-MAX($E43,$B29)+1)/$G43 -> 0 | AC43: =MAX(0,MIN($F43,$C30)-MAX($E43,$B30)+1)/$G43 -> 0
A44: ='06_Presupuesto'!A349 -> G | B44: ='06_Presupuesto'!E349 -> 0.044414678 | C44: ='06_Presupuesto'!C349 -> 2647058.8 | D44: ='06_Presupuesto'!D349 -> 3308823.5 | E44: ='06_Presupuesto'!F349 -> 46364 | F44: ='06_Presupuesto'!G349 -> 46376 | G44: =F44-E44+1 -> 13 | H44: =MAX(0,MIN($F44,$C9)-MAX($E44,$B9)+1)/$G44 -> 0 | I44: =MAX(0,MIN($F44,$C10)-MAX($E44,$B10)+1)/$G44 -> 0 | J44: =MAX(0,MIN($F44,$C11)-MAX($E44,$B11)+1)/$G44 -> 0 | K44: =MAX(0,MIN($F44,$C12)-MAX($E44,$B12)+1)/$G44 -> 0 | L44: =MAX(0,MIN($F44,$C13)-MAX($E44,$B13)+1)/$G44 -> 0 | M44: =MAX(0,MIN($F44,$C14)-MAX($E44,$B14)+1)/$G44 -> 0.46153846 | N44: =MAX(0,MIN($F44,$C15)-MAX($E44,$B15)+1)/$G44 -> 0.53846154 | O44: =MAX(0,MIN($F44,$C16)-MAX($E44,$B16)+1)/$G44 -> 0 | P44: =MAX(0,MIN($F44,$C17)-MAX($E44,$B17)+1)/$G44 -> 0 | Q44: =MAX(0,MIN($F44,$C18)-MAX($E44,$B18)+1)/$G44 -> 0 | R44: =MAX(0,MIN($F44,$C19)-MAX($E44,$B19)+1)/$G44 -> 0 | S44: =MAX(0,MIN($F44,$C20)-MAX($E44,$B20)+1)/$G44 -> 0 | T44: =MAX(0,MIN($F44,$C21)-MAX($E44,$B21)+1)/$G44 -> 0 | U44: =MAX(0,MIN($F44,$C22)-MAX($E44,$B22)+1)/$G44 -> 0 | V44: =MAX(0,MIN($F44,$C23)-MAX($E44,$B23)+1)/$G44 -> 0 | W44: =MAX(0,MIN($F44,$C24)-MAX($E44,$B24)+1)/$G44 -> 0 | X44: =MAX(0,MIN($F44,$C25)-MAX($E44,$B25)+1)/$G44 -> 0 | Y44: =MAX(0,MIN($F44,$C26)-MAX($E44,$B26)+1)/$G44 -> 0 | Z44: =MAX(0,MIN($F44,$C27)-MAX($E44,$B27)+1)/$G44 -> 0 | AA44: =MAX(0,MIN($F44,$C28)-MAX($E44,$B28)+1)/$G44 -> 0 | AB44: =MAX(0,MIN($F44,$C29)-MAX($E44,$B29)+1)/$G44 -> 0 | AC44: =MAX(0,MIN($F44,$C30)-MAX($E44,$B30)+1)/$G44 -> 0
A45: ='06_Presupuesto'!A350 -> H | B45: ='06_Presupuesto'!E350 -> 0.037673164 | C45: ='06_Presupuesto'!C350 -> 4864860.5 | D45: ='06_Presupuesto'!D350 -> 6081075.6 | E45: ='06_Presupuesto'!F350 -> 46377 | F45: ='06_Presupuesto'!G350 -> 46388 | G45: =F45-E45+1 -> 12 | H45: =MAX(0,MIN($F45,$C9)-MAX($E45,$B9)+1)/$G45 -> 0 | I45: =MAX(0,MIN($F45,$C10)-MAX($E45,$B10)+1)/$G45 -> 0 | J45: =MAX(0,MIN($F45,$C11)-MAX($E45,$B11)+1)/$G45 -> 0 | K45: =MAX(0,MIN($F45,$C12)-MAX($E45,$B12)+1)/$G45 -> 0 | L45: =MAX(0,MIN($F45,$C13)-MAX($E45,$B13)+1)/$G45 -> 0 | M45: =MAX(0,MIN($F45,$C14)-MAX($E45,$B14)+1)/$G45 -> 0 | N45: =MAX(0,MIN($F45,$C15)-MAX($E45,$B15)+1)/$G45 -> 0 | O45: =MAX(0,MIN($F45,$C16)-MAX($E45,$B16)+1)/$G45 -> 0.58333333 | P45: =MAX(0,MIN($F45,$C17)-MAX($E45,$B17)+1)/$G45 -> 0.41666667 | Q45: =MAX(0,MIN($F45,$C18)-MAX($E45,$B18)+1)/$G45 -> 0 | R45: =MAX(0,MIN($F45,$C19)-MAX($E45,$B19)+1)/$G45 -> 0 | S45: =MAX(0,MIN($F45,$C20)-MAX($E45,$B20)+1)/$G45 -> 0 | T45: =MAX(0,MIN($F45,$C21)-MAX($E45,$B21)+1)/$G45 -> 0 | U45: =MAX(0,MIN($F45,$C22)-MAX($E45,$B22)+1)/$G45 -> 0 | V45: =MAX(0,MIN($F45,$C23)-MAX($E45,$B23)+1)/$G45 -> 0 | W45: =MAX(0,MIN($F45,$C24)-MAX($E45,$B24)+1)/$G45 -> 0 | X45: =MAX(0,MIN($F45,$C25)-MAX($E45,$B25)+1)/$G45 -> 0 | Y45: =MAX(0,MIN($F45,$C26)-MAX($E45,$B26)+1)/$G45 -> 0 | Z45: =MAX(0,MIN($F45,$C27)-MAX($E45,$B27)+1)/$G45 -> 0 | AA45: =MAX(0,MIN($F45,$C28)-MAX($E45,$B28)+1)/$G45 -> 0 | AB45: =MAX(0,MIN($F45,$C29)-MAX($E45,$B29)+1)/$G45 -> 0 | AC45: =MAX(0,MIN($F45,$C30)-MAX($E45,$B30)+1)/$G45 -> 0
A46: ='06_Presupuesto'!A351 -> I | B46: ='06_Presupuesto'!E351 -> 0.088829356 | C46: ='06_Presupuesto'!C351 -> 2246000 | D46: ='06_Presupuesto'!D351 -> 2807500 | E46: ='06_Presupuesto'!F351 -> 46377 | F46: ='06_Presupuesto'!G351 -> 46396 | G46: =F46-E46+1 -> 20 | H46: =MAX(0,MIN($F46,$C9)-MAX($E46,$B9)+1)/$G46 -> 0 | I46: =MAX(0,MIN($F46,$C10)-MAX($E46,$B10)+1)/$G46 -> 0 | J46: =MAX(0,MIN($F46,$C11)-MAX($E46,$B11)+1)/$G46 -> 0 | K46: =MAX(0,MIN($F46,$C12)-MAX($E46,$B12)+1)/$G46 -> 0 | L46: =MAX(0,MIN($F46,$C13)-MAX($E46,$B13)+1)/$G46 -> 0 | M46: =MAX(0,MIN($F46,$C14)-MAX($E46,$B14)+1)/$G46 -> 0 | N46: =MAX(0,MIN($F46,$C15)-MAX($E46,$B15)+1)/$G46 -> 0 | O46: =MAX(0,MIN($F46,$C16)-MAX($E46,$B16)+1)/$G46 -> 0.35 | P46: =MAX(0,MIN($F46,$C17)-MAX($E46,$B17)+1)/$G46 -> 0.35 | Q46: =MAX(0,MIN($F46,$C18)-MAX($E46,$B18)+1)/$G46 -> 0.3 | R46: =MAX(0,MIN($F46,$C19)-MAX($E46,$B19)+1)/$G46 -> 0 | S46: =MAX(0,MIN($F46,$C20)-MAX($E46,$B20)+1)/$G46 -> 0 | T46: =MAX(0,MIN($F46,$C21)-MAX($E46,$B21)+1)/$G46 -> 0 | U46: =MAX(0,MIN($F46,$C22)-MAX($E46,$B22)+1)/$G46 -> 0 | V46: =MAX(0,MIN($F46,$C23)-MAX($E46,$B23)+1)/$G46 -> 0 | W46: =MAX(0,MIN($F46,$C24)-MAX($E46,$B24)+1)/$G46 -> 0 | X46: =MAX(0,MIN($F46,$C25)-MAX($E46,$B25)+1)/$G46 -> 0 | Y46: =MAX(0,MIN($F46,$C26)-MAX($E46,$B26)+1)/$G46 -> 0 | Z46: =MAX(0,MIN($F46,$C27)-MAX($E46,$B27)+1)/$G46 -> 0 | AA46: =MAX(0,MIN($F46,$C28)-MAX($E46,$B28)+1)/$G46 -> 0 | AB46: =MAX(0,MIN($F46,$C29)-MAX($E46,$B29)+1)/$G46 -> 0 | AC46: =MAX(0,MIN($F46,$C30)-MAX($E46,$B30)+1)/$G46 -> 0
A47: ='06_Presupuesto'!A352 -> J | B47: ='06_Presupuesto'!E352 -> 0.04688216 | C47: ='06_Presupuesto'!C352 -> 3300826.1 | D47: ='06_Presupuesto'!D352 -> 4126032.6 | E47: ='06_Presupuesto'!F352 -> 46397 | F47: ='06_Presupuesto'!G352 -> 46408 | G47: =F47-E47+1 -> 12 | H47: =MAX(0,MIN($F47,$C9)-MAX($E47,$B9)+1)/$G47 -> 0 | I47: =MAX(0,MIN($F47,$C10)-MAX($E47,$B10)+1)/$G47 -> 0 | J47: =MAX(0,MIN($F47,$C11)-MAX($E47,$B11)+1)/$G47 -> 0 | K47: =MAX(0,MIN($F47,$C12)-MAX($E47,$B12)+1)/$G47 -> 0 | L47: =MAX(0,MIN($F47,$C13)-MAX($E47,$B13)+1)/$G47 -> 0 | M47: =MAX(0,MIN($F47,$C14)-MAX($E47,$B14)+1)/$G47 -> 0 | N47: =MAX(0,MIN($F47,$C15)-MAX($E47,$B15)+1)/$G47 -> 0 | O47: =MAX(0,MIN($F47,$C16)-MAX($E47,$B16)+1)/$G47 -> 0 | P47: =MAX(0,MIN($F47,$C17)-MAX($E47,$B17)+1)/$G47 -> 0 | Q47: =MAX(0,MIN($F47,$C18)-MAX($E47,$B18)+1)/$G47 -> 0.083333333 | R47: =MAX(0,MIN($F47,$C19)-MAX($E47,$B19)+1)/$G47 -> 0.58333333 | S47: =MAX(0,MIN($F47,$C20)-MAX($E47,$B20)+1)/$G47 -> 0.33333333 | T47: =MAX(0,MIN($F47,$C21)-MAX($E47,$B21)+1)/$G47 -> 0 | U47: =MAX(0,MIN($F47,$C22)-MAX($E47,$B22)+1)/$G47 -> 0 | V47: =MAX(0,MIN($F47,$C23)-MAX($E47,$B23)+1)/$G47 -> 0 | W47: =MAX(0,MIN($F47,$C24)-MAX($E47,$B24)+1)/$G47 -> 0 | X47: =MAX(0,MIN($F47,$C25)-MAX($E47,$B25)+1)/$G47 -> 0 | Y47: =MAX(0,MIN($F47,$C26)-MAX($E47,$B26)+1)/$G47 -> 0 | Z47: =MAX(0,MIN($F47,$C27)-MAX($E47,$B27)+1)/$G47 -> 0 | AA47: =MAX(0,MIN($F47,$C28)-MAX($E47,$B28)+1)/$G47 -> 0 | AB47: =MAX(0,MIN($F47,$C29)-MAX($E47,$B29)+1)/$G47 -> 0 | AC47: =MAX(0,MIN($F47,$C30)-MAX($E47,$B30)+1)/$G47 -> 0
A48: ='06_Presupuesto'!A353 -> K | B48: ='06_Presupuesto'!E353 -> 0.044414678 | C48: ='06_Presupuesto'!C353 -> 12679328 | D48: ='06_Presupuesto'!D353 -> 15849160 | E48: ='06_Presupuesto'!F353 -> 46377 | F48: ='06_Presupuesto'!G353 -> 46394 | G48: =F48-E48+1 -> 18 | H48: =MAX(0,MIN($F48,$C9)-MAX($E48,$B9)+1)/$G48 -> 0 | I48: =MAX(0,MIN($F48,$C10)-MAX($E48,$B10)+1)/$G48 -> 0 | J48: =MAX(0,MIN($F48,$C11)-MAX($E48,$B11)+1)/$G48 -> 0 | K48: =MAX(0,MIN($F48,$C12)-MAX($E48,$B12)+1)/$G48 -> 0 | L48: =MAX(0,MIN($F48,$C13)-MAX($E48,$B13)+1)/$G48 -> 0 | M48: =MAX(0,MIN($F48,$C14)-MAX($E48,$B14)+1)/$G48 -> 0 | N48: =MAX(0,MIN($F48,$C15)-MAX($E48,$B15)+1)/$G48 -> 0 | O48: =MAX(0,MIN($F48,$C16)-MAX($E48,$B16)+1)/$G48 -> 0.38888889 | P48: =MAX(0,MIN($F48,$C17)-MAX($E48,$B17)+1)/$G48 -> 0.38888889 | Q48: =MAX(0,MIN($F48,$C18)-MAX($E48,$B18)+1)/$G48 -> 0.22222222 | R48: =MAX(0,MIN($F48,$C19)-MAX($E48,$B19)+1)/$G48 -> 0 | S48: =MAX(0,MIN($F48,$C20)-MAX($E48,$B20)+1)/$G48 -> 0 | T48: =MAX(0,MIN($F48,$C21)-MAX($E48,$B21)+1)/$G48 -> 0 | U48: =MAX(0,MIN($F48,$C22)-MAX($E48,$B22)+1)/$G48 -> 0 | V48: =MAX(0,MIN($F48,$C23)-MAX($E48,$B23)+1)/$G48 -> 0 | W48: =MAX(0,MIN($F48,$C24)-MAX($E48,$B24)+1)/$G48 -> 0 | X48: =MAX(0,MIN($F48,$C25)-MAX($E48,$B25)+1)/$G48 -> 0 | Y48: =MAX(0,MIN($F48,$C26)-MAX($E48,$B26)+1)/$G48 -> 0 | Z48: =MAX(0,MIN($F48,$C27)-MAX($E48,$B27)+1)/$G48 -> 0 | AA48: =MAX(0,MIN($F48,$C28)-MAX($E48,$B28)+1)/$G48 -> 0 | AB48: =MAX(0,MIN($F48,$C29)-MAX($E48,$B29)+1)/$G48 -> 0 | AC48: =MAX(0,MIN($F48,$C30)-MAX($E48,$B30)+1)/$G48 -> 0
A49: ='06_Presupuesto'!A354 -> L | B49: ='06_Presupuesto'!E354 -> 0.044414678 | C49: ='06_Presupuesto'!C354 -> 4052689.1 | D49: ='06_Presupuesto'!D354 -> 5065861.3 | E49: ='06_Presupuesto'!F354 -> 46409 | F49: ='06_Presupuesto'!G354 -> 46422 | G49: =F49-E49+1 -> 14 | H49: =MAX(0,MIN($F49,$C9)-MAX($E49,$B9)+1)/$G49 -> 0 | I49: =MAX(0,MIN($F49,$C10)-MAX($E49,$B10)+1)/$G49 -> 0 | J49: =MAX(0,MIN($F49,$C11)-MAX($E49,$B11)+1)/$G49 -> 0 | K49: =MAX(0,MIN($F49,$C12)-MAX($E49,$B12)+1)/$G49 -> 0 | L49: =MAX(0,MIN($F49,$C13)-MAX($E49,$B13)+1)/$G49 -> 0 | M49: =MAX(0,MIN($F49,$C14)-MAX($E49,$B14)+1)/$G49 -> 0 | N49: =MAX(0,MIN($F49,$C15)-MAX($E49,$B15)+1)/$G49 -> 0 | O49: =MAX(0,MIN($F49,$C16)-MAX($E49,$B16)+1)/$G49 -> 0 | P49: =MAX(0,MIN($F49,$C17)-MAX($E49,$B17)+1)/$G49 -> 0 | Q49: =MAX(0,MIN($F49,$C18)-MAX($E49,$B18)+1)/$G49 -> 0 | R49: =MAX(0,MIN($F49,$C19)-MAX($E49,$B19)+1)/$G49 -> 0 | S49: =MAX(0,MIN($F49,$C20)-MAX($E49,$B20)+1)/$G49 -> 0.21428571 | T49: =MAX(0,MIN($F49,$C21)-MAX($E49,$B21)+1)/$G49 -> 0.5 | U49: =MAX(0,MIN($F49,$C22)-MAX($E49,$B22)+1)/$G49 -> 0.28571429 | V49: =MAX(0,MIN($F49,$C23)-MAX($E49,$B23)+1)/$G49 -> 0 | W49: =MAX(0,MIN($F49,$C24)-MAX($E49,$B24)+1)/$G49 -> 0 | X49: =MAX(0,MIN($F49,$C25)-MAX($E49,$B25)+1)/$G49 -> 0 | Y49: =MAX(0,MIN($F49,$C26)-MAX($E49,$B26)+1)/$G49 -> 0 | Z49: =MAX(0,MIN($F49,$C27)-MAX($E49,$B27)+1)/$G49 -> 0 | AA49: =MAX(0,MIN($F49,$C28)-MAX($E49,$B28)+1)/$G49 -> 0 | AB49: =MAX(0,MIN($F49,$C29)-MAX($E49,$B29)+1)/$G49 -> 0 | AC49: =MAX(0,MIN($F49,$C30)-MAX($E49,$B30)+1)/$G49 -> 0
A50: ='06_Presupuesto'!A355 -> M | B50: ='06_Presupuesto'!E355 -> 0.044414678 | C50: ='06_Presupuesto'!C355 -> 2618455.5 | D50: ='06_Presupuesto'!D355 -> 3273069.3 | E50: ='06_Presupuesto'!F355 -> 46395 | F50: ='06_Presupuesto'!G355 -> 46406 | G50: =F50-E50+1 -> 12 | H50: =MAX(0,MIN($F50,$C9)-MAX($E50,$B9)+1)/$G50 -> 0 | I50: =MAX(0,MIN($F50,$C10)-MAX($E50,$B10)+1)/$G50 -> 0 | J50: =MAX(0,MIN($F50,$C11)-MAX($E50,$B11)+1)/$G50 -> 0 | K50: =MAX(0,MIN($F50,$C12)-MAX($E50,$B12)+1)/$G50 -> 0 | L50: =MAX(0,MIN($F50,$C13)-MAX($E50,$B13)+1)/$G50 -> 0 | M50: =MAX(0,MIN($F50,$C14)-MAX($E50,$B14)+1)/$G50 -> 0 | N50: =MAX(0,MIN($F50,$C15)-MAX($E50,$B15)+1)/$G50 -> 0 | O50: =MAX(0,MIN($F50,$C16)-MAX($E50,$B16)+1)/$G50 -> 0 | P50: =MAX(0,MIN($F50,$C17)-MAX($E50,$B17)+1)/$G50 -> 0 | Q50: =MAX(0,MIN($F50,$C18)-MAX($E50,$B18)+1)/$G50 -> 0.25 | R50: =MAX(0,MIN($F50,$C19)-MAX($E50,$B19)+1)/$G50 -> 0.58333333 | S50: =MAX(0,MIN($F50,$C20)-MAX($E50,$B20)+1)/$G50 -> 0.16666667 | T50: =MAX(0,MIN($F50,$C21)-MAX($E50,$B21)+1)/$G50 -> 0 | U50: =MAX(0,MIN($F50,$C22)-MAX($E50,$B22)+1)/$G50 -> 0 | V50: =MAX(0,MIN($F50,$C23)-MAX($E50,$B23)+1)/$G50 -> 0 | W50: =MAX(0,MIN($F50,$C24)-MAX($E50,$B24)+1)/$G50 -> 0 | X50: =MAX(0,MIN($F50,$C25)-MAX($E50,$B25)+1)/$G50 -> 0 | Y50: =MAX(0,MIN($F50,$C26)-MAX($E50,$B26)+1)/$G50 -> 0 | Z50: =MAX(0,MIN($F50,$C27)-MAX($E50,$B27)+1)/$G50 -> 0 | AA50: =MAX(0,MIN($F50,$C28)-MAX($E50,$B28)+1)/$G50 -> 0 | AB50: =MAX(0,MIN($F50,$C29)-MAX($E50,$B29)+1)/$G50 -> 0 | AC50: =MAX(0,MIN($F50,$C30)-MAX($E50,$B30)+1)/$G50 -> 0
A51: ='06_Presupuesto'!A356 -> N | B51: ='06_Presupuesto'!E356 -> 0.03997321 | C51: ='06_Presupuesto'!C356 -> 2673923.5 | D51: ='06_Presupuesto'!D356 -> 3342404.4 | E51: ='06_Presupuesto'!F356 -> 46359 | F51: ='06_Presupuesto'!G356 -> 46372 | G51: =F51-E51+1 -> 14 | H51: =MAX(0,MIN($F51,$C9)-MAX($E51,$B9)+1)/$G51 -> 0 | I51: =MAX(0,MIN($F51,$C10)-MAX($E51,$B10)+1)/$G51 -> 0 | J51: =MAX(0,MIN($F51,$C11)-MAX($E51,$B11)+1)/$G51 -> 0 | K51: =MAX(0,MIN($F51,$C12)-MAX($E51,$B12)+1)/$G51 -> 0 | L51: =MAX(0,MIN($F51,$C13)-MAX($E51,$B13)+1)/$G51 -> 0.28571429 | M51: =MAX(0,MIN($F51,$C14)-MAX($E51,$B14)+1)/$G51 -> 0.5 | N51: =MAX(0,MIN($F51,$C15)-MAX($E51,$B15)+1)/$G51 -> 0.21428571 | O51: =MAX(0,MIN($F51,$C16)-MAX($E51,$B16)+1)/$G51 -> 0 | P51: =MAX(0,MIN($F51,$C17)-MAX($E51,$B17)+1)/$G51 -> 0 | Q51: =MAX(0,MIN($F51,$C18)-MAX($E51,$B18)+1)/$G51 -> 0 | R51: =MAX(0,MIN($F51,$C19)-MAX($E51,$B19)+1)/$G51 -> 0 | S51: =MAX(0,MIN($F51,$C20)-MAX($E51,$B20)+1)/$G51 -> 0 | T51: =MAX(0,MIN($F51,$C21)-MAX($E51,$B21)+1)/$G51 -> 0 | U51: =MAX(0,MIN($F51,$C22)-MAX($E51,$B22)+1)/$G51 -> 0 | V51: =MAX(0,MIN($F51,$C23)-MAX($E51,$B23)+1)/$G51 -> 0 | W51: =MAX(0,MIN($F51,$C24)-MAX($E51,$B24)+1)/$G51 -> 0 | X51: =MAX(0,MIN($F51,$C25)-MAX($E51,$B25)+1)/$G51 -> 0 | Y51: =MAX(0,MIN($F51,$C26)-MAX($E51,$B26)+1)/$G51 -> 0 | Z51: =MAX(0,MIN($F51,$C27)-MAX($E51,$B27)+1)/$G51 -> 0 | AA51: =MAX(0,MIN($F51,$C28)-MAX($E51,$B28)+1)/$G51 -> 0 | AB51: =MAX(0,MIN($F51,$C29)-MAX($E51,$B29)+1)/$G51 -> 0 | AC51: =MAX(0,MIN($F51,$C30)-MAX($E51,$B30)+1)/$G51 -> 0
A52: ='06_Presupuesto'!A357 -> O | B52: ='06_Presupuesto'!E357 -> 0.022207339 | C52: ='06_Presupuesto'!C357 -> 1382352.9 | D52: ='06_Presupuesto'!D357 -> 1727941.2 | E52: ='06_Presupuesto'!F357 -> 46407 | F52: ='06_Presupuesto'!G357 -> 46414 | G52: =F52-E52+1 -> 8 | H52: =MAX(0,MIN($F52,$C9)-MAX($E52,$B9)+1)/$G52 -> 0 | I52: =MAX(0,MIN($F52,$C10)-MAX($E52,$B10)+1)/$G52 -> 0 | J52: =MAX(0,MIN($F52,$C11)-MAX($E52,$B11)+1)/$G52 -> 0 | K52: =MAX(0,MIN($F52,$C12)-MAX($E52,$B12)+1)/$G52 -> 0 | L52: =MAX(0,MIN($F52,$C13)-MAX($E52,$B13)+1)/$G52 -> 0 | M52: =MAX(0,MIN($F52,$C14)-MAX($E52,$B14)+1)/$G52 -> 0 | N52: =MAX(0,MIN($F52,$C15)-MAX($E52,$B15)+1)/$G52 -> 0 | O52: =MAX(0,MIN($F52,$C16)-MAX($E52,$B16)+1)/$G52 -> 0 | P52: =MAX(0,MIN($F52,$C17)-MAX($E52,$B17)+1)/$G52 -> 0 | Q52: =MAX(0,MIN($F52,$C18)-MAX($E52,$B18)+1)/$G52 -> 0 | R52: =MAX(0,MIN($F52,$C19)-MAX($E52,$B19)+1)/$G52 -> 0 | S52: =MAX(0,MIN($F52,$C20)-MAX($E52,$B20)+1)/$G52 -> 0.625 | T52: =MAX(0,MIN($F52,$C21)-MAX($E52,$B21)+1)/$G52 -> 0.375 | U52: =MAX(0,MIN($F52,$C22)-MAX($E52,$B22)+1)/$G52 -> 0 | V52: =MAX(0,MIN($F52,$C23)-MAX($E52,$B23)+1)/$G52 -> 0 | W52: =MAX(0,MIN($F52,$C24)-MAX($E52,$B24)+1)/$G52 -> 0 | X52: =MAX(0,MIN($F52,$C25)-MAX($E52,$B25)+1)/$G52 -> 0 | Y52: =MAX(0,MIN($F52,$C26)-MAX($E52,$B26)+1)/$G52 -> 0 | Z52: =MAX(0,MIN($F52,$C27)-MAX($E52,$B27)+1)/$G52 -> 0 | AA52: =MAX(0,MIN($F52,$C28)-MAX($E52,$B28)+1)/$G52 -> 0 | AB52: =MAX(0,MIN($F52,$C29)-MAX($E52,$B29)+1)/$G52 -> 0 | AC52: =MAX(0,MIN($F52,$C30)-MAX($E52,$B30)+1)/$G52 -> 0
A53: ='06_Presupuesto'!A358 -> P | B53: ='06_Presupuesto'!E358 -> 0.022207339 | C53: ='06_Presupuesto'!C358 -> 0 | D53: ='06_Presupuesto'!D358 -> 0 | E53: ='06_Presupuesto'!F358 -> 46423 | F53: ='06_Presupuesto'!G358 -> 46430 | G53: =F53-E53+1 -> 8 | H53: =MAX(0,MIN($F53,$C9)-MAX($E53,$B9)+1)/$G53 -> 0 | I53: =MAX(0,MIN($F53,$C10)-MAX($E53,$B10)+1)/$G53 -> 0 | J53: =MAX(0,MIN($F53,$C11)-MAX($E53,$B11)+1)/$G53 -> 0 | K53: =MAX(0,MIN($F53,$C12)-MAX($E53,$B12)+1)/$G53 -> 0 | L53: =MAX(0,MIN($F53,$C13)-MAX($E53,$B13)+1)/$G53 -> 0 | M53: =MAX(0,MIN($F53,$C14)-MAX($E53,$B14)+1)/$G53 -> 0 | N53: =MAX(0,MIN($F53,$C15)-MAX($E53,$B15)+1)/$G53 -> 0 | O53: =MAX(0,MIN($F53,$C16)-MAX($E53,$B16)+1)/$G53 -> 0 | P53: =MAX(0,MIN($F53,$C17)-MAX($E53,$B17)+1)/$G53 -> 0 | Q53: =MAX(0,MIN($F53,$C18)-MAX($E53,$B18)+1)/$G53 -> 0 | R53: =MAX(0,MIN($F53,$C19)-MAX($E53,$B19)+1)/$G53 -> 0 | S53: =MAX(0,MIN($F53,$C20)-MAX($E53,$B20)+1)/$G53 -> 0 | T53: =MAX(0,MIN($F53,$C21)-MAX($E53,$B21)+1)/$G53 -> 0 | U53: =MAX(0,MIN($F53,$C22)-MAX($E53,$B22)+1)/$G53 -> 0.375 | V53: =MAX(0,MIN($F53,$C23)-MAX($E53,$B23)+1)/$G53 -> 0.625 | W53: =MAX(0,MIN($F53,$C24)-MAX($E53,$B24)+1)/$G53 -> 0 | X53: =MAX(0,MIN($F53,$C25)-MAX($E53,$B25)+1)/$G53 -> 0 | Y53: =MAX(0,MIN($F53,$C26)-MAX($E53,$B26)+1)/$G53 -> 0 | Z53: =MAX(0,MIN($F53,$C27)-MAX($E53,$B27)+1)/$G53 -> 0 | AA53: =MAX(0,MIN($F53,$C28)-MAX($E53,$B28)+1)/$G53 -> 0 | AB53: =MAX(0,MIN($F53,$C29)-MAX($E53,$B29)+1)/$G53 -> 0 | AC53: =MAX(0,MIN($F53,$C30)-MAX($E53,$B30)+1)/$G53 -> 0
A54: ='06_Presupuesto'!A359 -> Q | B54: ='06_Presupuesto'!E359 -> 0.11658853 | C54: ='06_Presupuesto'!C359 -> 3102857.1 | D54: ='06_Presupuesto'!D359 -> 3878571.4 | E54: ='06_Presupuesto'!F359 -> 46423 | F54: ='06_Presupuesto'!G359 -> 46438 | G54: =F54-E54+1 -> 16 | H54: =MAX(0,MIN($F54,$C9)-MAX($E54,$B9)+1)/$G54 -> 0 | I54: =MAX(0,MIN($F54,$C10)-MAX($E54,$B10)+1)/$G54 -> 0 | J54: =MAX(0,MIN($F54,$C11)-MAX($E54,$B11)+1)/$G54 -> 0 | K54: =MAX(0,MIN($F54,$C12)-MAX($E54,$B12)+1)/$G54 -> 0 | L54: =MAX(0,MIN($F54,$C13)-MAX($E54,$B13)+1)/$G54 -> 0 | M54: =MAX(0,MIN($F54,$C14)-MAX($E54,$B14)+1)/$G54 -> 0 | N54: =MAX(0,MIN($F54,$C15)-MAX($E54,$B15)+1)/$G54 -> 0 | O54: =MAX(0,MIN($F54,$C16)-MAX($E54,$B16)+1)/$G54 -> 0 | P54: =MAX(0,MIN($F54,$C17)-MAX($E54,$B17)+1)/$G54 -> 0 | Q54: =MAX(0,MIN($F54,$C18)-MAX($E54,$B18)+1)/$G54 -> 0 | R54: =MAX(0,MIN($F54,$C19)-MAX($E54,$B19)+1)/$G54 -> 0 | S54: =MAX(0,MIN($F54,$C20)-MAX($E54,$B20)+1)/$G54 -> 0 | T54: =MAX(0,MIN($F54,$C21)-MAX($E54,$B21)+1)/$G54 -> 0 | U54: =MAX(0,MIN($F54,$C22)-MAX($E54,$B22)+1)/$G54 -> 0.1875 | V54: =MAX(0,MIN($F54,$C23)-MAX($E54,$B23)+1)/$G54 -> 0.4375 | W54: =MAX(0,MIN($F54,$C24)-MAX($E54,$B24)+1)/$G54 -> 0.375 | X54: =MAX(0,MIN($F54,$C25)-MAX($E54,$B25)+1)/$G54 -> 0 | Y54: =MAX(0,MIN($F54,$C26)-MAX($E54,$B26)+1)/$G54 -> 0 | Z54: =MAX(0,MIN($F54,$C27)-MAX($E54,$B27)+1)/$G54 -> 0 | AA54: =MAX(0,MIN($F54,$C28)-MAX($E54,$B28)+1)/$G54 -> 0 | AB54: =MAX(0,MIN($F54,$C29)-MAX($E54,$B29)+1)/$G54 -> 0 | AC54: =MAX(0,MIN($F54,$C30)-MAX($E54,$B30)+1)/$G54 -> 0
A55: ='06_Presupuesto'!A360 -> R | B55: ='06_Presupuesto'!E360 -> 0.060277063 | C55: ='06_Presupuesto'!C360 -> 2127041.2 | D55: ='06_Presupuesto'!D360 -> 2658801.5 | E55: ='06_Presupuesto'!F360 -> 46439 | F55: ='06_Presupuesto'!G360 -> 46450 | G55: =F55-E55+1 -> 12 | H55: =MAX(0,MIN($F55,$C9)-MAX($E55,$B9)+1)/$G55 -> 0 | I55: =MAX(0,MIN($F55,$C10)-MAX($E55,$B10)+1)/$G55 -> 0 | J55: =MAX(0,MIN($F55,$C11)-MAX($E55,$B11)+1)/$G55 -> 0 | K55: =MAX(0,MIN($F55,$C12)-MAX($E55,$B12)+1)/$G55 -> 0 | L55: =MAX(0,MIN($F55,$C13)-MAX($E55,$B13)+1)/$G55 -> 0 | M55: =MAX(0,MIN($F55,$C14)-MAX($E55,$B14)+1)/$G55 -> 0 | N55: =MAX(0,MIN($F55,$C15)-MAX($E55,$B15)+1)/$G55 -> 0 | O55: =MAX(0,MIN($F55,$C16)-MAX($E55,$B16)+1)/$G55 -> 0 | P55: =MAX(0,MIN($F55,$C17)-MAX($E55,$B17)+1)/$G55 -> 0 | Q55: =MAX(0,MIN($F55,$C18)-MAX($E55,$B18)+1)/$G55 -> 0 | R55: =MAX(0,MIN($F55,$C19)-MAX($E55,$B19)+1)/$G55 -> 0 | S55: =MAX(0,MIN($F55,$C20)-MAX($E55,$B20)+1)/$G55 -> 0 | T55: =MAX(0,MIN($F55,$C21)-MAX($E55,$B21)+1)/$G55 -> 0 | U55: =MAX(0,MIN($F55,$C22)-MAX($E55,$B22)+1)/$G55 -> 0 | V55: =MAX(0,MIN($F55,$C23)-MAX($E55,$B23)+1)/$G55 -> 0 | W55: =MAX(0,MIN($F55,$C24)-MAX($E55,$B24)+1)/$G55 -> 0.083333333 | X55: =MAX(0,MIN($F55,$C25)-MAX($E55,$B25)+1)/$G55 -> 0.58333333 | Y55: =MAX(0,MIN($F55,$C26)-MAX($E55,$B26)+1)/$G55 -> 0.33333333 | Z55: =MAX(0,MIN($F55,$C27)-MAX($E55,$B27)+1)/$G55 -> 0 | AA55: =MAX(0,MIN($F55,$C28)-MAX($E55,$B28)+1)/$G55 -> 0 | AB55: =MAX(0,MIN($F55,$C29)-MAX($E55,$B29)+1)/$G55 -> 0 | AC55: =MAX(0,MIN($F55,$C30)-MAX($E55,$B30)+1)/$G55 -> 0
A56: ='06_Presupuesto'!A361 -> S | B56: ='06_Presupuesto'!E361 -> 0.066622017 | C56: ='06_Presupuesto'!C361 -> 3813445.4 | D56: ='06_Presupuesto'!D361 -> 4766806.7 | E56: ='06_Presupuesto'!F361 -> 46439 | F56: ='06_Presupuesto'!G361 -> 46448 | G56: =F56-E56+1 -> 10 | H56: =MAX(0,MIN($F56,$C9)-MAX($E56,$B9)+1)/$G56 -> 0 | I56: =MAX(0,MIN($F56,$C10)-MAX($E56,$B10)+1)/$G56 -> 0 | J56: =MAX(0,MIN($F56,$C11)-MAX($E56,$B11)+1)/$G56 -> 0 | K56: =MAX(0,MIN($F56,$C12)-MAX($E56,$B12)+1)/$G56 -> 0 | L56: =MAX(0,MIN($F56,$C13)-MAX($E56,$B13)+1)/$G56 -> 0 | M56: =MAX(0,MIN($F56,$C14)-MAX($E56,$B14)+1)/$G56 -> 0 | N56: =MAX(0,MIN($F56,$C15)-MAX($E56,$B15)+1)/$G56 -> 0 | O56: =MAX(0,MIN($F56,$C16)-MAX($E56,$B16)+1)/$G56 -> 0 | P56: =MAX(0,MIN($F56,$C17)-MAX($E56,$B17)+1)/$G56 -> 0 | Q56: =MAX(0,MIN($F56,$C18)-MAX($E56,$B18)+1)/$G56 -> 0 | R56: =MAX(0,MIN($F56,$C19)-MAX($E56,$B19)+1)/$G56 -> 0 | S56: =MAX(0,MIN($F56,$C20)-MAX($E56,$B20)+1)/$G56 -> 0 | T56: =MAX(0,MIN($F56,$C21)-MAX($E56,$B21)+1)/$G56 -> 0 | U56: =MAX(0,MIN($F56,$C22)-MAX($E56,$B22)+1)/$G56 -> 0 | V56: =MAX(0,MIN($F56,$C23)-MAX($E56,$B23)+1)/$G56 -> 0 | W56: =MAX(0,MIN($F56,$C24)-MAX($E56,$B24)+1)/$G56 -> 0.1 | X56: =MAX(0,MIN($F56,$C25)-MAX($E56,$B25)+1)/$G56 -> 0.7 | Y56: =MAX(0,MIN($F56,$C26)-MAX($E56,$B26)+1)/$G56 -> 0.2 | Z56: =MAX(0,MIN($F56,$C27)-MAX($E56,$B27)+1)/$G56 -> 0 | AA56: =MAX(0,MIN($F56,$C28)-MAX($E56,$B28)+1)/$G56 -> 0 | AB56: =MAX(0,MIN($F56,$C29)-MAX($E56,$B29)+1)/$G56 -> 0 | AC56: =MAX(0,MIN($F56,$C30)-MAX($E56,$B30)+1)/$G56 -> 0
A57: ='06_Presupuesto'!A362 -> T | B57: ='06_Presupuesto'!E362 -> 0.088829356 | C57: ='06_Presupuesto'!C362 -> 1976890.8 | D57: ='06_Presupuesto'!D362 -> 2471113.4 | E57: ='06_Presupuesto'!F362 -> 46451 | F57: ='06_Presupuesto'!G362 -> 46470 | G57: =F57-E57+1 -> 20 | H57: =MAX(0,MIN($F57,$C9)-MAX($E57,$B9)+1)/$G57 -> 0 | I57: =MAX(0,MIN($F57,$C10)-MAX($E57,$B10)+1)/$G57 -> 0 | J57: =MAX(0,MIN($F57,$C11)-MAX($E57,$B11)+1)/$G57 -> 0 | K57: =MAX(0,MIN($F57,$C12)-MAX($E57,$B12)+1)/$G57 -> 0 | L57: =MAX(0,MIN($F57,$C13)-MAX($E57,$B13)+1)/$G57 -> 0 | M57: =MAX(0,MIN($F57,$C14)-MAX($E57,$B14)+1)/$G57 -> 0 | N57: =MAX(0,MIN($F57,$C15)-MAX($E57,$B15)+1)/$G57 -> 0 | O57: =MAX(0,MIN($F57,$C16)-MAX($E57,$B16)+1)/$G57 -> 0 | P57: =MAX(0,MIN($F57,$C17)-MAX($E57,$B17)+1)/$G57 -> 0 | Q57: =MAX(0,MIN($F57,$C18)-MAX($E57,$B18)+1)/$G57 -> 0 | R57: =MAX(0,MIN($F57,$C19)-MAX($E57,$B19)+1)/$G57 -> 0 | S57: =MAX(0,MIN($F57,$C20)-MAX($E57,$B20)+1)/$G57 -> 0 | T57: =MAX(0,MIN($F57,$C21)-MAX($E57,$B21)+1)/$G57 -> 0 | U57: =MAX(0,MIN($F57,$C22)-MAX($E57,$B22)+1)/$G57 -> 0 | V57: =MAX(0,MIN($F57,$C23)-MAX($E57,$B23)+1)/$G57 -> 0 | W57: =MAX(0,MIN($F57,$C24)-MAX($E57,$B24)+1)/$G57 -> 0 | X57: =MAX(0,MIN($F57,$C25)-MAX($E57,$B25)+1)/$G57 -> 0 | Y57: =MAX(0,MIN($F57,$C26)-MAX($E57,$B26)+1)/$G57 -> 0.15 | Z57: =MAX(0,MIN($F57,$C27)-MAX($E57,$B27)+1)/$G57 -> 0.35 | AA57: =MAX(0,MIN($F57,$C28)-MAX($E57,$B28)+1)/$G57 -> 0.35 | AB57: =MAX(0,MIN($F57,$C29)-MAX($E57,$B29)+1)/$G57 -> 0.15 | AC57: =MAX(0,MIN($F57,$C30)-MAX($E57,$B30)+1)/$G57 -> 0
A58: ='06_Presupuesto'!A363 -> U | B58: ='06_Presupuesto'!E363 -> 0.066622017 | C58: ='06_Presupuesto'!C363 -> 13258235 | D58: ='06_Presupuesto'!D363 -> 16572794 | E58: ='06_Presupuesto'!F363 -> 46409 | F58: ='06_Presupuesto'!G363 -> 46424 | G58: =F58-E58+1 -> 16 | H58: =MAX(0,MIN($F58,$C9)-MAX($E58,$B9)+1)/$G58 -> 0 | I58: =MAX(0,MIN($F58,$C10)-MAX($E58,$B10)+1)/$G58 -> 0 | J58: =MAX(0,MIN($F58,$C11)-MAX($E58,$B11)+1)/$G58 -> 0 | K58: =MAX(0,MIN($F58,$C12)-MAX($E58,$B12)+1)/$G58 -> 0 | L58: =MAX(0,MIN($F58,$C13)-MAX($E58,$B13)+1)/$G58 -> 0 | M58: =MAX(0,MIN($F58,$C14)-MAX($E58,$B14)+1)/$G58 -> 0 | N58: =MAX(0,MIN($F58,$C15)-MAX($E58,$B15)+1)/$G58 -> 0 | O58: =MAX(0,MIN($F58,$C16)-MAX($E58,$B16)+1)/$G58 -> 0 | P58: =MAX(0,MIN($F58,$C17)-MAX($E58,$B17)+1)/$G58 -> 0 | Q58: =MAX(0,MIN($F58,$C18)-MAX($E58,$B18)+1)/$G58 -> 0 | R58: =MAX(0,MIN($F58,$C19)-MAX($E58,$B19)+1)/$G58 -> 0 | S58: =MAX(0,MIN($F58,$C20)-MAX($E58,$B20)+1)/$G58 -> 0.1875 | T58: =MAX(0,MIN($F58,$C21)-MAX($E58,$B21)+1)/$G58 -> 0.4375 | U58: =MAX(0,MIN($F58,$C22)-MAX($E58,$B22)+1)/$G58 -> 0.375 | V58: =MAX(0,MIN($F58,$C23)-MAX($E58,$B23)+1)/$G58 -> 0 | W58: =MAX(0,MIN($F58,$C24)-MAX($E58,$B24)+1)/$G58 -> 0 | X58: =MAX(0,MIN($F58,$C25)-MAX($E58,$B25)+1)/$G58 -> 0 | Y58: =MAX(0,MIN($F58,$C26)-MAX($E58,$B26)+1)/$G58 -> 0 | Z58: =MAX(0,MIN($F58,$C27)-MAX($E58,$B27)+1)/$G58 -> 0 | AA58: =MAX(0,MIN($F58,$C28)-MAX($E58,$B28)+1)/$G58 -> 0 | AB58: =MAX(0,MIN($F58,$C29)-MAX($E58,$B29)+1)/$G58 -> 0 | AC58: =MAX(0,MIN($F58,$C30)-MAX($E58,$B30)+1)/$G58 -> 0
A59: ='06_Presupuesto'!A364 -> V | B59: ='06_Presupuesto'!E364 -> 0.022207339 | C59: ='06_Presupuesto'!C364 -> 1398082.4 | D59: ='06_Presupuesto'!D364 -> 1747602.9 | E59: ='06_Presupuesto'!F364 -> 46471 | F59: ='06_Presupuesto'!G364 -> 46477 | G59: =F59-E59+1 -> 7 | H59: =MAX(0,MIN($F59,$C9)-MAX($E59,$B9)+1)/$G59 -> 0 | I59: =MAX(0,MIN($F59,$C10)-MAX($E59,$B10)+1)/$G59 -> 0 | J59: =MAX(0,MIN($F59,$C11)-MAX($E59,$B11)+1)/$G59 -> 0 | K59: =MAX(0,MIN($F59,$C12)-MAX($E59,$B12)+1)/$G59 -> 0 | L59: =MAX(0,MIN($F59,$C13)-MAX($E59,$B13)+1)/$G59 -> 0 | M59: =MAX(0,MIN($F59,$C14)-MAX($E59,$B14)+1)/$G59 -> 0 | N59: =MAX(0,MIN($F59,$C15)-MAX($E59,$B15)+1)/$G59 -> 0 | O59: =MAX(0,MIN($F59,$C16)-MAX($E59,$B16)+1)/$G59 -> 0 | P59: =MAX(0,MIN($F59,$C17)-MAX($E59,$B17)+1)/$G59 -> 0 | Q59: =MAX(0,MIN($F59,$C18)-MAX($E59,$B18)+1)/$G59 -> 0 | R59: =MAX(0,MIN($F59,$C19)-MAX($E59,$B19)+1)/$G59 -> 0 | S59: =MAX(0,MIN($F59,$C20)-MAX($E59,$B20)+1)/$G59 -> 0 | T59: =MAX(0,MIN($F59,$C21)-MAX($E59,$B21)+1)/$G59 -> 0 | U59: =MAX(0,MIN($F59,$C22)-MAX($E59,$B22)+1)/$G59 -> 0 | V59: =MAX(0,MIN($F59,$C23)-MAX($E59,$B23)+1)/$G59 -> 0 | W59: =MAX(0,MIN($F59,$C24)-MAX($E59,$B24)+1)/$G59 -> 0 | X59: =MAX(0,MIN($F59,$C25)-MAX($E59,$B25)+1)/$G59 -> 0 | Y59: =MAX(0,MIN($F59,$C26)-MAX($E59,$B26)+1)/$G59 -> 0 | Z59: =MAX(0,MIN($F59,$C27)-MAX($E59,$B27)+1)/$G59 -> 0 | AA59: =MAX(0,MIN($F59,$C28)-MAX($E59,$B28)+1)/$G59 -> 0 | AB59: =MAX(0,MIN($F59,$C29)-MAX($E59,$B29)+1)/$G59 -> 0.57142857 | AC59: =MAX(0,MIN($F59,$C30)-MAX($E59,$B30)+1)/$G59 -> 0.42857143
B69: PASO 7 · CURVA “S” FÍSICA · ES3 IND. 7
B70: GRUPO 4 · SEDE SOCIAL EL BOSQUE · ANDACOLLO
B71: DESARROLLO DIARIO POR PARTIDA · 1 = DÍA ACTIVO | F71: PLAZO DE EJECUCIÓN: 150 DÍAS CORRIDOS
B72: PROYECTO: CONSTRUCCIÓN SEDE SOCIAL EL BOSQUE | I72: MES 1 (30 DÍAS CORRIDOS) | AM72: MES 2 (30 DÍAS CORRIDOS) | BQ72: MES 3 (30 DÍAS CORRIDOS) | CU72: MES 4 (30 DÍAS CORRIDOS) | DY72: MES 5 (30 DÍAS CORRIDOS)
I73: SEMANA 1 | P73: SEMANA 2 | W73: SEMANA 3 | AD73: SEMANA 4 | AK73: SEMANA 5 | AR73: SEMANA 6 | AY73: SEMANA 7 | BF73: SEMANA 8 | BM73: SEMANA 9 | BT73: SEMANA 10 | CA73: SEMANA 11 | CH73: SEMANA 12 | CO73: SEMANA 13 | CV73: SEMANA 14 | DC73: SEMANA 15 | DJ73: SEMANA 16 | DQ73: SEMANA 17 | DX73: SEMANA 18 | EE73: SEMANA 19 | EL73: SEMANA 20 | ES73: SEMANA 21 | EZ73: SEMANA 22
B74: Ítem | C74: Partida | D74: Unidad | E74: Cantidad | F74: P.U. compensado | G74: Subtotal con IVA | H74: Duración (d) | I74: 1 | J74: 2 | K74: 3 | L74: 4 | M74: 5 | N74: 6 | O74: 7 | P74: 8 | Q74: 9 | R74: 10 | S74: 11 | T74: 12 | U74: 13 | V74: 14 | W74: 15 | X74: 16 | Y74: 17 | Z74: 18 | AA74: 19 | AB74: 20 | AC74: 21 | AD74: 22 | AE74: 23 | AF74: 24 | AG74: 25 | AH74: 26 | AI74: 27 | AJ74: 28 | AK74: 29 | AL74: 30 | AM74: 31 | AN74: 32 | AO74: 33 | AP74: 34 | AQ74: 35 | AR74: 36 | AS74: 37 | AT74: 38 | AU74: 39 | AV74: 40 | AW74: 41 | AX74: 42 | AY74: 43 | AZ74: 44 | BA74: 45 | BB74: 46 | BC74: 47 | BD74: 48 | BE74: 49 | BF74: 50 | BG74: 51 | BH74: 52 | BI74: 53 | BJ74: 54 | BK74: 55 | BL74: 56 | BM74: 57 | BN74: 58 | BO74: 59 | BP74: 60 | BQ74: 61 | BR74: 62 | BS74: 63 | BT74: 64 | BU74: 65 | BV74: 66 | BW74: 67 | BX74: 68 | BY74: 69 | BZ74: 70 | CA74: 71 | CB74: 72 | CC74: 73 | CD74: 74 | CE74: 75 | CF74: 76 | CG74: 77 | CH74: 78 | CI74: 79 | CJ74: 80 | CK74: 81 | CL74: 82 | CM74: 83 | CN74: 84 | CO74: 85 | CP74: 86 | CQ74: 87 | CR74: 88 | CS74: 89 | CT74: 90 | CU74: 91 | CV74: 92 | CW74: 93 | CX74: 94 | CY74: 95 | CZ74: 96 | DA74: 97 | DB74: 98 | DC74: 99 | DD74: 100 | DE74: 101 | DF74: 102 | DG74: 103 | DH74: 104 | DI74: 105 | DJ74: 106 | DK74: 107 | DL74: 108 | DM74: 109 | DN74: 110 | DO74: 111 | DP74: 112 | DQ74: 113 | DR74: 114 | DS74: 115 | DT74: 116 | DU74: 117 | DV74: 118 | DW74: 119 | DX74: 120 | DY74: 121 | DZ74: 122 | EA74: 123 | EB74: 124 | EC74: 125 | ED74: 126 | EE74: 127 | EF74: 128 | EG74: 129 | EH74: 130 | EI74: 131 | EJ74: 132 | EK74: 133 | EL74: 134 | EM74: 135 | EN74: 136 | EO74: 137 | EP74: 138 | EQ74: 139 | ER74: 140 | ES74: 141 | ET74: 142 | EU74: 143 | EV74: 144 | EW74: 145 | EX74: 146 | EY74: 147 | EZ74: 148 | FA74: 149 | FB74: 150 | FC74: Inicio día | FD74: Fin día | FE74: Peso físico
B75: INSTALACIÓN DE FAENAS
B76: ='03_CPM_Obra_Gruesa'!B145 -> 1.1 | C76: ='02_Rendimientos'!C6 -> Instalación de faenas y cierre perimetral | D76: ='02_Rendimientos'!E6 -> lote | E76: ='02_Rendimientos'!D6 -> 1 | F76: =IFERROR(G76/E76,0) -> 10544902 | G76: ='06_Presupuesto'!D343*(1+'02_Rendimientos'!B82) -> 10544902 | H76: ='02_Rendimientos'!K6 -> 6 | I76: =IF(AND(I$74>=FC76,I$74<=FD76),1,"") -> 1 | J76: =IF(AND(J$74>=FC76,J$74<=FD76),1,"") -> 1 | K76: =IF(AND(K$74>=FC76,K$74<=FD76),1,"") -> 1 | L76: =IF(AND(L$74>=FC76,L$74<=FD76),1,"") -> 1 | M76: =IF(AND(M$74>=FC76,M$74<=FD76),1,"") -> 1 | N76: =IF(AND(N$74>=FC76,N$74<=FD76),1,"") -> 1 | O76: =IF(AND(O$74>=FC76,O$74<=FD76),1,"") | P76: =IF(AND(P$74>=FC76,P$74<=FD76),1,"") | Q76: =IF(AND(Q$74>=FC76,Q$74<=FD76),1,"") | R76: =IF(AND(R$74>=FC76,R$74<=FD76),1,"") | S76: =IF(AND(S$74>=FC76,S$74<=FD76),1,"") | T76: =IF(AND(T$74>=FC76,T$74<=FD76),1,"") | U76: =IF(AND(U$74>=FC76,U$74<=FD76),1,"") | V76: =IF(AND(V$74>=FC76,V$74<=FD76),1,"") | W76: =IF(AND(W$74>=FC76,W$74<=FD76),1,"") | X76: =IF(AND(X$74>=FC76,X$74<=FD76),1,"") | Y76: =IF(AND(Y$74>=FC76,Y$74<=FD76),1,"") | Z76: =IF(AND(Z$74>=FC76,Z$74<=FD76),1,"") | AA76: =IF(AND(AA$74>=FC76,AA$74<=FD76),1,"") | AB76: =IF(AND(AB$74>=FC76,AB$74<=FD76),1,"") | AC76: =IF(AND(AC$74>=FC76,AC$74<=FD76),1,"") | AD76: =IF(AND(AD$74>=FC76,AD$74<=FD76),1,"") | AE76: =IF(AND(AE$74>=FC76,AE$74<=FD76),1,"") | AF76: =IF(AND(AF$74>=FC76,AF$74<=FD76),1,"") | AG76: =IF(AND(AG$74>=FC76,AG$74<=FD76),1,"") | AH76: =IF(AND(AH$74>=FC76,AH$74<=FD76),1,"") | AI76: =IF(AND(AI$74>=FC76,AI$74<=FD76),1,"") | AJ76: =IF(AND(AJ$74>=FC76,AJ$74<=FD76),1,"") | AK76: =IF(AND(AK$74>=FC76,AK$74<=FD76),1,"") | AL76: =IF(AND(AL$74>=FC76,AL$74<=FD76),1,"") | AM76: =IF(AND(AM$74>=FC76,AM$74<=FD76),1,"") | AN76: =IF(AND(AN$74>=FC76,AN$74<=FD76),1,"") | AO76: =IF(AND(AO$74>=FC76,AO$74<=FD76),1,"") | AP76: =IF(AND(AP$74>=FC76,AP$74<=FD76),1,"") | AQ76: =IF(AND(AQ$74>=FC76,AQ$74<=FD76),1,"") | AR76: =IF(AND(AR$74>=FC76,AR$74<=FD76),1,"") | AS76: =IF(AND(AS$74>=FC76,AS$74<=FD76),1,"") | AT76: =IF(AND(AT$74>=FC76,AT$74<=FD76),1,"") | AU76: =IF(AND(AU$74>=FC76,AU$74<=FD76),1,"") | AV76: =IF(AND(AV$74>=FC76,AV$74<=FD76),1,"") | AW76: =IF(AND(AW$74>=FC76,AW$74<=FD76),1,"") | AX76: =IF(AND(AX$74>=FC76,AX$74<=FD76),1,"") | AY76: =IF(AND(AY$74>=FC76,AY$74<=FD76),1,"") | AZ76: =IF(AND(AZ$74>=FC76,AZ$74<=FD76),1,"") | BA76: =IF(AND(BA$74>=FC76,BA$74<=FD76),1,"") | BB76: =IF(AND(BB$74>=FC76,BB$74<=FD76),1,"") | BC76: =IF(AND(BC$74>=FC76,BC$74<=FD76),1,"") | BD76: =IF(AND(BD$74>=FC76,BD$74<=FD76),1,"") | BE76: =IF(AND(BE$74>=FC76,BE$74<=FD76),1,"") | BF76: =IF(AND(BF$74>=FC76,BF$74<=FD76),1,"") | BG76: =IF(AND(BG$74>=FC76,BG$74<=FD76),1,"") | BH76: =IF(AND(BH$74>=FC76,BH$74<=FD76),1,"") | BI76: =IF(AND(BI$74>=FC76,BI$74<=FD76),1,"") | BJ76: =IF(AND(BJ$74>=FC76,BJ$74<=FD76),1,"") | BK76: =IF(AND(BK$74>=FC76,BK$74<=FD76),1,"") | BL76: =IF(AND(BL$74>=FC76,BL$74<=FD76),1,"") | BM76: =IF(AND(BM$74>=FC76,BM$74<=FD76),1,"") | BN76: =IF(AND(BN$74>=FC76,BN$74<=FD76),1,"") | BO76: =IF(AND(BO$74>=FC76,BO$74<=FD76),1,"") | BP76: =IF(AND(BP$74>=FC76,BP$74<=FD76),1,"") | BQ76: =IF(AND(BQ$74>=FC76,BQ$74<=FD76),1,"") | BR76: =IF(AND(BR$74>=FC76,BR$74<=FD76),1,"") | BS76: =IF(AND(BS$74>=FC76,BS$74<=FD76),1,"") | BT76: =IF(AND(BT$74>=FC76,BT$74<=FD76),1,"") | BU76: =IF(AND(BU$74>=FC76,BU$74<=FD76),1,"") | BV76: =IF(AND(BV$74>=FC76,BV$74<=FD76),1,"") | BW76: =IF(AND(BW$74>=FC76,BW$74<=FD76),1,"") | BX76: =IF(AND(BX$74>=FC76,BX$74<=FD76),1,"") | BY76: =IF(AND(BY$74>=FC76,BY$74<=FD76),1,"") | BZ76: =IF(AND(BZ$74>=FC76,BZ$74<=FD76),1,"") | CA76: =IF(AND(CA$74>=FC76,CA$74<=FD76),1,"") | CB76: =IF(AND(CB$74>=FC76,CB$74<=FD76),1,"") | CC76: =IF(AND(CC$74>=FC76,CC$74<=FD76),1,"") | CD76: =IF(AND(CD$74>=FC76,CD$74<=FD76),1,"") | CE76: =IF(AND(CE$74>=FC76,CE$74<=FD76),1,"") | CF76: =IF(AND(CF$74>=FC76,CF$74<=FD76),1,"") | CG76: =IF(AND(CG$74>=FC76,CG$74<=FD76),1,"") | CH76: =IF(AND(CH$74>=FC76,CH$74<=FD76),1,"") | CI76: =IF(AND(CI$74>=FC76,CI$74<=FD76),1,"") | CJ76: =IF(AND(CJ$74>=FC76,CJ$74<=FD76),1,"") | CK76: =IF(AND(CK$74>=FC76,CK$74<=FD76),1,"") | CL76: =IF(AND(CL$74>=FC76,CL$74<=FD76),1,"") | CM76: =IF(AND(CM$74>=FC76,CM$74<=FD76),1,"") | CN76: =IF(AND(CN$74>=FC76,CN$74<=FD76),1,"") | CO76: =IF(AND(CO$74>=FC76,CO$74<=FD76),1,"") | CP76: =IF(AND(CP$74>=FC76,CP$74<=FD76),1,"") | CQ76: =IF(AND(CQ$74>=FC76,CQ$74<=FD76),1,"") | CR76: =IF(AND(CR$74>=FC76,CR$74<=FD76),1,"") | CS76: =IF(AND(CS$74>=FC76,CS$74<=FD76),1,"") | CT76: =IF(AND(CT$74>=FC76,CT$74<=FD76),1,"") | CU76: =IF(AND(CU$74>=FC76,CU$74<=FD76),1,"") | CV76: =IF(AND(CV$74>=FC76,CV$74<=FD76),1,"") | CW76: =IF(AND(CW$74>=FC76,CW$74<=FD76),1,"") | CX76: =IF(AND(CX$74>=FC76,CX$74<=FD76),1,"") | CY76: =IF(AND(CY$74>=FC76,CY$74<=FD76),1,"") | CZ76: =IF(AND(CZ$74>=FC76,CZ$74<=FD76),1,"") | DA76: =IF(AND(DA$74>=FC76,DA$74<=FD76),1,"") | DB76: =IF(AND(DB$74>=FC76,DB$74<=FD76),1,"") | DC76: =IF(AND(DC$74>=FC76,DC$74<=FD76),1,"") | DD76: =IF(AND(DD$74>=FC76,DD$74<=FD76),1,"") | DE76: =IF(AND(DE$74>=FC76,DE$74<=FD76),1,"") | DF76: =IF(AND(DF$74>=FC76,DF$74<=FD76),1,"") | DG76: =IF(AND(DG$74>=FC76,DG$74<=FD76),1,"") | DH76: =IF(AND(DH$74>=FC76,DH$74<=FD76),1,"") | DI76: =IF(AND(DI$74>=FC76,DI$74<=FD76),1,"") | DJ76: =IF(AND(DJ$74>=FC76,DJ$74<=FD76),1,"") | DK76: =IF(AND(DK$74>=FC76,DK$74<=FD76),1,"") | DL76: =IF(AND(DL$74>=FC76,DL$74<=FD76),1,"") | DM76: =IF(AND(DM$74>=FC76,DM$74<=FD76),1,"") | DN76: =IF(AND(DN$74>=FC76,DN$74<=FD76),1,"") | DO76: =IF(AND(DO$74>=FC76,DO$74<=FD76),1,"") | DP76: =IF(AND(DP$74>=FC76,DP$74<=FD76),1,"") | DQ76: =IF(AND(DQ$74>=FC76,DQ$74<=FD76),1,"") | DR76: =IF(AND(DR$74>=FC76,DR$74<=FD76),1,"") | DS76: =IF(AND(DS$74>=FC76,DS$74<=FD76),1,"") | DT76: =IF(AND(DT$74>=FC76,DT$74<=FD76),1,"") | DU76: =IF(AND(DU$74>=FC76,DU$74<=FD76),1,"") | DV76: =IF(AND(DV$74>=FC76,DV$74<=FD76),1,"") | DW76: =IF(AND(DW$74>=FC76,DW$74<=FD76),1,"") | DX76: =IF(AND(DX$74>=FC76,DX$74<=FD76),1,"") | DY76: =IF(AND(DY$74>=FC76,DY$74<=FD76),1,"") | DZ76: =IF(AND(DZ$74>=FC76,DZ$74<=FD76),1,"") | EA76: =IF(AND(EA$74>=FC76,EA$74<=FD76),1,"") | EB76: =IF(AND(EB$74>=FC76,EB$74<=FD76),1,"") | EC76: =IF(AND(EC$74>=FC76,EC$74<=FD76),1,"") | ED76: =IF(AND(ED$74>=FC76,ED$74<=FD76),1,"") | EE76: =IF(AND(EE$74>=FC76,EE$74<=FD76),1,"") | EF76: =IF(AND(EF$74>=FC76,EF$74<=FD76),1,"") | EG76: =IF(AND(EG$74>=FC76,EG$74<=FD76),1,"") | EH76: =IF(AND(EH$74>=FC76,EH$74<=FD76),1,"") | EI76: =IF(AND(EI$74>=FC76,EI$74<=FD76),1,"") | EJ76: =IF(AND(EJ$74>=FC76,EJ$74<=FD76),1,"") | EK76: =IF(AND(EK$74>=FC76,EK$74<=FD76),1,"") | EL76: =IF(AND(EL$74>=FC76,EL$74<=FD76),1,"") | EM76: =IF(AND(EM$74>=FC76,EM$74<=FD76),1,"") | EN76: =IF(AND(EN$74>=FC76,EN$74<=FD76),1,"") | EO76: =IF(AND(EO$74>=FC76,EO$74<=FD76),1,"") | EP76: =IF(AND(EP$74>=FC76,EP$74<=FD76),1,"") | EQ76: =IF(AND(EQ$74>=FC76,EQ$74<=FD76),1,"") | ER76: =IF(AND(ER$74>=FC76,ER$74<=FD76),1,"") | ES76: =IF(AND(ES$74>=FC76,ES$74<=FD76),1,"") | ET76: =IF(AND(ET$74>=FC76,ET$74<=FD76),1,"") | EU76: =IF(AND(EU$74>=FC76,EU$74<=FD76),1,"") | EV76: =IF(AND(EV$74>=FC76,EV$74<=FD76),1,"") | EW76: =IF(AND(EW$74>=FC76,EW$74<=FD76),1,"") | EX76: =IF(AND(EX$74>=FC76,EX$74<=FD76),1,"") | EY76: =IF(AND(EY$74>=FC76,EY$74<=FD76),1,"") | EZ76: =IF(AND(EZ$74>=FC76,EZ$74<=FD76),1,"") | FA76: =IF(AND(FA$74>=FC76,FA$74<=FD76),1,"") | FB76: =IF(AND(FB$74>=FC76,FB$74<=FD76),1,"") | FC76: ='06_Presupuesto'!F343-'02_Rendimientos'!$B$79+1 -> 1 | FD76: ='06_Presupuesto'!G343-'02_Rendimientos'!$B$79+1 -> 6 | FE76: ='06_Presupuesto'!E343 -> 0.011103669
B77: ='03_CPM_Obra_Gruesa'!B146 -> 1.2 | C77: ='02_Rendimientos'!C7 -> Replanteo y nivelación del área de trabajo | D77: ='02_Rendimientos'!E7 -> m2 | E77: ='02_Rendimientos'!D7 -> 180 | F77: =IFERROR(G77/E77,0) -> 6482.4375 | G77: ='06_Presupuesto'!D344*(1+'02_Rendimientos'!B82) -> 1166838.8 | H77: ='02_Rendimientos'!K7 -> 5 | I77: =IF(AND(I$74>=FC77,I$74<=FD77),1,"") | J77: =IF(AND(J$74>=FC77,J$74<=FD77),1,"") | K77: =IF(AND(K$74>=FC77,K$74<=FD77),1,"") | L77: =IF(AND(L$74>=FC77,L$74<=FD77),1,"") | M77: =IF(AND(M$74>=FC77,M$74<=FD77),1,"") | N77: =IF(AND(N$74>=FC77,N$74<=FD77),1,"") | O77: =IF(AND(O$74>=FC77,O$74<=FD77),1,"") -> 1 | P77: =IF(AND(P$74>=FC77,P$74<=FD77),1,"") -> 1 | Q77: =IF(AND(Q$74>=FC77,Q$74<=FD77),1,"") -> 1 | R77: =IF(AND(R$74>=FC77,R$74<=FD77),1,"") -> 1 | S77: =IF(AND(S$74>=FC77,S$74<=FD77),1,"") -> 1 | T77: =IF(AND(T$74>=FC77,T$74<=FD77),1,"") | U77: =IF(AND(U$74>=FC77,U$74<=FD77),1,"") | V77: =IF(AND(V$74>=FC77,V$74<=FD77),1,"") | W77: =IF(AND(W$74>=FC77,W$74<=FD77),1,"") | X77: =IF(AND(X$74>=FC77,X$74<=FD77),1,"") | Y77: =IF(AND(Y$74>=FC77,Y$74<=FD77),1,"") | Z77: =IF(AND(Z$74>=FC77,Z$74<=FD77),1,"") | AA77: =IF(AND(AA$74>=FC77,AA$74<=FD77),1,"") | AB77: =IF(AND(AB$74>=FC77,AB$74<=FD77),1,"") | AC77: =IF(AND(AC$74>=FC77,AC$74<=FD77),1,"") | AD77: =IF(AND(AD$74>=FC77,AD$74<=FD77),1,"") | AE77: =IF(AND(AE$74>=FC77,AE$74<=FD77),1,"") | AF77: =IF(AND(AF$74>=FC77,AF$74<=FD77),1,"") | AG77: =IF(AND(AG$74>=FC77,AG$74<=FD77),1,"") | AH77: =IF(AND(AH$74>=FC77,AH$74<=FD77),1,"") | AI77: =IF(AND(AI$74>=FC77,AI$74<=FD77),1,"") | AJ77: =IF(AND(AJ$74>=FC77,AJ$74<=FD77),1,"") | AK77: =IF(AND(AK$74>=FC77,AK$74<=FD77),1,"") | AL77: =IF(AND(AL$74>=FC77,AL$74<=FD77),1,"") | AM77: =IF(AND(AM$74>=FC77,AM$74<=FD77),1,"") | AN77: =IF(AND(AN$74>=FC77,AN$74<=FD77),1,"") | AO77: =IF(AND(AO$74>=FC77,AO$74<=FD77),1,"") | AP77: =IF(AND(AP$74>=FC77,AP$74<=FD77),1,"") | AQ77: =IF(AND(AQ$74>=FC77,AQ$74<=FD77),1,"") | AR77: =IF(AND(AR$74>=FC77,AR$74<=FD77),1,"") | AS77: =IF(AND(AS$74>=FC77,AS$74<=FD77),1,"") | AT77: =IF(AND(AT$74>=FC77,AT$74<=FD77),1,"") | AU77: =IF(AND(AU$74>=FC77,AU$74<=FD77),1,"") | AV77: =IF(AND(AV$74>=FC77,AV$74<=FD77),1,"") | AW77: =IF(AND(AW$74>=FC77,AW$74<=FD77),1,"") | AX77: =IF(AND(AX$74>=FC77,AX$74<=FD77),1,"") | AY77: =IF(AND(AY$74>=FC77,AY$74<=FD77),1,"") | AZ77: =IF(AND(AZ$74>=FC77,AZ$74<=FD77),1,"") | BA77: =IF(AND(BA$74>=FC77,BA$74<=FD77),1,"") | BB77: =IF(AND(BB$74>=FC77,BB$74<=FD77),1,"") | BC77: =IF(AND(BC$74>=FC77,BC$74<=FD77),1,"") | BD77: =IF(AND(BD$74>=FC77,BD$74<=FD77),1,"") | BE77: =IF(AND(BE$74>=FC77,BE$74<=FD77),1,"") | BF77: =IF(AND(BF$74>=FC77,BF$74<=FD77),1,"") | BG77: =IF(AND(BG$74>=FC77,BG$74<=FD77),1,"") | BH77: =IF(AND(BH$74>=FC77,BH$74<=FD77),1,"") | BI77: =IF(AND(BI$74>=FC77,BI$74<=FD77),1,"") | BJ77: =IF(AND(BJ$74>=FC77,BJ$74<=FD77),1,"") | BK77: =IF(AND(BK$74>=FC77,BK$74<=FD77),1,"") | BL77: =IF(AND(BL$74>=FC77,BL$74<=FD77),1,"") | BM77: =IF(AND(BM$74>=FC77,BM$74<=FD77),1,"") | BN77: =IF(AND(BN$74>=FC77,BN$74<=FD77),1,"") | BO77: =IF(AND(BO$74>=FC77,BO$74<=FD77),1,"") | BP77: =IF(AND(BP$74>=FC77,BP$74<=FD77),1,"") | BQ77: =IF(AND(BQ$74>=FC77,BQ$74<=FD77),1,"") | BR77: =IF(AND(BR$74>=FC77,BR$74<=FD77),1,"") | BS77: =IF(AND(BS$74>=FC77,BS$74<=FD77),1,"") | BT77: =IF(AND(BT$74>=FC77,BT$74<=FD77),1,"") | BU77: =IF(AND(BU$74>=FC77,BU$74<=FD77),1,"") | BV77: =IF(AND(BV$74>=FC77,BV$74<=FD77),1,"") | BW77: =IF(AND(BW$74>=FC77,BW$74<=FD77),1,"") | BX77: =IF(AND(BX$74>=FC77,BX$74<=FD77),1,"") | BY77: =IF(AND(BY$74>=FC77,BY$74<=FD77),1,"") | BZ77: =IF(AND(BZ$74>=FC77,BZ$74<=FD77),1,"") | CA77: =IF(AND(CA$74>=FC77,CA$74<=FD77),1,"") | CB77: =IF(AND(CB$74>=FC77,CB$74<=FD77),1,"") | CC77: =IF(AND(CC$74>=FC77,CC$74<=FD77),1,"") | CD77: =IF(AND(CD$74>=FC77,CD$74<=FD77),1,"") | CE77: =IF(AND(CE$74>=FC77,CE$74<=FD77),1,"") | CF77: =IF(AND(CF$74>=FC77,CF$74<=FD77),1,"") | CG77: =IF(AND(CG$74>=FC77,CG$74<=FD77),1,"") | CH77: =IF(AND(CH$74>=FC77,CH$74<=FD77),1,"") | CI77: =IF(AND(CI$74>=FC77,CI$74<=FD77),1,"") | CJ77: =IF(AND(CJ$74>=FC77,CJ$74<=FD77),1,"") | CK77: =IF(AND(CK$74>=FC77,CK$74<=FD77),1,"") | CL77: =IF(AND(CL$74>=FC77,CL$74<=FD77),1,"") | CM77: =IF(AND(CM$74>=FC77,CM$74<=FD77),1,"") | CN77: =IF(AND(CN$74>=FC77,CN$74<=FD77),1,"") | CO77: =IF(AND(CO$74>=FC77,CO$74<=FD77),1,"") | CP77: =IF(AND(CP$74>=FC77,CP$74<=FD77),1,"") | CQ77: =IF(AND(CQ$74>=FC77,CQ$74<=FD77),1,"") | CR77: =IF(AND(CR$74>=FC77,CR$74<=FD77),1,"") | CS77: =IF(AND(CS$74>=FC77,CS$74<=FD77),1,"") | CT77: =IF(AND(CT$74>=FC77,CT$74<=FD77),1,"") | CU77: =IF(AND(CU$74>=FC77,CU$74<=FD77),1,"") | CV77: =IF(AND(CV$74>=FC77,CV$74<=FD77),1,"") | CW77: =IF(AND(CW$74>=FC77,CW$74<=FD77),1,"") | CX77: =IF(AND(CX$74>=FC77,CX$74<=FD77),1,"") | CY77: =IF(AND(CY$74>=FC77,CY$74<=FD77),1,"") | CZ77: =IF(AND(CZ$74>=FC77,CZ$74<=FD77),1,"") | DA77: =IF(AND(DA$74>=FC77,DA$74<=FD77),1,"") | DB77: =IF(AND(DB$74>=FC77,DB$74<=FD77),1,"") | DC77: =IF(AND(DC$74>=FC77,DC$74<=FD77),1,"") | DD77: =IF(AND(DD$74>=FC77,DD$74<=FD77),1,"") | DE77: =IF(AND(DE$74>=FC77,DE$74<=FD77),1,"") | DF77: =IF(AND(DF$74>=FC77,DF$74<=FD77),1,"") | DG77: =IF(AND(DG$74>=FC77,DG$74<=FD77),1,"") | DH77: =IF(AND(DH$74>=FC77,DH$74<=FD77),1,"") | DI77: =IF(AND(DI$74>=FC77,DI$74<=FD77),1,"") | DJ77: =IF(AND(DJ$74>=FC77,DJ$74<=FD77),1,"") | DK77: =IF(AND(DK$74>=FC77,DK$74<=FD77),1,"") | DL77: =IF(AND(DL$74>=FC77,DL$74<=FD77),1,"") | DM77: =IF(AND(DM$74>=FC77,DM$74<=FD77),1,"") | DN77: =IF(AND(DN$74>=FC77,DN$74<=FD77),1,"") | DO77: =IF(AND(DO$74>=FC77,DO$74<=FD77),1,"") | DP77: =IF(AND(DP$74>=FC77,DP$74<=FD77),1,"") | DQ77: =IF(AND(DQ$74>=FC77,DQ$74<=FD77),1,"") | DR77: =IF(AND(DR$74>=FC77,DR$74<=FD77),1,"") | DS77: =IF(AND(DS$74>=FC77,DS$74<=FD77),1,"") | DT77: =IF(AND(DT$74>=FC77,DT$74<=FD77),1,"") | DU77: =IF(AND(DU$74>=FC77,DU$74<=FD77),1,"") | DV77: =IF(AND(DV$74>=FC77,DV$74<=FD77),1,"") | DW77: =IF(AND(DW$74>=FC77,DW$74<=FD77),1,"") | DX77: =IF(AND(DX$74>=FC77,DX$74<=FD77),1,"") | DY77: =IF(AND(DY$74>=FC77,DY$74<=FD77),1,"") | DZ77: =IF(AND(DZ$74>=FC77,DZ$74<=FD77),1,"") | EA77: =IF(AND(EA$74>=FC77,EA$74<=FD77),1,"") | EB77: =IF(AND(EB$74>=FC77,EB$74<=FD77),1,"") | EC77: =IF(AND(EC$74>=FC77,EC$74<=FD77),1,"") | ED77: =IF(AND(ED$74>=FC77,ED$74<=FD77),1,"") | EE77: =IF(AND(EE$74>=FC77,EE$74<=FD77),1,"") | EF77: =IF(AND(EF$74>=FC77,EF$74<=FD77),1,"") | EG77: =IF(AND(EG$74>=FC77,EG$74<=FD77),1,"") | EH77: =IF(AND(EH$74>=FC77,EH$74<=FD77),1,"") | EI77: =IF(AND(EI$74>=FC77,EI$74<=FD77),1,"") | EJ77: =IF(AND(EJ$74>=FC77,EJ$74<=FD77),1,"") | EK77: =IF(AND(EK$74>=FC77,EK$74<=FD77),1,"") | EL77: =IF(AND(EL$74>=FC77,EL$74<=FD77),1,"") | EM77: =IF(AND(EM$74>=FC77,EM$74<=FD77),1,"") | EN77: =IF(AND(EN$74>=FC77,EN$74<=FD77),1,"") | EO77: =IF(AND(EO$74>=FC77,EO$74<=FD77),1,"") | EP77: =IF(AND(EP$74>=FC77,EP$74<=FD77),1,"") | EQ77: =IF(AND(EQ$74>=FC77,EQ$74<=FD77),1,"") | ER77: =IF(AND(ER$74>=FC77,ER$74<=FD77),1,"") | ES77: =IF(AND(ES$74>=FC77,ES$74<=FD77),1,"") | ET77: =IF(AND(ET$74>=FC77,ET$74<=FD77),1,"") | EU77: =IF(AND(EU$74>=FC77,EU$74<=FD77),1,"") | EV77: =IF(AND(EV$74>=FC77,EV$74<=FD77),1,"") | EW77: =IF(AND(EW$74>=FC77,EW$74<=FD77),1,"") | EX77: =IF(AND(EX$74>=FC77,EX$74<=FD77),1,"") | EY77: =IF(AND(EY$74>=FC77,EY$74<=FD77),1,"") | EZ77: =IF(AND(EZ$74>=FC77,EZ$74<=FD77),1,"") | FA77: =IF(AND(FA$74>=FC77,FA$74<=FD77),1,"") | FB77: =IF(AND(FB$74>=FC77,FB$74<=FD77),1,"") | FC77: ='06_Presupuesto'!F344-'02_Rendimientos'!$B$79+1 -> 7 | FD77: ='06_Presupuesto'!G344-'02_Rendimientos'!$B$79+1 -> 11 | FE77: ='06_Presupuesto'!E344 -> 0.011103669
B78: ='03_CPM_Obra_Gruesa'!B147 -> 1.3 | C78: ='02_Rendimientos'!C8 -> Servicios provisorios y habilitación de instalaciones | D78: ='02_Rendimientos'!E8 -> lote | E78: ='02_Rendimientos'!D8 -> 1 | F78: =IFERROR(G78/E78,0) -> 0 | G78: ='06_Presupuesto'!D345*(1+'02_Rendimientos'!B82) -> 0 | H78: ='02_Rendimientos'!K8 -> 10 | I78: =IF(AND(I$74>=FC78,I$74<=FD78),1,"") | J78: =IF(AND(J$74>=FC78,J$74<=FD78),1,"") | K78: =IF(AND(K$74>=FC78,K$74<=FD78),1,"") | L78: =IF(AND(L$74>=FC78,L$74<=FD78),1,"") | M78: =IF(AND(M$74>=FC78,M$74<=FD78),1,"") | N78: =IF(AND(N$74>=FC78,N$74<=FD78),1,"") | O78: =IF(AND(O$74>=FC78,O$74<=FD78),1,"") -> 1 | P78: =IF(AND(P$74>=FC78,P$74<=FD78),1,"") -> 1 | Q78: =IF(AND(Q$74>=FC78,Q$74<=FD78),1,"") -> 1 | R78: =IF(AND(R$74>=FC78,R$74<=FD78),1,"") -> 1 | S78: =IF(AND(S$74>=FC78,S$74<=FD78),1,"") -> 1 | T78: =IF(AND(T$74>=FC78,T$74<=FD78),1,"") -> 1 | U78: =IF(AND(U$74>=FC78,U$74<=FD78),1,"") -> 1 | V78: =IF(AND(V$74>=FC78,V$74<=FD78),1,"") -> 1 | W78: =IF(AND(W$74>=FC78,W$74<=FD78),1,"") -> 1 | X78: =IF(AND(X$74>=FC78,X$74<=FD78),1,"") -> 1 | Y78: =IF(AND(Y$74>=FC78,Y$74<=FD78),1,"") | Z78: =IF(AND(Z$74>=FC78,Z$74<=FD78),1,"") | AA78: =IF(AND(AA$74>=FC78,AA$74<=FD78),1,"") | AB78: =IF(AND(AB$74>=FC78,AB$74<=FD78),1,"") | AC78: =IF(AND(AC$74>=FC78,AC$74<=FD78),1,"") | AD78: =IF(AND(AD$74>=FC78,AD$74<=FD78),1,"") | AE78: =IF(AND(AE$74>=FC78,AE$74<=FD78),1,"") | AF78: =IF(AND(AF$74>=FC78,AF$74<=FD78),1,"") | AG78: =IF(AND(AG$74>=FC78,AG$74<=FD78),1,"") | AH78: =IF(AND(AH$74>=FC78,AH$74<=FD78),1,"") | AI78: =IF(AND(AI$74>=FC78,AI$74<=FD78),1,"") | AJ78: =IF(AND(AJ$74>=FC78,AJ$74<=FD78),1,"") | AK78: =IF(AND(AK$74>=FC78,AK$74<=FD78),1,"") | AL78: =IF(AND(AL$74>=FC78,AL$74<=FD78),1,"") | AM78: =IF(AND(AM$74>=FC78,AM$74<=FD78),1,"") | AN78: =IF(AND(AN$74>=FC78,AN$74<=FD78),1,"") | AO78: =IF(AND(AO$74>=FC78,AO$74<=FD78),1,"") | AP78: =IF(AND(AP$74>=FC78,AP$74<=FD78),1,"") | AQ78: =IF(AND(AQ$74>=FC78,AQ$74<=FD78),1,"") | AR78: =IF(AND(AR$74>=FC78,AR$74<=FD78),1,"") | AS78: =IF(AND(AS$74>=FC78,AS$74<=FD78),1,"") | AT78: =IF(AND(AT$74>=FC78,AT$74<=FD78),1,"") | AU78: =IF(AND(AU$74>=FC78,AU$74<=FD78),1,"") | AV78: =IF(AND(AV$74>=FC78,AV$74<=FD78),1,"") | AW78: =IF(AND(AW$74>=FC78,AW$74<=FD78),1,"") | AX78: =IF(AND(AX$74>=FC78,AX$74<=FD78),1,"") | AY78: =IF(AND(AY$74>=FC78,AY$74<=FD78),1,"") | AZ78: =IF(AND(AZ$74>=FC78,AZ$74<=FD78),1,"") | BA78: =IF(AND(BA$74>=FC78,BA$74<=FD78),1,"") | BB78: =IF(AND(BB$74>=FC78,BB$74<=FD78),1,"") | BC78: =IF(AND(BC$74>=FC78,BC$74<=FD78),1,"") | BD78: =IF(AND(BD$74>=FC78,BD$74<=FD78),1,"") | BE78: =IF(AND(BE$74>=FC78,BE$74<=FD78),1,"") | BF78: =IF(AND(BF$74>=FC78,BF$74<=FD78),1,"") | BG78: =IF(AND(BG$74>=FC78,BG$74<=FD78),1,"") | BH78: =IF(AND(BH$74>=FC78,BH$74<=FD78),1,"") | BI78: =IF(AND(BI$74>=FC78,BI$74<=FD78),1,"") | BJ78: =IF(AND(BJ$74>=FC78,BJ$74<=FD78),1,"") | BK78: =IF(AND(BK$74>=FC78,BK$74<=FD78),1,"") | BL78: =IF(AND(BL$74>=FC78,BL$74<=FD78),1,"") | BM78: =IF(AND(BM$74>=FC78,BM$74<=FD78),1,"") | BN78: =IF(AND(BN$74>=FC78,BN$74<=FD78),1,"") | BO78: =IF(AND(BO$74>=FC78,BO$74<=FD78),1,"") | BP78: =IF(AND(BP$74>=FC78,BP$74<=FD78),1,"") | BQ78: =IF(AND(BQ$74>=FC78,BQ$74<=FD78),1,"") | BR78: =IF(AND(BR$74>=FC78,BR$74<=FD78),1,"") | BS78: =IF(AND(BS$74>=FC78,BS$74<=FD78),1,"") | BT78: =IF(AND(BT$74>=FC78,BT$74<=FD78),1,"") | BU78: =IF(AND(BU$74>=FC78,BU$74<=FD78),1,"") | BV78: =IF(AND(BV$74>=FC78,BV$74<=FD78),1,"") | BW78: =IF(AND(BW$74>=FC78,BW$74<=FD78),1,"") | BX78: =IF(AND(BX$74>=FC78,BX$74<=FD78),1,"") | BY78: =IF(AND(BY$74>=FC78,BY$74<=FD78),1,"") | BZ78: =IF(AND(BZ$74>=FC78,BZ$74<=FD78),1,"") | CA78: =IF(AND(CA$74>=FC78,CA$74<=FD78),1,"") | CB78: =IF(AND(CB$74>=FC78,CB$74<=FD78),1,"") | CC78: =IF(AND(CC$74>=FC78,CC$74<=FD78),1,"") | CD78: =IF(AND(CD$74>=FC78,CD$74<=FD78),1,"") | CE78: =IF(AND(CE$74>=FC78,CE$74<=FD78),1,"") | CF78: =IF(AND(CF$74>=FC78,CF$74<=FD78),1,"") | CG78: =IF(AND(CG$74>=FC78,CG$74<=FD78),1,"") | CH78: =IF(AND(CH$74>=FC78,CH$74<=FD78),1,"") | CI78: =IF(AND(CI$74>=FC78,CI$74<=FD78),1,"") | CJ78: =IF(AND(CJ$74>=FC78,CJ$74<=FD78),1,"") | CK78: =IF(AND(CK$74>=FC78,CK$74<=FD78),1,"") | CL78: =IF(AND(CL$74>=FC78,CL$74<=FD78),1,"") | CM78: =IF(AND(CM$74>=FC78,CM$74<=FD78),1,"") | CN78: =IF(AND(CN$74>=FC78,CN$74<=FD78),1,"") | CO78: =IF(AND(CO$74>=FC78,CO$74<=FD78),1,"") | CP78: =IF(AND(CP$74>=FC78,CP$74<=FD78),1,"") | CQ78: =IF(AND(CQ$74>=FC78,CQ$74<=FD78),1,"") | CR78: =IF(AND(CR$74>=FC78,CR$74<=FD78),1,"") | CS78: =IF(AND(CS$74>=FC78,CS$74<=FD78),1,"") | CT78: =IF(AND(CT$74>=FC78,CT$74<=FD78),1,"") | CU78: =IF(AND(CU$74>=FC78,CU$74<=FD78),1,"") | CV78: =IF(AND(CV$74>=FC78,CV$74<=FD78),1,"") | CW78: =IF(AND(CW$74>=FC78,CW$74<=FD78),1,"") | CX78: =IF(AND(CX$74>=FC78,CX$74<=FD78),1,"") | CY78: =IF(AND(CY$74>=FC78,CY$74<=FD78),1,"") | CZ78: =IF(AND(CZ$74>=FC78,CZ$74<=FD78),1,"") | DA78: =IF(AND(DA$74>=FC78,DA$74<=FD78),1,"") | DB78: =IF(AND(DB$74>=FC78,DB$74<=FD78),1,"") | DC78: =IF(AND(DC$74>=FC78,DC$74<=FD78),1,"") | DD78: =IF(AND(DD$74>=FC78,DD$74<=FD78),1,"") | DE78: =IF(AND(DE$74>=FC78,DE$74<=FD78),1,"") | DF78: =IF(AND(DF$74>=FC78,DF$74<=FD78),1,"") | DG78: =IF(AND(DG$74>=FC78,DG$74<=FD78),1,"") | DH78: =IF(AND(DH$74>=FC78,DH$74<=FD78),1,"") | DI78: =IF(AND(DI$74>=FC78,DI$74<=FD78),1,"") | DJ78: =IF(AND(DJ$74>=FC78,DJ$74<=FD78),1,"") | DK78: =IF(AND(DK$74>=FC78,DK$74<=FD78),1,"") | DL78: =IF(AND(DL$74>=FC78,DL$74<=FD78),1,"") | DM78: =IF(AND(DM$74>=FC78,DM$74<=FD78),1,"") | DN78: =IF(AND(DN$74>=FC78,DN$74<=FD78),1,"") | DO78: =IF(AND(DO$74>=FC78,DO$74<=FD78),1,"") | DP78: =IF(AND(DP$74>=FC78,DP$74<=FD78),1,"") | DQ78: =IF(AND(DQ$74>=FC78,DQ$74<=FD78),1,"") | DR78: =IF(AND(DR$74>=FC78,DR$74<=FD78),1,"") | DS78: =IF(AND(DS$74>=FC78,DS$74<=FD78),1,"") | DT78: =IF(AND(DT$74>=FC78,DT$74<=FD78),1,"") | DU78: =IF(AND(DU$74>=FC78,DU$74<=FD78),1,"") | DV78: =IF(AND(DV$74>=FC78,DV$74<=FD78),1,"") | DW78: =IF(AND(DW$74>=FC78,DW$74<=FD78),1,"") | DX78: =IF(AND(DX$74>=FC78,DX$74<=FD78),1,"") | DY78: =IF(AND(DY$74>=FC78,DY$74<=FD78),1,"") | DZ78: =IF(AND(DZ$74>=FC78,DZ$74<=FD78),1,"") | EA78: =IF(AND(EA$74>=FC78,EA$74<=FD78),1,"") | EB78: =IF(AND(EB$74>=FC78,EB$74<=FD78),1,"") | EC78: =IF(AND(EC$74>=FC78,EC$74<=FD78),1,"") | ED78: =IF(AND(ED$74>=FC78,ED$74<=FD78),1,"") | EE78: =IF(AND(EE$74>=FC78,EE$74<=FD78),1,"") | EF78: =IF(AND(EF$74>=FC78,EF$74<=FD78),1,"") | EG78: =IF(AND(EG$74>=FC78,EG$74<=FD78),1,"") | EH78: =IF(AND(EH$74>=FC78,EH$74<=FD78),1,"") | EI78: =IF(AND(EI$74>=FC78,EI$74<=FD78),1,"") | EJ78: =IF(AND(EJ$74>=FC78,EJ$74<=FD78),1,"") | EK78: =IF(AND(EK$74>=FC78,EK$74<=FD78),1,"") | EL78: =IF(AND(EL$74>=FC78,EL$74<=FD78),1,"") | EM78: =IF(AND(EM$74>=FC78,EM$74<=FD78),1,"") | EN78: =IF(AND(EN$74>=FC78,EN$74<=FD78),1,"") | EO78: =IF(AND(EO$74>=FC78,EO$74<=FD78),1,"") | EP78: =IF(AND(EP$74>=FC78,EP$74<=FD78),1,"") | EQ78: =IF(AND(EQ$74>=FC78,EQ$74<=FD78),1,"") | ER78: =IF(AND(ER$74>=FC78,ER$74<=FD78),1,"") | ES78: =IF(AND(ES$74>=FC78,ES$74<=FD78),1,"") | ET78: =IF(AND(ET$74>=FC78,ET$74<=FD78),1,"") | EU78: =IF(AND(EU$74>=FC78,EU$74<=FD78),1,"") | EV78: =IF(AND(EV$74>=FC78,EV$74<=FD78),1,"") | EW78: =IF(AND(EW$74>=FC78,EW$74<=FD78),1,"") | EX78: =IF(AND(EX$74>=FC78,EX$74<=FD78),1,"") | EY78: =IF(AND(EY$74>=FC78,EY$74<=FD78),1,"") | EZ78: =IF(AND(EZ$74>=FC78,EZ$74<=FD78),1,"") | FA78: =IF(AND(FA$74>=FC78,FA$74<=FD78),1,"") | FB78: =IF(AND(FB$74>=FC78,FB$74<=FD78),1,"") | FC78: ='06_Presupuesto'!F345-'02_Rendimientos'!$B$79+1 -> 7 | FD78: ='06_Presupuesto'!G345-'02_Rendimientos'!$B$79+1 -> 16 | FE78: ='06_Presupuesto'!E345 -> 0.022207339
B79: OBRA GRUESA
B80: ='03_CPM_Obra_Gruesa'!B148 -> 2.1 | C80: ='02_Rendimientos'!C9 -> Excavación y retiro de material | D80: ='02_Rendimientos'!E9 -> m3 | E80: ='02_Rendimientos'!D9 -> 45 | F80: =IFERROR(G80/E80,0) -> 17500 | G80: ='06_Presupuesto'!D346*(1+'02_Rendimientos'!B82) -> 787500 | H80: ='02_Rendimientos'!K9 -> 11 | I80: =IF(AND(I$74>=FC80,I$74<=FD80),1,"") | J80: =IF(AND(J$74>=FC80,J$74<=FD80),1,"") | K80: =IF(AND(K$74>=FC80,K$74<=FD80),1,"") | L80: =IF(AND(L$74>=FC80,L$74<=FD80),1,"") | M80: =IF(AND(M$74>=FC80,M$74<=FD80),1,"") | N80: =IF(AND(N$74>=FC80,N$74<=FD80),1,"") | O80: =IF(AND(O$74>=FC80,O$74<=FD80),1,"") | P80: =IF(AND(P$74>=FC80,P$74<=FD80),1,"") | Q80: =IF(AND(Q$74>=FC80,Q$74<=FD80),1,"") | R80: =IF(AND(R$74>=FC80,R$74<=FD80),1,"") | S80: =IF(AND(S$74>=FC80,S$74<=FD80),1,"") | T80: =IF(AND(T$74>=FC80,T$74<=FD80),1,"") -> 1 | U80: =IF(AND(U$74>=FC80,U$74<=FD80),1,"") -> 1 | V80: =IF(AND(V$74>=FC80,V$74<=FD80),1,"") -> 1 | W80: =IF(AND(W$74>=FC80,W$74<=FD80),1,"") -> 1 | X80: =IF(AND(X$74>=FC80,X$74<=FD80),1,"") -> 1 | Y80: =IF(AND(Y$74>=FC80,Y$74<=FD80),1,"") -> 1 | Z80: =IF(AND(Z$74>=FC80,Z$74<=FD80),1,"") -> 1 | AA80: =IF(AND(AA$74>=FC80,AA$74<=FD80),1,"") -> 1 | AB80: =IF(AND(AB$74>=FC80,AB$74<=FD80),1,"") -> 1 | AC80: =IF(AND(AC$74>=FC80,AC$74<=FD80),1,"") -> 1 | AD80: =IF(AND(AD$74>=FC80,AD$74<=FD80),1,"") -> 1 | AE80: =IF(AND(AE$74>=FC80,AE$74<=FD80),1,"") | AF80: =IF(AND(AF$74>=FC80,AF$74<=FD80),1,"") | AG80: =IF(AND(AG$74>=FC80,AG$74<=FD80),1,"") | AH80: =IF(AND(AH$74>=FC80,AH$74<=FD80),1,"") | AI80: =IF(AND(AI$74>=FC80,AI$74<=FD80),1,"") | AJ80: =IF(AND(AJ$74>=FC80,AJ$74<=FD80),1,"") | AK80: =IF(AND(AK$74>=FC80,AK$74<=FD80),1,"") | AL80: =IF(AND(AL$74>=FC80,AL$74<=FD80),1,"") | AM80: =IF(AND(AM$74>=FC80,AM$74<=FD80),1,"") | AN80: =IF(AND(AN$74>=FC80,AN$74<=FD80),1,"") | AO80: =IF(AND(AO$74>=FC80,AO$74<=FD80),1,"") | AP80: =IF(AND(AP$74>=FC80,AP$74<=FD80),1,"") | AQ80: =IF(AND(AQ$74>=FC80,AQ$74<=FD80),1,"") | AR80: =IF(AND(AR$74>=FC80,AR$74<=FD80),1,"") | AS80: =IF(AND(AS$74>=FC80,AS$74<=FD80),1,"") | AT80: =IF(AND(AT$74>=FC80,AT$74<=FD80),1,"") | AU80: =IF(AND(AU$74>=FC80,AU$74<=FD80),1,"") | AV80: =IF(AND(AV$74>=FC80,AV$74<=FD80),1,"") | AW80: =IF(AND(AW$74>=FC80,AW$74<=FD80),1,"") | AX80: =IF(AND(AX$74>=FC80,AX$74<=FD80),1,"") | AY80: =IF(AND(AY$74>=FC80,AY$74<=FD80),1,"") | AZ80: =IF(AND(AZ$74>=FC80,AZ$74<=FD80),1,"") | BA80: =IF(AND(BA$74>=FC80,BA$74<=FD80),1,"") | BB80: =IF(AND(BB$74>=FC80,BB$74<=FD80),1,"") | BC80: =IF(AND(BC$74>=FC80,BC$74<=FD80),1,"") | BD80: =IF(AND(BD$74>=FC80,BD$74<=FD80),1,"") | BE80: =IF(AND(BE$74>=FC80,BE$74<=FD80),1,"") | BF80: =IF(AND(BF$74>=FC80,BF$74<=FD80),1,"") | BG80: =IF(AND(BG$74>=FC80,BG$74<=FD80),1,"") | BH80: =IF(AND(BH$74>=FC80,BH$74<=FD80),1,"") | BI80: =IF(AND(BI$74>=FC80,BI$74<=FD80),1,"") | BJ80: =IF(AND(BJ$74>=FC80,BJ$74<=FD80),1,"") | BK80: =IF(AND(BK$74>=FC80,BK$74<=FD80),1,"") | BL80: =IF(AND(BL$74>=FC80,BL$74<=FD80),1,"") | BM80: =IF(AND(BM$74>=FC80,BM$74<=FD80),1,"") | BN80: =IF(AND(BN$74>=FC80,BN$74<=FD80),1,"") | BO80: =IF(AND(BO$74>=FC80,BO$74<=FD80),1,"") | BP80: =IF(AND(BP$74>=FC80,BP$74<=FD80),1,"") | BQ80: =IF(AND(BQ$74>=FC80,BQ$74<=FD80),1,"") | BR80: =IF(AND(BR$74>=FC80,BR$74<=FD80),1,"") | BS80: =IF(AND(BS$74>=FC80,BS$74<=FD80),1,"") | BT80: =IF(AND(BT$74>=FC80,BT$74<=FD80),1,"") | BU80: =IF(AND(BU$74>=FC80,BU$74<=FD80),1,"") | BV80: =IF(AND(BV$74>=FC80,BV$74<=FD80),1,"") | BW80: =IF(AND(BW$74>=FC80,BW$74<=FD80),1,"") | BX80: =IF(AND(BX$74>=FC80,BX$74<=FD80),1,"") | BY80: =IF(AND(BY$74>=FC80,BY$74<=FD80),1,"") | BZ80: =IF(AND(BZ$74>=FC80,BZ$74<=FD80),1,"") | CA80: =IF(AND(CA$74>=FC80,CA$74<=FD80),1,"") | CB80: =IF(AND(CB$74>=FC80,CB$74<=FD80),1,"") | CC80: =IF(AND(CC$74>=FC80,CC$74<=FD80),1,"") | CD80: =IF(AND(CD$74>=FC80,CD$74<=FD80),1,"") | CE80: =IF(AND(CE$74>=FC80,CE$74<=FD80),1,"") | CF80: =IF(AND(CF$74>=FC80,CF$74<=FD80),1,"") | CG80: =IF(AND(CG$74>=FC80,CG$74<=FD80),1,"") | CH80: =IF(AND(CH$74>=FC80,CH$74<=FD80),1,"") | CI80: =IF(AND(CI$74>=FC80,CI$74<=FD80),1,"") | CJ80: =IF(AND(CJ$74>=FC80,CJ$74<=FD80),1,"") | CK80: =IF(AND(CK$74>=FC80,CK$74<=FD80),1,"") | CL80: =IF(AND(CL$74>=FC80,CL$74<=FD80),1,"") | CM80: =IF(AND(CM$74>=FC80,CM$74<=FD80),1,"") | CN80: =IF(AND(CN$74>=FC80,CN$74<=FD80),1,"") | CO80: =IF(AND(CO$74>=FC80,CO$74<=FD80),1,"") | CP80: =IF(AND(CP$74>=FC80,CP$74<=FD80),1,"") | CQ80: =IF(AND(CQ$74>=FC80,CQ$74<=FD80),1,"") | CR80: =IF(AND(CR$74>=FC80,CR$74<=FD80),1,"") | CS80: =IF(AND(CS$74>=FC80,CS$74<=FD80),1,"") | CT80: =IF(AND(CT$74>=FC80,CT$74<=FD80),1,"") | CU80: =IF(AND(CU$74>=FC80,CU$74<=FD80),1,"") | CV80: =IF(AND(CV$74>=FC80,CV$74<=FD80),1,"") | CW80: =IF(AND(CW$74>=FC80,CW$74<=FD80),1,"") | CX80: =IF(AND(CX$74>=FC80,CX$74<=FD80),1,"") | CY80: =IF(AND(CY$74>=FC80,CY$74<=FD80),1,"") | CZ80: =IF(AND(CZ$74>=FC80,CZ$74<=FD80),1,"") | DA80: =IF(AND(DA$74>=FC80,DA$74<=FD80),1,"") | DB80: =IF(AND(DB$74>=FC80,DB$74<=FD80),1,"") | DC80: =IF(AND(DC$74>=FC80,DC$74<=FD80),1,"") | DD80: =IF(AND(DD$74>=FC80,DD$74<=FD80),1,"") | DE80: =IF(AND(DE$74>=FC80,DE$74<=FD80),1,"") | DF80: =IF(AND(DF$74>=FC80,DF$74<=FD80),1,"") | DG80: =IF(AND(DG$74>=FC80,DG$74<=FD80),1,"") | DH80: =IF(AND(DH$74>=FC80,DH$74<=FD80),1,"") | DI80: =IF(AND(DI$74>=FC80,DI$74<=FD80),1,"") | DJ80: =IF(AND(DJ$74>=FC80,DJ$74<=FD80),1,"") | DK80: =IF(AND(DK$74>=FC80,DK$74<=FD80),1,"") | DL80: =IF(AND(DL$74>=FC80,DL$74<=FD80),1,"") | DM80: =IF(AND(DM$74>=FC80,DM$74<=FD80),1,"") | DN80: =IF(AND(DN$74>=FC80,DN$74<=FD80),1,"") | DO80: =IF(AND(DO$74>=FC80,DO$74<=FD80),1,"") | DP80: =IF(AND(DP$74>=FC80,DP$74<=FD80),1,"") | DQ80: =IF(AND(DQ$74>=FC80,DQ$74<=FD80),1,"") | DR80: =IF(AND(DR$74>=FC80,DR$74<=FD80),1,"") | DS80: =IF(AND(DS$74>=FC80,DS$74<=FD80),1,"") | DT80: =IF(AND(DT$74>=FC80,DT$74<=FD80),1,"") | DU80: =IF(AND(DU$74>=FC80,DU$74<=FD80),1,"") | DV80: =IF(AND(DV$74>=FC80,DV$74<=FD80),1,"") | DW80: =IF(AND(DW$74>=FC80,DW$74<=FD80),1,"") | DX80: =IF(AND(DX$74>=FC80,DX$74<=FD80),1,"") | DY80: =IF(AND(DY$74>=FC80,DY$74<=FD80),1,"") | DZ80: =IF(AND(DZ$74>=FC80,DZ$74<=FD80),1,"") | EA80: =IF(AND(EA$74>=FC80,EA$74<=FD80),1,"") | EB80: =IF(AND(EB$74>=FC80,EB$74<=FD80),1,"") | EC80: =IF(AND(EC$74>=FC80,EC$74<=FD80),1,"") | ED80: =IF(AND(ED$74>=FC80,ED$74<=FD80),1,"") | EE80: =IF(AND(EE$74>=FC80,EE$74<=FD80),1,"") | EF80: =IF(AND(EF$74>=FC80,EF$74<=FD80),1,"") | EG80: =IF(AND(EG$74>=FC80,EG$74<=FD80),1,"") | EH80: =IF(AND(EH$74>=FC80,EH$74<=FD80),1,"") | EI80: =IF(AND(EI$74>=FC80,EI$74<=FD80),1,"") | EJ80: =IF(AND(EJ$74>=FC80,EJ$74<=FD80),1,"") | EK80: =IF(AND(EK$74>=FC80,EK$74<=FD80),1,"") | EL80: =IF(AND(EL$74>=FC80,EL$74<=FD80),1,"") | EM80: =IF(AND(EM$74>=FC80,EM$74<=FD80),1,"") | EN80: =IF(AND(EN$74>=FC80,EN$74<=FD80),1,"") | EO80: =IF(AND(EO$74>=FC80,EO$74<=FD80),1,"") | EP80: =IF(AND(EP$74>=FC80,EP$74<=FD80),1,"") | EQ80: =IF(AND(EQ$74>=FC80,EQ$74<=FD80),1,"") | ER80: =IF(AND(ER$74>=FC80,ER$74<=FD80),1,"") | ES80: =IF(AND(ES$74>=FC80,ES$74<=FD80),1,"") | ET80: =IF(AND(ET$74>=FC80,ET$74<=FD80),1,"") | EU80: =IF(AND(EU$74>=FC80,EU$74<=FD80),1,"") | EV80: =IF(AND(EV$74>=FC80,EV$74<=FD80),1,"") | EW80: =IF(AND(EW$74>=FC80,EW$74<=FD80),1,"") | EX80: =IF(AND(EX$74>=FC80,EX$74<=FD80),1,"") | EY80: =IF(AND(EY$74>=FC80,EY$74<=FD80),1,"") | EZ80: =IF(AND(EZ$74>=FC80,EZ$74<=FD80),1,"") | FA80: =IF(AND(FA$74>=FC80,FA$74<=FD80),1,"") | FB80: =IF(AND(FB$74>=FC80,FB$74<=FD80),1,"") | FC80: ='06_Presupuesto'!F346-'02_Rendimientos'!$B$79+1 -> 12 | FD80: ='06_Presupuesto'!G346-'02_Rendimientos'!$B$79+1 -> 22 | FE80: ='06_Presupuesto'!E346 -> 0.033311008
